Workbook

Sheet Dev Phase ->

Sheet Board Report (Dev) 
A1: PROJECT Budget
A2: CLR Silsbee PO LLC
A3: Application Period: 12.2024
A4: Requisition:
B6: Requisition Total | C6: Approved Budget | D6: $/RSF | E6: Payment To Date | F6: Balance To Pay | G6: % Paid | I6: Project NRSF
B7: LAND | C7: ='Budget to Actual P1'!G13 -> 0 | D7: =C7/$I$7 -> 0 | E7: ='Budget to Actual P1'!J13 -> 0 | F7: ='Budget to Actual P1'!L13 -> 0 | G7: =IF(ISERROR(E7/C7),0,E7/C7) -> 0 | I7: 222677
B8: SITEWORK | C8: ='Budget to Actual P1'!G18 -> 0 | D8: =C8/$I$7 -> 0 | E8: ='Budget to Actual P1'!J18 -> 0 | F8: ='Budget to Actual P1'!L18 -> 0 | G8: =IF(ISERROR(E8/C8),0,E8/C8) -> 0
B9: CONSTRUCTION - BASE | C9: ='Budget to Actual P1'!G28 -> 6379396.9 | D9: =C9/$I$7 -> 28.648657 | E9: ='Budget to Actual P1'!J28 -> 5467355.1 | F9: ='Budget to Actual P1'!L28 -> 912041.77 | G9: =IF(ISERROR(E9/C9),0,E9/C9) -> 0.85703323
B10: PERMITS AND FEES | C10: ='Budget to Actual P1'!G44 -> 0 | D10: =C10/$I$7 -> 0 | E10: ='Budget to Actual P1'!J44 -> 0 | F10: ='Budget to Actual P1'!L44 -> 0 | G10: =IF(ISERROR(E10/C10),0,E10/C10) -> 0
B11: DESIGN AND ENGINEERING CONSULTANTS | C11: ='Budget to Actual P1'!G67 -> 164385.7 | D11: =C11/$I$7 -> 0.73822487 | E11: ='Budget to Actual P1'!J67 -> 164385.7 | F11: ='Budget to Actual P1'!L67 -> 0 | G11: =IF(ISERROR(E11/C11),0,E11/C11) -> 1
B12: FINANCING | C12: ='Budget to Actual P1'!G92 -> 2586495.5 | D12: =C12/$I$7 -> 11.615459 | E12: ='Budget to Actual P1'!J92 -> 735654.03 | F12: ='Budget to Actual P1'!L92 -> 1850841.5 | G12: =IF(ISERROR(E12/C12),0,E12/C12) -> 0.28442115
B13: OTHER DEVELOPMENT COSTS | C13: ='Budget to Actual P1'!G113 -> 329018.68 | D13: =C13/$I$7 -> 1.4775602 | E13: ='Budget to Actual P1'!J113 -> 291272.48 | F13: ='Budget to Actual P1'!L113 -> 37746.205 | G13: =IF(ISERROR(E13/C13),0,E13/C13) -> 0.88527641
B14: LEASING AND MARKETING | C14: ='Budget to Actual P1'!G124 -> 1416100.7 | D14: =C14/$I$7 -> 6.3594386 | E14: ='Budget to Actual P1'!J124 -> 917186.84 | F14: ='Budget to Actual P1'!L124 -> 498913.86 | G14: =IF(ISERROR(E14/C14),0,E14/C14) -> 0.64768476
B15: TOTAL PROJECT COSTS | C15: =SUM(C7:C14) -> 10875398 | D15: =SUM(D7:D14) -> 48.839339 | E15: =SUM(E7:E14) -> 7575854.2 | F15: =SUM(F7:F14) -> 3299543.3 | G15: =E15/C15 -> 0.69660481
C16: ='Budget to Actual P1'!G126-C15 -> 0 | E16: =E15-'Budget to Actual P1'!J126 -> 0 | F16: =F15-'Budget to Actual P1'!L126 -> 0

Sheet Budget to Actual P1
H1: change date in line #9 | I1: change date in line #9 | J1: change date in line #9 | L1: 2026-07-31
B2: County Line Rail Silsbee LLC
B3: Budget to Actual
B4: 46234
D7: Silsbee PO | E7: Previous Contingency | F7: Current Contingency | G7: Silsbee PO | H7: Previous Application | I7: Payment this period | J7: Total Complete & Draw To Date | L7: Balance remaining
B8: GL Coding | C8: Account Name | D8: Approved Budget | E8: Funding & Reallocation | F8: Funding & Reallocation | G8: Current Approved Budget | H8: Inception to 06/30/2026 | I8: 7/31/2026 | J8: Incurred to 7/31/2026 | K8: Percent Drawn | L8: As of 7/31/2026
C10: Land Purchase | D10: 0 | E10: 0 | F10: 0 | G10: =+D10+E10+F10 -> 0 | H10: =SUMIF('Prior Invoice Log P1'!C:C,'Budget to Actual P1'!B10,'Prior Invoice Log P1'!G:G) -> 0 | I10: =SUMIF('Current Invoice Log P1'!C:C,'Budget to Actual P1'!B10,'Current Invoice Log P1'!G:G) -> 0 | J10: =SUM(H10,I10) -> 0 | K10: =J10/G10 -> #DIV/0! | L10: =+G10-J10 -> 0
B11: 11010 | C11: Acquisitions Costs (Land Purchase) | D11: 0 | E11: 0 | F11: 0 | G11: =+D11+E11+F11 -> 0 | H11: =SUMIF('Prior Invoice Log P1'!C:C,'Budget to Actual P1'!B11,'Prior Invoice Log P1'!G:G) -> 0 | I11: =SUMIF('Current Invoice Log P1'!C:C,'Budget to Actual P1'!B11,'Current Invoice Log P1'!G:G) -> 0 | J11: =SUM(H11:I11) -> 0 | K11: =J11/G11 -> #DIV/0! | L11: =+G11-J11 -> 0
C12: Other Land Costs | D12: 0 | E12: 0 | F12: 0 | G12: =+D12+E12+F12 -> 0 | H12: =SUMIF('Prior Invoice Log P1'!C:C,'Budget to Actual P1'!B12,'Prior Invoice Log P1'!G:G) -> 0 | I12: =SUMIF('Current Invoice Log P1'!C:C,'Budget to Actual P1'!B12,'Current Invoice Log P1'!G:G) -> 0 | J12: =SUM(H12,I12) -> 0 | K12: =J12/G12 -> #DIV/0! | L12: =+G12-J12 -> 0
C13: Total Land Cost | D13: =SUBTOTAL(9,D10:D12) -> 0 | E13: =SUBTOTAL(9,E10:E12) -> 0 | F13: =SUBTOTAL(9,F10:F12) -> 0 | G13: =SUBTOTAL(9,G10:G12) -> 0 | H13: =SUBTOTAL(9,H10:H12) -> 0 | I13: =SUBTOTAL(9,I10:I12) -> 0 | J13: =SUBTOTAL(9,J10:J12) -> 0 | K13: =J13/G13 -> #DIV/0! | L13: =SUBTOTAL(9,L10:L12) -> 0
C14: Demolition | D14: 0 | E14: 0 | F14: 0 | G14: =+D14+E14+F14 -> 0 | H14: =SUMIF('Prior Invoice Log P1'!C:C,'Budget to Actual P1'!B14,'Prior Invoice Log P1'!G:G) -> 0 | I14: =SUMIF('Current Invoice Log P1'!C:C,'Budget to Actual P1'!B14,'Current Invoice Log P1'!G:G) -> 0 | J14: =SUM(H14,I14) -> 0 | K14: =J14/G14 -> #DIV/0! | L14: =+G14-J14 -> 0
C15: Offsite Utilities | D15: 0 | E15: 0 | F15: 0 | G15: =+D15+E15+F15 -> 0 | H15: =SUMIF('Prior Invoice Log P1'!C:C,'Budget to Actual P1'!B15,'Prior Invoice Log P1'!G:G) -> 0 | I15: =SUMIF('Current Invoice Log P1'!C:C,'Budget to Actual P1'!B15,'Current Invoice Log P1'!G:G) -> 0 | J15: =SUM(H15,I15) -> 0 | K15: =J15/G15 -> #DIV/0! | L15: =+G15-J15 -> 0
C16: Site Work | D16: 0 | E16: 0 | F16: 0 | G16: =+D16+E16+F16 -> 0 | H16: =SUMIF('Prior Invoice Log P1'!C:C,'Budget to Actual P1'!B16,'Prior Invoice Log P1'!G:G) -> 0 | I16: =SUMIF('Current Invoice Log P1'!C:C,'Budget to Actual P1'!B16,'Current Invoice Log P1'!G:G) -> 0 | J16: =SUM(H16,I16) -> 0 | K16: =J16/G16 -> #DIV/0! | L16: =+G16-J16 -> 0
C17: Utilities Relocation | D17: 0 | E17: 0 | F17: 0 | G17: =+D17+E17+F17 -> 0 | H17: =SUMIF('Prior Invoice Log P1'!C:C,'Budget to Actual P1'!B17,'Prior Invoice Log P1'!G:G) -> 0 | I17: =SUMIF('Current Invoice Log P1'!C:C,'Budget to Actual P1'!B17,'Current Invoice Log P1'!G:G) -> 0 | J17: =SUM(H17,I17) -> 0 | K17: =J17/G17 -> #DIV/0! | L17: =+G17-J17 -> 0
C18: Total Site Work | D18: =SUBTOTAL(9,D14:D17) -> 0 | E18: =SUBTOTAL(9,E14:E17) -> 0 | F18: =SUBTOTAL(9,F14:F17) -> 0 | G18: =SUBTOTAL(9,G14:G17) -> 0 | H18: =SUBTOTAL(9,H14:H17) -> 0 | I18: =SUBTOTAL(9,I14:I17) -> 0 | J18: =SUBTOTAL(9,J14:J17) -> 0 | K18: =IFERROR(J18/G18,0) -> 0 | L18: =SUBTOTAL(9,L14:L17) -> 0
B19: 11230-1 | C19: Yard Stabilization | D19: 100000 | E19: 2678658.4 | F19: 0 | G19: =+D19+E19+F19 -> 2778658.4 | H19: =SUMIF('Prior Invoice Log P1'!C:C,'Budget to Actual P1'!B19,'Prior Invoice Log P1'!G:G) -> 2778658.4 | I19: =SUMIF('Current Invoice Log P1'!C:C,'Budget to Actual P1'!B19,'Current Invoice Log P1'!G:G) -> 0 | J19: =SUM(H19,I19) -> 2778658.4 | K19: =J19/G19 -> 1 | L19: =+G19-J19 -> 0
B20: 11230-2 | C20: Warehouse Improvements | D20: 814195 | E20: 336094.78 | F20: 0 | G20: =+D20+E20+F20 -> 1150289.8 | H20: =SUMIF('Prior Invoice Log P1'!C:C,'Budget to Actual P1'!B20,'Prior Invoice Log P1'!G:G) -> 1150289.8 | I20: =SUMIF('Current Invoice Log P1'!C:C,'Budget to Actual P1'!B20,'Current Invoice Log P1'!G:G) -> 0 | J20: =SUM(H20,I20) -> 1150289.8 | K20: =J20/G20 -> 1 | L20: =+G20-J20 -> 0
B21: 11230-3 | C21: Sprinkler Improvements | D21: 143563 | E21: 480944 | F21: 0 | G21: =+D21+E21+F21 -> 624507 | H21: =SUMIF('Prior Invoice Log P1'!C:C,'Budget to Actual P1'!B21,'Prior Invoice Log P1'!G:G) -> 537651.9 | I21: =SUMIF('Current Invoice Log P1'!C:C,'Budget to Actual P1'!B21,'Current Invoice Log P1'!G:G) -> 86855.1 | J21: =SUM(H21,I21) -> 624507 | K21: =J21/G21 -> 1 | L21: =+G21-J21 -> 0
B22: 11230-4 | C22: Roof Improvements | D22: 210385 | E22: 300 | F22: 0 | G22: =+D22+E22+F22 -> 210685 | H22: =SUMIF('Prior Invoice Log P1'!C:C,'Budget to Actual P1'!B22,'Prior Invoice Log P1'!G:G) -> 210685 | I22: =SUMIF('Current Invoice Log P1'!C:C,'Budget to Actual P1'!B22,'Current Invoice Log P1'!G:G) -> 0 | J22: =SUM(H22,I22) -> 210685 | K22: =J22/G22 -> 1 | L22: =+G22-J22 -> 0
B23: 11230-5 | C23: Electrical Improvements | D23: 222358 | E23: 79782.64 | F23: 0 | G23: =+D23+E23+F23 -> 302140.64 | H23: =SUMIF('Prior Invoice Log P1'!C:C,'Budget to Actual P1'!B23,'Prior Invoice Log P1'!G:G) -> 206823.46 | I23: =SUMIF('Current Invoice Log P1'!C:C,'Budget to Actual P1'!B23,'Current Invoice Log P1'!G:G) -> 95317.18 | J23: =SUM(H23,I23) -> 302140.64 | K23: =J23/G23 -> 1 | L23: =+G23-J23 -> 0
B24: 11230-6 | C24: Fencing | D24: 650000 | E24: 0 | F24: 0 | G24: =+D24+E24+F24 -> 650000 | H24: =SUMIF('Prior Invoice Log P1'!C:C,'Budget to Actual P1'!B24,'Prior Invoice Log P1'!G:G) -> 112500 | I24: =SUMIF('Current Invoice Log P1'!C:C,'Budget to Actual P1'!B24,'Current Invoice Log P1'!G:G) -> 0 | J24: =SUM(H24,I24) -> 112500 | K24: =J24/G24 -> 0.17307692 | L24: =+G24-J24 -> 537500
B25: 11230-7 | C25: Other Hard Costs | D25: 83393 | E25: 205181.29 | F25: 0 | G25: =+D25+E25+F25 -> 288574.29 | H25: =SUMIF('Prior Invoice Log P1'!C:C,'Budget to Actual P1'!B25,'Prior Invoice Log P1'!G:G) -> 288574.29 | I25: =SUMIF('Current Invoice Log P1'!C:C,'Budget to Actual P1'!B25,'Current Invoice Log P1'!G:G) -> 0 | J25: =SUM(H25,I25) -> 288574.29 | K25: =J25/G25 -> 1 | L25: =+G25-J25 -> 0
B26: 11216 | C26: Hard Cost Contingency | D26: 346282.8 | E26: -221655.29 | F26: 0 | G26: =+D26+E26+F26 -> 124627.51 | H26: =SUMIF('Prior Invoice Log P1'!C:C,'Budget to Actual P1'!B26,'Prior Invoice Log P1'!G:G) -> 0 | I26: =SUMIF('Current Invoice Log P1'!C:C,'Budget to Actual P1'!B26,'Current Invoice Log P1'!G:G) -> 0 | J26: =SUM(H26,I26) -> 0 | K26: =IFERROR(J26/G26,) -> 0 | L26: =+G26-J26 -> 124627.51
B27: 11217 | C27: Soft Cost Contingency | D27: 293570.38 | E27: -43656.12 | F27: 0 | G27: =+D27+E27+F27 -> 249914.26 | H27: =SUMIF('Prior Invoice Log P1'!C:C,'Budget to Actual P1'!B27,'Prior Invoice Log P1'!G:G) -> 0 | I27: =SUMIF('Current Invoice Log P1'!C:C,'Budget to Actual P1'!B27,'Current Invoice Log P1'!G:G) -> 0 | J27: =SUM(H27,I27) -> 0 | K27: =J27/G27 -> 0 | L27: =+G27-J27 -> 249914.26
C28: Construction Costs | D28: =SUBTOTAL(9,D19:D27) -> 2863747.2 | E28: 3515649.7 | F28: 0 | G28: =SUBTOTAL(9,G19:G27) -> 6379396.9 | H28: =SUBTOTAL(9,H19:H27) -> 5285182.9 | I28: =SUBTOTAL(9,I19:I27) -> 182172.28 | J28: =SUBTOTAL(9,J19:J27) -> 5467355.1 | K28: =J28/G28 -> 0.85703323 | L28: =SUBTOTAL(9,L19:L27) -> 912041.77
C29: Sanitary Charges | D29: 0 | E29: 0 | F29: 0 | G29: =+D29+E29+F29 -> 0 | H29: =SUMIF('Prior Invoice Log P1'!C:C,'Budget to Actual P1'!B29,'Prior Invoice Log P1'!G:G) -> 0 | I29: =SUMIF('Current Invoice Log P1'!C:C,'Budget to Actual P1'!B29,'Current Invoice Log P1'!G:G) -> 0 | J29: =SUM(H29,I29) -> 0 | K29: =IFERROR(J29/G29,0) -> 0 | L29: =+G29-J29 -> 0
C30: Water Charges | D30: 0 | E30: 0 | F30: 0 | G30: =+D30+E30+F30 -> 0 | H30: =SUMIF('Prior Invoice Log P1'!C:C,'Budget to Actual P1'!B30,'Prior Invoice Log P1'!G:G) -> 0 | I30: =SUMIF('Current Invoice Log P1'!C:C,'Budget to Actual P1'!B30,'Current Invoice Log P1'!G:G) -> 0 | J30: =SUM(H30,I30) -> 0 | K30: =IFERROR(J30/G30,0) -> 0 | L30: =+G30-J30 -> 0
C31: Building Permits | D31: 0 | E31: 0 | F31: 0 | G31: =+D31+E31+F31 -> 0 | H31: =SUMIF('Prior Invoice Log P1'!C:C,'Budget to Actual P1'!B31,'Prior Invoice Log P1'!G:G) -> 0 | I31: =SUMIF('Current Invoice Log P1'!C:C,'Budget to Actual P1'!B31,'Current Invoice Log P1'!G:G) -> 0 | J31: =SUM(H31,I31) -> 0 | K31: =IFERROR(J31/G31,0) -> 0 | L31: =+G31-J31 -> 0
C32: CO Fees | D32: 0 | E32: 0 | F32: 0 | G32: =+D32+E32+F32 -> 0 | H32: =SUMIF('Prior Invoice Log P1'!C:C,'Budget to Actual P1'!B32,'Prior Invoice Log P1'!G:G) -> 0 | I32: =SUMIF('Current Invoice Log P1'!C:C,'Budget to Actual P1'!B32,'Current Invoice Log P1'!G:G) -> 0 | J32: =SUM(H32,I32) -> 0 | K32: =IFERROR(J32/G32,0) -> 0 | L32: =+G32-J32 -> 0
C33: A&E Permit Fees | D33: 0 | E33: 0 | F33: 0 | G33: =+D33+E33+F33 -> 0 | H33: =SUMIF('Prior Invoice Log P1'!C:C,'Budget to Actual P1'!B33,'Prior Invoice Log P1'!G:G) -> 0 | I33: =SUMIF('Current Invoice Log P1'!C:C,'Budget to Actual P1'!B33,'Current Invoice Log P1'!G:G) -> 0 | J33: =SUM(H33,I33) -> 0 | K33: =IFERROR(J33/G33,0) -> 0 | L33: =+G33-J33 -> 0
C34: File & Review Fees | D34: 0 | E34: 0 | F34: 0 | G34: =+D34+E34+F34 -> 0 | H34: =SUMIF('Prior Invoice Log P1'!C:C,'Budget to Actual P1'!B34,'Prior Invoice Log P1'!G:G) -> 0 | I34: =SUMIF('Current Invoice Log P1'!C:C,'Budget to Actual P1'!B34,'Current Invoice Log P1'!G:G) -> 0 | J34: =SUM(H34,I34) -> 0 | K34: =IFERROR(J34/G34,0) -> 0 | L34: =+G34-J34 -> 0
C35: Tax Abatement | D35: 0 | E35: 0 | F35: 0 | G35: =+D35+E35+F35 -> 0 | H35: =SUMIF('Prior Invoice Log P1'!C:C,'Budget to Actual P1'!B35,'Prior Invoice Log P1'!G:G) -> 0 | I35: =SUMIF('Current Invoice Log P1'!C:C,'Budget to Actual P1'!B35,'Current Invoice Log P1'!G:G) -> 0 | J35: =SUM(H35,I35) -> 0 | K35: =IFERROR(J35/G35,0) -> 0 | L35: =+G35-J35 -> 0
C36: Zoning Variances Fees | D36: 0 | E36: 0 | F36: 0 | G36: =+D36+E36+F36 -> 0 | H36: =SUMIF('Prior Invoice Log P1'!C:C,'Budget to Actual P1'!B36,'Prior Invoice Log P1'!G:G) -> 0 | I36: =SUMIF('Current Invoice Log P1'!C:C,'Budget to Actual P1'!B36,'Current Invoice Log P1'!G:G) -> 0 | J36: =SUM(H36,I36) -> 0 | K36: =IFERROR(J36/G36,0) -> 0 | L36: =+G36-J36 -> 0
C37: Impact Fees - General | D37: 0 | E37: 0 | F37: 0 | G37: =+D37+E37+F37 -> 0 | H37: =SUMIF('Prior Invoice Log P1'!C:C,'Budget to Actual P1'!B37,'Prior Invoice Log P1'!G:G) -> 0 | I37: =SUMIF('Current Invoice Log P1'!C:C,'Budget to Actual P1'!B37,'Current Invoice Log P1'!G:G) -> 0 | J37: =SUM(H37,I37) -> 0 | K37: =IFERROR(J37/G37,0) -> 0 | L37: =+G37-J37 -> 0
C38: Impact Fees - Water | D38: 0 | E38: 0 | F38: 0 | G38: =+D38+E38+F38 -> 0 | H38: =SUMIF('Prior Invoice Log P1'!C:C,'Budget to Actual P1'!B38,'Prior Invoice Log P1'!G:G) -> 0 | I38: =SUMIF('Current Invoice Log P1'!C:C,'Budget to Actual P1'!B38,'Current Invoice Log P1'!G:G) -> 0 | J38: =SUM(H38,I38) -> 0 | K38: =IFERROR(J38/G38,0) -> 0 | L38: =+G38-J38 -> 0
C39: Impact Fees - Sewer | D39: 0 | E39: 0 | F39: 0 | G39: =+D39+E39+F39 -> 0 | H39: =SUMIF('Prior Invoice Log P1'!C:C,'Budget to Actual P1'!B39,'Prior Invoice Log P1'!G:G) -> 0 | I39: =SUMIF('Current Invoice Log P1'!C:C,'Budget to Actual P1'!B39,'Current Invoice Log P1'!G:G) -> 0 | J39: =SUM(H39,I39) -> 0 | K39: =IFERROR(J39/G39,0) -> 0 | L39: =+G39-J39 -> 0
C40: Impact Fees - Park | D40: 0 | E40: 0 | F40: 0 | G40: =+D40+E40+F40 -> 0 | H40: =SUMIF('Prior Invoice Log P1'!C:C,'Budget to Actual P1'!B40,'Prior Invoice Log P1'!G:G) -> 0 | I40: =SUMIF('Current Invoice Log P1'!C:C,'Budget to Actual P1'!B40,'Current Invoice Log P1'!G:G) -> 0 | J40: =SUM(H40,I40) -> 0 | K40: =IFERROR(J40/G40,0) -> 0 | L40: =+G40-J40 -> 0
... C43: Impact Fees - Other | D43: 0 | E43: 0 | F43: 0 | G43: =+D43+E43+F43 -> 0 | H43: =SUMIF('Prior Invoice Log P1'!C:C,'Budget to Actual P1'!B43,'Prior Invoice Log P1'!G:G) -> 0 | I43: =SUMIF('Current Invoice Log P1'!C:C,'Budget to Actual P1'!B43,'Current Invoice Log P1'!G:G) -> 0 | J43: =SUM(H43,I43) -> 0 | K43: =IFERROR(J43/G43,0) -> 0 | L43: =+G43-J43 -> 0
C44: Permits and Fees | D44: =SUBTOTAL(9,D29:D43) -> 0 | E44: =SUBTOTAL(9,E29:E43) -> 0 | F44: =SUBTOTAL(9,F29:F43) -> 0 | G44: =SUBTOTAL(9,G29:G43) -> 0 | H44: =SUBTOTAL(9,H29:H43) -> 0 | I44: =SUBTOTAL(9,I29:I43) -> 0 | J44: =SUBTOTAL(9,J29:J43) -> 0 | K44: =IFERROR(J44/G44,0) -> 0 | L44: =SUBTOTAL(9,L29:L43) -> 0
C45: Construction Management Fees | E45: 0 | F45: 0 | G45: =+D45+E45+F45 -> 0 | H45: =SUMIF('Prior Invoice Log P1'!C:C,'Budget to Actual P1'!B45,'Prior Invoice Log P1'!G:G) -> 0 | I45: =SUMIF('Current Invoice Log P1'!C:C,'Budget to Actual P1'!B45,'Current Invoice Log P1'!G:G) -> 0 | J45: =SUM(H45:I45) -> 0 | K45: =J45/G45 -> #DIV/0! | L45: =+G45-J45 -> 0
B46: 12115 | C46: A&E | D46: 53750 | E46: 34396.36 | F46: 0 | G46: =+D46+E46+F46 -> 88146.36 | H46: =SUMIF('Prior Invoice Log P1'!C:C,'Budget to Actual P1'!B46,'Prior Invoice Log P1'!G:G) -> 88146.36 | I46: =SUMIF('Current Invoice Log P1'!C:C,'Budget to Actual P1'!B46,'Current Invoice Log P1'!G:G) -> 0 | J46: =SUM(H46:I46) -> 88146.36 | K46: =J46/G46 -> 1 | L46: =+G46-J46 -> 0
B47: 12116 | C47: Environmental (incl. Enviro Insurance) | D47: 0 | E47: 0 | F47: 0 | G47: =+D47+E47+F47 -> 0 | H47: =SUMIF('Prior Invoice Log P1'!C:C,'Budget to Actual P1'!B47,'Prior Invoice Log P1'!G:G) -> 0 | I47: =SUMIF('Current Invoice Log P1'!C:C,'Budget to Actual P1'!B47,'Current Invoice Log P1'!G:G) -> 0 | J47: =SUM(H47:I47) -> 0 | K47: =J47/G47 -> #DIV/0! | L47: =+G47-J47 -> 0
B48: 11760 | C48: Other Due Diligence | D48: 0 | E48: 0 | F48: 0 | G48: =+D48+E48+F48 -> 0 | H48: =SUMIF('Prior Invoice Log P1'!C:C,'Budget to Actual P1'!B48,'Prior Invoice Log P1'!G:G) -> 0 | I48: =SUMIF('Current Invoice Log P1'!C:C,'Budget to Actual P1'!B48,'Current Invoice Log P1'!G:G) -> 0 | J48: =SUM(H48:I48) -> 0 | K48: =J48/G48 -> #DIV/0! | L48: =+G48-J48 -> 0
B49: 12013 | C49: Civil Engineering Plans | D49: 0 | E49: 0 | F49: 0 | G49: =+D49+E49+F49 -> 0 | H49: =SUMIF('Prior Invoice Log P1'!C:C,'Budget to Actual P1'!B49,'Prior Invoice Log P1'!G:G) -> 0 | I49: =SUMIF('Current Invoice Log P1'!C:C,'Budget to Actual P1'!B49,'Current Invoice Log P1'!G:G) -> 0 | J49: =SUM(H49:I49) -> 0 | K49: =J49/G49 -> #DIV/0! | L49: =+G49-J49 -> 0
B50: 12127 | C50: General Consultant | D50: 0 | E50: 0 | F50: 0 | G50: =+D50+E50+F50 -> 0 | H50: =SUMIF('Prior Invoice Log P1'!C:C,'Budget to Actual P1'!B50,'Prior Invoice Log P1'!G:G) -> 0 | I50: =SUMIF('Current Invoice Log P1'!C:C,'Budget to Actual P1'!B50,'Current Invoice Log P1'!G:G) -> 0 | J50: =SUM(H50:I50) -> 0 | K50: =J50/G50 -> #DIV/0! | L50: =+G50-J50 -> 0
C51: Accessibility Consultant | D51: 0 | E51: 0 | F51: 0 | G51: =+D51+E51+F51 -> 0 | H51: =SUMIF('Prior Invoice Log P1'!C:C,'Budget to Actual P1'!B51,'Prior Invoice Log P1'!G:G) -> 0 | I51: =SUMIF('Current Invoice Log P1'!C:C,'Budget to Actual P1'!B51,'Current Invoice Log P1'!G:G) -> 0 | J51: =SUM(H51:I51) -> 0 | K51: =J51/G51 -> #DIV/0! | L51: =+G51-J51 -> 0
C52: Pool Consultant | D52: 0 | E52: 0 | F52: 0 | G52: =+D52+E52+F52 -> 0 | H52: =SUMIF('Prior Invoice Log P1'!C:C,'Budget to Actual P1'!B52,'Prior Invoice Log P1'!G:G) -> 0 | I52: =SUMIF('Current Invoice Log P1'!C:C,'Budget to Actual P1'!B52,'Current Invoice Log P1'!G:G) -> 0 | J52: =SUM(H52:I52) -> 0 | K52: =J52/G52 -> #DIV/0! | L52: =+G52-J52 -> 0
C53: Moisture Consultant | D53: 0 | E53: 0 | F53: 0 | G53: =+D53+E53+F53 -> 0 | H53: =SUMIF('Prior Invoice Log P1'!C:C,'Budget to Actual P1'!B53,'Prior Invoice Log P1'!G:G) -> 0 | I53: =SUMIF('Current Invoice Log P1'!C:C,'Budget to Actual P1'!B53,'Current Invoice Log P1'!G:G) -> 0 | J53: =SUM(H53:I53) -> 0 | K53: =J53/G53 -> #DIV/0! | L53: =+G53-J53 -> 0
C54: Renderings & Models | D54: 0 | E54: 0 | F54: 0 | G54: =+D54+E54+F54 -> 0 | H54: =SUMIF('Prior Invoice Log P1'!C:C,'Budget to Actual P1'!B54,'Prior Invoice Log P1'!G:G) -> 0 | I54: =SUMIF('Current Invoice Log P1'!C:C,'Budget to Actual P1'!B54,'Current Invoice Log P1'!G:G) -> 0 | J54: =SUM(H54:I54) -> 0 | K54: =J54/G54 -> #DIV/0! | L54: =+G54-J54 -> 0
C55: Reproduction/Printing | D55: 0 | E55: 0 | F55: 0 | G55: =+D55+E55+F55 -> 0 | H55: =SUMIF('Prior Invoice Log P1'!C:C,'Budget to Actual P1'!B55,'Prior Invoice Log P1'!G:G) -> 0 | I55: =SUMIF('Current Invoice Log P1'!C:C,'Budget to Actual P1'!B55,'Current Invoice Log P1'!G:G) -> 0 | J55: =SUM(H55:I55) -> 0 | K55: =J55/G55 -> #DIV/0! | L55: =+G55-J55 -> 0
C56: Reimbursable | D56: 0 | E56: 0 | F56: 0 | G56: =+D56+E56+F56 -> 0 | H56: =SUMIF('Prior Invoice Log P1'!C:C,'Budget to Actual P1'!B56,'Prior Invoice Log P1'!G:G) -> 0 | I56: =SUMIF('Current Invoice Log P1'!C:C,'Budget to Actual P1'!B56,'Current Invoice Log P1'!G:G) -> 0 | J56: =SUM(H56:I56) -> 0 | K56: =J56/G56 -> #DIV/0! | L56: =+G56-J56 -> 0
C57: Revisions/Change Orders | D57: 0 | E57: 0 | F57: 0 | G57: =+D57+E57+F57 -> 0 | H57: =SUMIF('Prior Invoice Log P1'!C:C,'Budget to Actual P1'!B57,'Prior Invoice Log P1'!G:G) -> 0 | I57: =SUMIF('Current Invoice Log P1'!C:C,'Budget to Actual P1'!B57,'Current Invoice Log P1'!G:G) -> 0 | J57: =SUM(H57:I57) -> 0 | K57: =J57/G57 -> #DIV/0! | L57: =+G57-J57 -> 0
C58: Bidding, Negotiation & Admin Phase | D58: 0 | E58: 0 | F58: 0 | G58: =+D58+E58+F58 -> 0 | H58: =SUMIF('Prior Invoice Log P1'!C:C,'Budget to Actual P1'!B58,'Prior Invoice Log P1'!G:G) -> 0 | I58: =SUMIF('Current Invoice Log P1'!C:C,'Budget to Actual P1'!B58,'Current Invoice Log P1'!G:G) -> 0 | J58: =SUM(H58:I58) -> 0 | K58: =J58/G58 -> #DIV/0! | L58: =+G58-J58 -> 0
C59: Travel - Architectural and Design | D59: 0 | E59: 0 | F59: 0 | G59: =+D59+E59+F59 -> 0 | H59: =SUMIF('Prior Invoice Log P1'!C:C,'Budget to Actual P1'!B59,'Prior Invoice Log P1'!G:G) -> 0 | I59: =SUMIF('Current Invoice Log P1'!C:C,'Budget to Actual P1'!B59,'Current Invoice Log P1'!G:G) -> 0 | J59: =SUM(H59:I59) -> 0 | K59: =J59/G59 -> #DIV/0! | L59: =+G59-J59 -> 0
C60: Permits/Approval | D60: 0 | E60: 0 | F60: 0 | G60: =+D60+E60+F60 -> 0 | H60: =SUMIF('Prior Invoice Log P1'!C:C,'Budget to Actual P1'!B60,'Prior Invoice Log P1'!G:G) -> 0 | I60: =SUMIF('Current Invoice Log P1'!C:C,'Budget to Actual P1'!B60,'Current Invoice Log P1'!G:G) -> 0 | J60: =SUM(H60:I60) -> 0 | K60: 0 | L60: =+G60-J60 -> 0
C61: Postage & Delivery | D61: 0 | E61: 0 | F61: 0 | G61: =+D61+E61+F61 -> 0 | H61: =SUMIF('Prior Invoice Log P1'!C:C,'Budget to Actual P1'!B61,'Prior Invoice Log P1'!G:G) -> 0 | I61: =SUMIF('Current Invoice Log P1'!C:C,'Budget to Actual P1'!B61,'Current Invoice Log P1'!G:G) -> 0 | J61: =SUM(H61:I61) -> 0 | K61: =J61/G61 -> #DIV/0! | L61: =+G61-J61 -> 0
C62: Architectural % of Construction Costs | D62: 0 | E62: 0 | F62: 0 | G62: =+D62+E62+F62 -> 0 | H62: =SUMIF('Prior Invoice Log P1'!C:C,'Budget to Actual P1'!B62,'Prior Invoice Log P1'!G:G) -> 0 | I62: =SUMIF('Current Invoice Log P1'!C:C,'Budget to Actual P1'!B62,'Current Invoice Log P1'!G:G) -> 0 | J62: =SUM(H62:I62) -> 0 | K62: =J62/G62 -> #DIV/0! | L62: =+G62-J62 -> 0
C63: Corp Setup accounting | D63: 0 | E63: 0 | F63: 0 | G63: =+D63+E63+F63 -> 0 | H63: =SUMIF('Prior Invoice Log P1'!C:C,'Budget to Actual P1'!B63,'Prior Invoice Log P1'!G:G) -> 0 | I63: =SUMIF('Current Invoice Log P1'!C:C,'Budget to Actual P1'!B63,'Current Invoice Log P1'!G:G) -> 0 | J63: =SUM(H63:I63) -> 0 | K63: =J63/G63 -> #DIV/0! | L63: =+G63-J63 -> 0
C64: Tax Preparation accounting | D64: 0 | E64: 0 | F64: 0 | G64: =+D64+E64+F64 -> 0 | H64: =SUMIF('Prior Invoice Log P1'!C:C,'Budget to Actual P1'!B64,'Prior Invoice Log P1'!G:G) -> 0 | I64: =SUMIF('Current Invoice Log P1'!C:C,'Budget to Actual P1'!B64,'Current Invoice Log P1'!G:G) -> 0 | J64: =SUM(H64:I64) -> 0 | K64: =J64/G64 -> #DIV/0! | L64: =+G64-J64 -> 0
B65: 12230 | C65: Professional Services - Accounting | D65: 72000 | E65: 4239.34 | F65: 0 | G65: =+D65+E65+F65 -> 76239.34 | H65: =SUMIF('Prior Invoice Log P1'!C:C,'Budget to Actual P1'!B65,'Prior Invoice Log P1'!G:G) -> 69274.24 | I65: =SUMIF('Current Invoice Log P1'!C:C,'Budget to Actual P1'!B65,'Current Invoice Log P1'!G:G) -> 6965.1 | J65: =SUM(H65:I65) -> 76239.34 | K65: =J65/G65 -> 1 | L65: =+G65-J65 -> 0
C66: Other Accounting | D66: 0 | E66: 0 | F66: 0 | G66: =+D66+E66+F66 -> 0 | H66: =SUMIF('Prior Invoice Log P1'!C:C,'Budget to Actual P1'!B66,'Prior Invoice Log P1'!G:G) -> 0 | I66: =SUMIF('Current Invoice Log P1'!C:C,'Budget to Actual P1'!B66,'Current Invoice Log P1'!G:G) -> 0 | J66: =SUM(H66:I66) -> 0 | L66: =+G66-J66 -> 0
C67: Total Design and Engineering Consultants | D67: =SUBTOTAL(9,D45:D66) -> 125750 | E67: 38635.7 | F67: 0 | G67: =SUBTOTAL(9,G45:G66) -> 164385.7 | H67: =SUBTOTAL(9,H45:H66) -> 157420.6 | I67: =SUBTOTAL(9,I45:I66) -> 6965.1 | J67: =SUBTOTAL(9,J45:J66) -> 164385.7 | K67: =J67/G67 -> 1 | L67: =SUBTOTAL(9,L45:L66) -> 0
B68: 11970 | C68: Legal | D68: 50000 | E68: 18086.04 | F68: 0 | G68: =+D68+E68+F68 -> 68086.04 | H68: =SUMIF('Prior Invoice Log P1'!C:C,'Budget to Actual P1'!B68,'Prior Invoice Log P1'!G:G) -> 68086.04 | I68: =SUMIF('Current Invoice Log P1'!C:C,'Budget to Actual P1'!B68,'Current Invoice Log P1'!G:G) -> 0 | J68: =SUM(H68:I68) -> 68086.04 | K68: =J68/G68 -> 1 | L68: =+G68-J68 -> 0
B69: 12343 | C69: Loan Fees | D69: 115935.11 | E69: =29172.33 -> 29172.33 | F69: 0 | G69: =+D69+E69+F69 -> 145107.44 | H69: =SUMIF('Prior Invoice Log P1'!C:C,'Budget to Actual P1'!B69,'Prior Invoice Log P1'!G:G) -> 145107.44 | I69: =SUMIF('Current Invoice Log P1'!C:C,'Budget to Actual P1'!B69,'Current Invoice Log P1'!G:G) -> 0 | J69: =SUM(H69:I69) -> 145107.44 | K69: =J69/G69 -> 1 | L69: =+G69-J69 -> 0
C70: Capitalized Interest, Insurance, and Taxes | E70: 0 | F70: 0 | G70: =+D70+E70+F70 -> 0 | H70: =SUMIF('Prior Invoice Log P1'!C:C,'Budget to Actual P1'!B70,'Prior Invoice Log P1'!G:G) -> 0 | I70: =SUMIF('Current Invoice Log P1'!C:C,'Budget to Actual P1'!B70,'Current Invoice Log P1'!G:G) -> 0 | J70: =SUM(H70:I70) -> 0 | K70: =J70/G70 -> #DIV/0! | L70: =+G70-J70 -> 0
B71: 12411 | C71: Interest Rate Cap | D71: 0 | E71: 0 | F71: 0 | G71: =+D71+E71+F71 -> 0 | H71: =SUMIF('Prior Invoice Log P1'!C:C,'Budget to Actual P1'!B71,'Prior Invoice Log P1'!G:G) -> 0 | I71: =SUMIF('Current Invoice Log P1'!C:C,'Budget to Actual P1'!B71,'Current Invoice Log P1'!G:G) -> 0 | J71: =SUM(H71:I71) -> 0 | K71: =J71/G71 -> #DIV/0! | L71: =+G71-J71 -> 0
B72: 12310 | C72: Appraisal | D72: 0 | E72: 0 | F72: 0 | G72: =+D72+E72+F72 -> 0 | H72: =SUMIF('Prior Invoice Log P1'!C:C,'Budget to Actual P1'!B72,'Prior Invoice Log P1'!G:G) -> 0 | I72: =SUMIF('Current Invoice Log P1'!C:C,'Budget to Actual P1'!B72,'Current Invoice Log P1'!G:G) -> 0 | J72: =SUM(H72:I72) -> 0 | K72: =J72/G72 -> #DIV/0! | L72: =+G72-J72 -> 0
C73: Market/Feasibility Study | D73: 0 | E73: 0 | F73: 0 | G73: =+D73+E73+F73 -> 0 | H73: =SUMIF('Prior Invoice Log P1'!C:C,'Budget to Actual P1'!B73,'Prior Invoice Log P1'!G:G) -> 0 | I73: =SUMIF('Current Invoice Log P1'!C:C,'Budget to Actual P1'!B73,'Current Invoice Log P1'!G:G) -> 0 | J73: =SUM(H73:I73) -> 0 | K73: =J73/G73 -> #DIV/0! | L73: =+G73-J73 -> 0
C74: Predevelopment Interest | D74: 0 | E74: 0 | F74: 0 | G74: =+D74+E74+F74 -> 0 | H74: =SUMIF('Prior Invoice Log P1'!C:C,'Budget to Actual P1'!B74,'Prior Invoice Log P1'!G:G) -> 0 | I74: =SUMIF('Current Invoice Log P1'!C:C,'Budget to Actual P1'!B74,'Current Invoice Log P1'!G:G) -> 0 | J74: =SUM(H74:I74) -> 0 | K74: =J74/G74 -> #DIV/0! | L74: =+G74-J74 -> 0
C75: Investor Interest | D75: 0 | E75: 0 | F75: 0 | G75: =+D75+E75+F75 -> 0 | H75: =SUMIF('Prior Invoice Log P1'!C:C,'Budget to Actual P1'!B75,'Prior Invoice Log P1'!G:G) -> 0 | I75: =SUMIF('Current Invoice Log P1'!C:C,'Budget to Actual P1'!B75,'Current Invoice Log P1'!G:G) -> 0 | J75: =SUM(H75:I75) -> 0 | K75: =J75/G75 -> #DIV/0! | L75: =+G75-J75 -> 0
C76: Points on Equity (LP Fee) | D76: 0 | E76: 0 | F76: 0 | G76: =+D76+E76+F76 -> 0 | H76: =SUMIF('Prior Invoice Log P1'!C:C,'Budget to Actual P1'!B76,'Prior Invoice Log P1'!G:G) -> 0 | I76: =SUMIF('Current Invoice Log P1'!C:C,'Budget to Actual P1'!B76,'Current Invoice Log P1'!G:G) -> 0 | J76: =SUM(H76:I76) -> 0 | K76: =J76/G76 -> #DIV/0! | L76: =+G76-J76 -> 0
C77: Debt Placement Fee | D77: 0 | E77: 0 | F77: 0 | G77: =+D77+E77+F77 -> 0 | H77: =SUMIF('Prior Invoice Log P1'!C:C,'Budget to Actual P1'!B77,'Prior Invoice Log P1'!G:G) -> 0 | I77: =SUMIF('Current Invoice Log P1'!C:C,'Budget to Actual P1'!B77,'Current Invoice Log P1'!G:G) -> 0 | J77: =SUM(H77:I77) -> 0 | K77: =J77/G77 -> #DIV/0! | L77: =+G77-J77 -> 0
C78: Development Oversight Fee (LP FEE) | D78: 0 | E78: 0 | F78: 0 | G78: =+D78+E78+F78 -> 0 | H78: =SUMIF('Prior Invoice Log P1'!C:C,'Budget to Actual P1'!B78,'Prior Invoice Log P1'!G:G) -> 0 | I78: =SUMIF('Current Invoice Log P1'!C:C,'Budget to Actual P1'!B78,'Current Invoice Log P1'!G:G) -> 0 | J78: =SUM(H78:I78) -> 0 | K78: =J78/G78 -> #DIV/0! | L78: =+G78-J78 -> 0
B79: 12596 | C79: Closing Fees | D79: 100000 | E79: =-41697.95 -> -41697.95 | F79: 0 | G79: =+D79+E79+F79 -> 58302.05 | H79: =SUMIF('Prior Invoice Log P1'!C:C,'Budget to Actual P1'!B79,'Prior Invoice Log P1'!G:G) -> 0 | I79: =SUMIF('Current Invoice Log P1'!C:C,'Budget to Actual P1'!B79,'Current Invoice Log P1'!G:G) -> 0 | J79: =SUM(H79:I79) -> 0 | K79: =J79/G79 -> 0 | L79: =+G79-J79 -> 58302.05
C80: Bank Charges | D80: 0 | E80: 0 | F80: 0 | G80: =+D80+E80+F80 -> 0 | H80: =SUMIF('Prior Invoice Log P1'!C:C,'Budget to Actual P1'!B80,'Prior Invoice Log P1'!G:G) -> 0 | I80: =SUMIF('Current Invoice Log P1'!C:C,'Budget to Actual P1'!B80,'Current Invoice Log P1'!G:G) -> 0 | J80: =SUM(H80:I80) -> 0 | K80: =J80/G80 -> #DIV/0! | L80: =+G80-J80 -> 0
C81: Inspections/Feasibility | D81: 0 | E81: 0 | F81: 0 | G81: =+D81+E81+F81 -> 0 | H81: =SUMIF('Prior Invoice Log P1'!C:C,'Budget to Actual P1'!B81,'Prior Invoice Log P1'!G:G) -> 0 | I81: =SUMIF('Current Invoice Log P1'!C:C,'Budget to Actual P1'!B81,'Current Invoice Log P1'!G:G) -> 0 | J81: =SUM(H81:I81) -> 0 | K81: =J81/G81 -> #DIV/0! | L81: =+G81-J81 -> 0
C82: Architectural Inspections | D82: 0 | E82: 0 | F82: 0 | G82: =+D82+E82+F82 -> 0 | H82: =SUMIF('Prior Invoice Log P1'!C:C,'Budget to Actual P1'!B82,'Prior Invoice Log P1'!G:G) -> 0 | I82: =SUMIF('Current Invoice Log P1'!C:C,'Budget to Actual P1'!B82,'Current Invoice Log P1'!G:G) -> 0 | J82: =SUM(H82:I82) -> 0 | K82: =J82/G82 -> #DIV/0! | L82: =+G82-J82 -> 0
C83: Title Updates | D83: 0 | E83: 0 | F83: 0 | G83: =+D83+E83+F83 -> 0 | H83: =SUMIF('Prior Invoice Log P1'!C:C,'Budget to Actual P1'!B83,'Prior Invoice Log P1'!G:G) -> 0 | I83: =SUMIF('Current Invoice Log P1'!C:C,'Budget to Actual P1'!B83,'Current Invoice Log P1'!G:G) -> 0 | J83: =SUM(H83:I83) -> 0 | K83: =J83/G83 -> #DIV/0! | L83: =+G83-J83 -> 0
C84: Letter of Credit | D84: 0 | E84: 0 | F84: 0 | G84: =+D84+E84+F84 -> 0 | H84: =SUMIF('Prior Invoice Log P1'!C:C,'Budget to Actual P1'!B84,'Prior Invoice Log P1'!G:G) -> 0 | I84: =SUMIF('Current Invoice Log P1'!C:C,'Budget to Actual P1'!B84,'Current Invoice Log P1'!G:G) -> 0 | J84: =SUM(H84:I84) -> 0 | K84: =J84/G84 -> #DIV/0! | L84: =+G84-J84 -> 0
C85: Applications Costs | D85: 0 | E85: 0 | F85: 0 | G85: =+D85+E85+F85 -> 0 | H85: =SUMIF('Prior Invoice Log P1'!C:C,'Budget to Actual P1'!B85,'Prior Invoice Log P1'!G:G) -> 0 | I85: =SUMIF('Current Invoice Log P1'!C:C,'Budget to Actual P1'!B85,'Current Invoice Log P1'!G:G) -> 0 | J85: =SUM(H85:I85) -> 0 | K85: =J85/G85 -> #DIV/0! | L85: =+G85-J85 -> 0
B86: 12385 | C86: Other Finance Costs (Loan Cap) | D86: 0 | E86: 0 | F86: 0 | G86: =+D86+E86+F86 -> 0 | H86: =SUMIF('Prior Invoice Log P1'!C:C,'Budget to Actual P1'!B86,'Prior Invoice Log P1'!G:G) -> 0 | I86: 0 | J86: =SUM(H86:I86) -> 0 | K86: =J86/G86 -> #DIV/0! | L86: =+G86-J86 -> 0
B87: 12410 | C87: Property Tax | D87: 0 | E87: 0 | F87: 0 | G87: =+D87+E87+F87 -> 0 | H87: =SUMIF('Prior Invoice Log P1'!C:C,'Budget to Actual P1'!B87,'Prior Invoice Log P1'!G:G) -> 0 | I87: =SUMIF('Current Invoice Log P1'!C:C,'Budget to Actual P1'!B87,'Current Invoice Log P1'!G:G) -> 0 | J87: =SUM(H87:I87) -> 0 | K87: =J87/G87 -> #DIV/0! | L87: =+G87-J87 -> 0
B88: 12421 | C88: Property Insurance | D88: 0 | E88: 0 | F88: 0 | G88: =+D88+E88+F88 -> 0 | H88: =SUMIF('Prior Invoice Log P1'!C:C,'Budget to Actual P1'!B88,'Prior Invoice Log P1'!G:G) -> 0 | I88: =SUMIF('Current Invoice Log P1'!C:C,'Budget to Actual P1'!B88,'Current Invoice Log P1'!G:G) -> 0 | J88: =SUM(H88:I88) -> 0 | K88: =J88/G88 -> #DIV/0! | L88: =+G88-J88 -> 0
C89: Guarantee Fee | D89: 0 | E89: 0 | F89: 0 | G89: =+D89+E89+F89 -> 0 | H89: =SUMIF('Prior Invoice Log P1'!C:C,'Budget to Actual P1'!B89,'Prior Invoice Log P1'!G:G) -> 0 | I89: =SUMIF('Current Invoice Log P1'!C:C,'Budget to Actual P1'!B89,'Current Invoice Log P1'!G:G) -> 0 | J89: =SUM(H89:I89) -> 0 | K89: =J89/G89 -> #DIV/0! | L89: =+G89-J89 -> 0
C90: LeaseUp Operating Deficits | D90: 0 | E90: 0 | F90: 0 | G90: =+D90+E90+F90 -> 0 | H90: =SUMIF('Prior Invoice Log P1'!C:C,'Budget to Actual P1'!B90,'Prior Invoice Log P1'!G:G) -> 0 | I90: =SUMIF('Current Invoice Log P1'!C:C,'Budget to Actual P1'!B90,'Current Invoice Log P1'!G:G) -> 0 | J90: =SUM(H90:I90) -> 0 | K90: =J90/G90 -> #DIV/0! | L90: =+G90-J90 -> 0
B91: 12321 | C91: Construction Period Interest | D91: 2315000 | E91: 0 | F91: 0 | G91: =+D91+E91+F91 -> 2315000 | H91: =SUMIF('Prior Invoice Log P1'!C:C,'Budget to Actual P1'!B91,'Prior Invoice Log P1'!G:G) -> 458105.13 | I91: =SUMIF('Current Invoice Log P1'!C:C,'Budget to Actual P1'!B91,'Current Invoice Log P1'!G:G) -> 64355.42 | J91: =SUM(H91:I91) -> 522460.55 | K91: =J91/G91 -> 0.2256849 | L91: =+G91-J91 -> 1792539.4
C92: Total Financing & Other Costs | D92: =SUBTOTAL(9,D68:D91) -> 2580935.1 | E92: =SUBTOTAL(9,E68:E91) -> 5560.42 | F92: =SUBTOTAL(9,F68:F91) -> 0 | G92: =SUBTOTAL(9,G68:G91) -> 2586495.5 | H92: =SUBTOTAL(9,H68:H91) -> 671298.61 | I92: =SUBTOTAL(9,I68:I91) -> 64355.42 | J92: =SUBTOTAL(9,J68:J91) -> 735654.03 | K92: =J92/G92 -> 0.28442115 | L92: =SUBTOTAL(9,L68:L91) -> 1850841.5
C93: GL Construction Insurance | E93: 0 | F93: 0 | G93: =+D93+E93+F93 -> 0 | H93: =SUMIF('Prior Invoice Log P1'!C:C,'Budget to Actual P1'!B93,'Prior Invoice Log P1'!G:G) -> 0 | I93: =SUMIF('Current Invoice Log P1'!C:C,'Budget to Actual P1'!B93,'Current Invoice Log P1'!G:G) -> 0 | J93: =SUM(H93:I93) -> 0 | K93: =J93/G93 -> #DIV/0! | L93: =+G93-J93 -> 0
C94: Development Management Fee | E94: 0 | F94: 0 | G94: =+D94+E94+F94 -> 0 | H94: =SUMIF('Prior Invoice Log P1'!C:C,'Budget to Actual P1'!B94,'Prior Invoice Log P1'!G:G) -> 0 | I94: =SUMIF('Current Invoice Log P1'!C:C,'Budget to Actual P1'!B94,'Current Invoice Log P1'!G:G) -> 0 | J94: =SUM(H94:I94) -> 0 | K94: =J94/G94 -> #DIV/0! | L94: =+G94-J94 -> 0
C95: Copies & Reproduction | D95: 0 | E95: 0 | F95: 0 | G95: =+D95+E95+F95 -> 0 | H95: =SUMIF('Prior Invoice Log P1'!C:C,'Budget to Actual P1'!B95,'Prior Invoice Log P1'!G:G) -> 0 | I95: =SUMIF('Current Invoice Log P1'!C:C,'Budget to Actual P1'!B95,'Current Invoice Log P1'!G:G) -> 0 | J95: =SUM(H95:I95) -> 0 | K95: =J95/G95 -> #DIV/0! | L95: =+G95-J95 -> 0
C96: Postage & Delivery | D96: 0 | E96: 0 | F96: 0 | G96: =+D96+E96+F96 -> 0 | H96: =SUMIF('Prior Invoice Log P1'!C:C,'Budget to Actual P1'!B96,'Prior Invoice Log P1'!G:G) -> 0 | I96: =SUMIF('Current Invoice Log P1'!C:C,'Budget to Actual P1'!B96,'Current Invoice Log P1'!G:G) -> 0 | J96: =SUM(H96:I96) -> 0 | K96: =J96/G96 -> #DIV/0! | L96: =+G96-J96 -> 0
B97: 12720 | C97: Travel - Other Development Costs | D97: 0 | E97: ='Prior Invoice Log P1'!G217 -> 0 | F97: 0 | G97: =+D97+E97+F97 -> 0 | H97: =SUMIF('Prior Invoice Log P1'!C:C,'Budget to Actual P1'!B97,'Prior Invoice Log P1'!G:G) -> 0 | I97: =SUMIF('Current Invoice Log P1'!C:C,'Budget to Actual P1'!B97,'Current Invoice Log P1'!G:G) -> 0 | J97: =SUM(H97:I97) -> 0 | K97: =J97/G97 -> #DIV/0! | L97: =+G97-J97 -> 0
B98: 12381 | C98: Acquisition Fees | D98: 0 | E98: 0 | F98: 0 | G98: =+D98+E98+F98 -> 0 | H98: =SUMIF('Prior Invoice Log P1'!C:C,'Budget to Actual P1'!B98,'Prior Invoice Log P1'!G:G) -> 0 | I98: =SUMIF('Current Invoice Log P1'!C:C,'Budget to Actual P1'!B98,'Current Invoice Log P1'!G:G) -> 0 | J98: =SUM(H98:I98) -> 0 | K98: =J98/G98 -> #DIV/0! | L98: =+G98-J98 -> 0
C99: Signage | D99: 0 | E99: 0 | F99: 0 | G99: =+D99+E99+F99 -> 0 | H99: =SUMIF('Prior Invoice Log P1'!C:C,'Budget to Actual P1'!B99,'Prior Invoice Log P1'!G:G) -> 0 | I99: =SUMIF('Current Invoice Log P1'!C:C,'Budget to Actual P1'!B99,'Current Invoice Log P1'!G:G) -> 0 | J99: =SUM(H99:I99) -> 0 | K99: =J99/G99 -> #DIV/0! | L99: =+G99-J99 -> 0
C100: Miscellaneous | D100: 0 | E100: 0 | F100: 0 | G100: =+D100+E100+F100 -> 0 | H100: =SUMIF('Prior Invoice Log P1'!C:C,'Budget to Actual P1'!B100,'Prior Invoice Log P1'!G:G) -> 0 | I100: =SUMIF('Current Invoice Log P1'!C:C,'Budget to Actual P1'!B100,'Current Invoice Log P1'!G:G) -> 0 | J100: =SUM(H100:I100) -> 0 | K100: =J100/G100 -> #DIV/0! | L100: =+G100-J100 -> 0
C101: Builder's Risk Insurance | D101: 0 | E101: 0 | F101: 0 | G101: =+D101+E101+F101 -> 0 | H101: =SUMIF('Prior Invoice Log P1'!C:C,'Budget to Actual P1'!B101,'Prior Invoice Log P1'!G:G) -> 0 | I101: =SUMIF('Current Invoice Log P1'!C:C,'Budget to Actual P1'!B101,'Current Invoice Log P1'!G:G) -> 0 | J101: =SUM(H101:I101) -> 0 | K101: =J101/G101 -> #DIV/0! | L101: =+G101-J101 -> 0
C102: Property Insurance | D102: 0 | E102: 0 | F102: 0 | G102: =+D102+E102+F102 -> 0 | H102: =SUMIF('Prior Invoice Log P1'!C:C,'Budget to Actual P1'!B102,'Prior Invoice Log P1'!G:G) -> 0 | I102: =SUMIF('Current Invoice Log P1'!C:C,'Budget to Actual P1'!B102,'Current Invoice Log P1'!G:G) -> 0 | J102: =SUM(H102:I102) -> 0 | K102: =J102/G102 -> #DIV/0! | L102: =+G102-J102 -> 0
C103: OCIP | D103: 0 | E103: 0 | F103: 0 | G103: =+D103+E103+F103 -> 0 | H103: =SUMIF('Prior Invoice Log P1'!C:C,'Budget to Actual P1'!B103,'Prior Invoice Log P1'!G:G) -> 0 | I103: =SUMIF('Current Invoice Log P1'!C:C,'Budget to Actual P1'!B103,'Current Invoice Log P1'!G:G) -> 0 | J103: =SUM(H103:I103) -> 0 | K103: =J103/G103 -> #DIV/0! | L103: =+G103-J103 -> 0
C104: Telecommunications | D104: 0 | E104: 0 | F104: 0 | G104: =+D104+E104+F104 -> 0 | H104: =SUMIF('Prior Invoice Log P1'!C:C,'Budget to Actual P1'!B104,'Prior Invoice Log P1'!G:G) -> 0 | I104: =SUMIF('Current Invoice Log P1'!C:C,'Budget to Actual P1'!B104,'Current Invoice Log P1'!G:G) -> 0 | J104: =SUM(H104:I104) -> 0 | K104: =J104/G104 -> #DIV/0! | L104: =+G104-J104 -> 0
C105: Electricity | D105: 0 | E105: 0 | F105: 0 | G105: =+D105+E105+F105 -> 0 | H105: =SUMIF('Prior Invoice Log P1'!C:C,'Budget to Actual P1'!B105,'Prior Invoice Log P1'!G:G) -> 0 | I105: =SUMIF('Current Invoice Log P1'!C:C,'Budget to Actual P1'!B105,'Current Invoice Log P1'!G:G) -> 0 | J105: =SUM(H105:I105) -> 0 | K105: 0 | L105: =+G105-J105 -> 0
...

Sheet Soft Cost Contingency P1
B1: ='Budget to Actual P1'!B2 -> County Line Rail Silsbee LLC
B2: Soft Cost Contingency Table
B3: ='Budget to Actual P1'!B4 -> 46203
C6: Cost Category | D6: Contingency | E6: Contingency | F6: Contingency | G6: Req # | H6: Notes
D7: Previously | E7: Requested | F7: Total
B8: COA# | D8: Requested | E8: Herein | F8: Requested
B15: 11230-5 | C15: Electrical Improvements | D15: -540 | G15: 10 | H15: Budget adjustment
B16: 12230 | C16: Professional Services - Accounting | D16: 4239.34 | G16: 10 | H16: Budget overrun on accounting
B17: 12115 | C17: A&E | D17: 2868.08 | G17: 9 | H17: Budget overrun on A&E
B18: 12115 | C18: A&E | D18: 5802.86 | G18: 8 | H18: Budget overrun on A&E
B19: 11970 | C19: Legal | D19: 5560.42 | G19: 7 | H19: Budget overrun on Legal
B20: 12115 | C20: A&E | D20: 5000 | G20: 7 | H20: Budget overrun on A&E
B21: 12115 | C21: A&E | D21: 9943.8 | G21: 6 | H21: Budget overrun on A&E
B22: 12115 | C22: A&E | D22: 10781.62 | G22: 5 | H22: Budget overrun on A&E
C23: Total Other Development Costs | D23: =SUBTOTAL(9,D$9:D$22) -> 39956.78 | E23: =SUBTOTAL(9,E$9:E$22) -> 3699.34 | F23: =D23+E23 -> 43656.12
B26: Contingency Allocations | D26: =SUM(D23:D25) -> 39956.78 | E26: =SUM(E23:E25) -> 3699.34 | F26: =SUM(F23:F25) -> 43656.12
B28: Original Contingency Budget | D28: ='Budget to Actual P1'!D27 -> 293570.38
B30: Contingency Previously Requested | D30: =+D26 -> 39956.78
B31: Contingency Requested Herein | D31: =+E26 -> 3699.34
B32: Total Contingency Requested | D32: =+SUM(D30:D31) -> 43656.12
B34: Remaining Contingency | D34: =+$D$28-$D$32 -> 249914.26
D39: =ROUND(D34,2)=ROUND('Budget to Actual P1'!L27,2) -> TRUE | E39: Budget to Actual = Soft Cost Contingency Table

Sheet Soft cost contingency-PSTR
B4: Cost Category | C4: Contingency | D4: Contingency | E4: Contingency | F4: Req | G4: Notes
C5: Previously | D5: Requested | E5: Total
A6: COA# | C6: Requested | D6: Herein | E6: Requested
B14: Land | C14: 0.36 | F14: 1
B15: Due Diligence | C15: 1949.64 | F15: 1
B16: Total Other Development Costs | C16: =SUM(C7:C15) -> 1950 | D16: =SUM(D7:D15) -> 0 | E16: =C16+D16 -> 1950
A19: Contingency Allocations | C19: =SUM(C16:C18) -> 1950 | D19: =SUM(D16:D18) -> 0 | E19: =SUM(E16:E18) -> 1950
A21: Original Contingency Budget | C21: =#REF! -> #REF!
A23: Contingency Previously Requested | C23: =+C19 -> 1950
A24: Contingency Requested Herein | C24: =+D19 -> 0
A25: Total Contingency Requested | C25: =+SUM(C23:C24) -> 1950
A27: Remaining Contingency | C27: =+C21-C25 -> #REF!
C30: =C27-#REF! -> #REF!

Sheet Hard cost contingency
B4: Cost Category | C4: Contingency | D4: Contingency | E4: Req | F4: Notes
C5: Previously | D5: Requested
A6: COA# | C6: Requested | D6: Herein
J20: Reference Hidden Tab "Bridge Approvd Budget to Actual"
J21: Added 489,803.90 to Orginal Budget (1,914,611.10)
D29: 0
B30: Total Other Development Costs | C30: =SUM(C10:C29) -> 0 | D30: =SUM(D7:D29) -> 0
A33: Contingency Allocations | C33: =SUM(C30:C32) -> 0 | D33: =SUM(D30:D32) -> 0
A35: Original Contingency Budget | C35: ='Budget to Actual P1'!#REF! -> #REF!
A37: Contingency Previously Requested | C37: =+C33 -> 0
A38: Contingency Requested Herein | C38: =+D33 -> 0
A39: Total Contingency Requested | C39: =+SUM(C37:C38) -> 0
A41: Remaining Contingency | C41: =+C35-C39 -> #REF!
C45: =C41-'Budget to Actual P1'!#REF! -> #REF!

Sheet Hard Cost Contigency P1
B1: ='Budget to Actual P1'!B2 -> County Line Rail Silsbee LLC
B2: Hard Cost Contingency Table
B3: ='Budget to Actual P1'!B4 -> 46203
C6: Cost Category | D6: Contingency | E6: Contingency | F6: Contingency | G6: Req # | H6: Notes
D7: Previously | E7: Requested | F7: Total
B8: COA# | D8: Requested | E8: Herein | F8: Requested
K13: 0
B19: 11230-3 | C19: Sprinkler Improvements | D19: 16174 | G19: 10 | H19: Budget Reallocation
B20: 11230-7 | C20: Other Hard Costs | D20: 15561.43 | G20: 8 | H20: Budget Reallocation
B21: 11230-1 | C21: Yard Stabilization | D21: 48645.39 | G21: 7 | H21: Budget Reallocation
B22: 11230-4 | C22: Roof Improvements | D22: 300 | G22: 6 | H22: Budget Reallocation
B23: 11230-7 | C23: Other Hard Costs | D23: 12605.92 | G23: 6 | H23: Budget Reallocation
B24: 11230-7 | C24: Other Hard Costs | D24: 19200.94 | G24: 5 | H24: Budget Reallocation
B25: 11230-7 | C25: Other Hard Costs | D25: 109167.61 | G25: 4 | H25: Budget Reallocation
C26: Total Other Development Costs | D26: =SUBTOTAL(9,D$9:D$25) -> 205481.29 | E26: =SUBTOTAL(9,E$9:E$25) -> 16174 | F26: =D26+E26 -> 221655.29
B29: Contingency Allocations | D29: =SUM(D26:D28) -> 205481.29 | E29: =SUM(E26:E28) -> 16174 | F29: =SUM(F26:F28) -> 221655.29
B31: Original Contingency Budget | D31: ='Budget to Actual P1'!D26 -> 346282.8
B33: Contingency Previously Requested | D33: =+D29 -> 205481.29
B34: Contingency Requested Herein | D34: =+E29 -> 16174
B35: Total Contingency Requested | D35: =+SUM(D33:D34) -> 221655.29
B37: Remaining Contingency | D37: =+$D$31-$D$35 -> 124627.51
D41: =ROUND(D37,2)=ROUND('Budget to Actual P1'!L26,2) -> TRUE | E41: Budget to Actual = Hard Cost Contingency Table

Sheet Current Invoice Log P1
A1: ='Budget to Actual P1'!B2 -> County Line Rail Silsbee LLC
A2: Current Invoice Log
A3: ='Budget to Actual P1'!B4 -> 46203
A5: Cost Category | B5: Bank Cost Category | C5: Cost Code # | D5: Cost Code Name | E5: Vendor | F5: Bill number | G5: Amount | H5: Requisition Month | I5: Invoice (Y/N)
A6: Professional Services - Accounting | C6: 12230 | D6: Professional Services - Accounting | E6: CliftonLarsonAllen LLP | F6: L261457720 | G6: 6912.36 | H6: Req#11 | K6: 2026-07-27 | Y6: 12230
D8: Professional Services - Accounting Total | G8: =SUBTOTAL(9,G6:G7)
A10: Construction Period Interest | C10: 12321 | D10: Construction Period Interest | E10: BoTX | F10: Jul_26 Interest | G10: 62794.4 | H10: Req#11 | K10: 2026-07-13 | Y10: 12321
D12: Construction Period Interest Total | G12: =SUBTOTAL(9,G10:G11)
A14: Soft Costs | B14: Development Fee | C14: 12913 | D14: Development Fee | E14: County Line Rail Interest | F14: July_26 Dev Fee | G14: 10049.82 | H14: Req#11 | Y14: 12913
D16: Development Fee Total | G16: =SUBTOTAL(9,G14:G15)
A18: Broker Commissions | C18: 12594 | D18: Broker Commissions | E18: DFW Lee & Associates, LLC - Houston Office, RS | F18: 20256631-1 | G18: 181538.72 | H18: Req#11 | K18: 2026-07-01 | Y18: 12594
D20: Broker Commissions Total | G20: =SUBTOTAL(9,G18:G19)
D22: Grand Total | G22: =SUBTOTAL(9,G6:G21)

Sheet Prior Invoice Log P1
A1: ='Budget to Actual P1'!B2 -> County Line Rail Silsbee LLC
A2: Prior Invoice Log
A3: ='Budget to Actual P1'!B4 -> 46203
A5: Cost Category | B5: Bank Cost Category | C5: Cost Code # | D5: Cost Code Name | E5: Vendor | F5: Bill number | G5: Amount Paid | H5: Requisition Month | I5: Invoice
A6: Land Cost | C6: 11010 | D6: Acquisitions Costs (Land Purchase)
D8: Acquisitions Costs (Land Purchase) Total | G8: =SUBTOTAL(9,G6:G7)
A10: Construction Costs | C10: 11210 | D10: Expansion Costs (Base Construction Costs)
A11: Construction Costs | C11: 11210 | D11: Expansion Costs (Base Construction Costs)
D13: Expansion Costs (Base Construction Costs) Total | G13: =SUBTOTAL(9,G10:G12)
A15: Construction Cost | C15: 11212 | D15: Other Structures (BNSF 418 Road Crossing Install)
A16: Construction Cost | C16: 11212 | D16: Other Structures (BNSF 418 Road Crossing Install)
A17: Construction Cost | C17: 11212 | D17: Other Structures (BNSF 418 Road Crossing Install)
D19: Other Structures (BNSF 418 Road Crossing Install) Total | G19: =SUBTOTAL(9,G15:G18)
A21: Construction Cost | C21: 11213 | D21: Track Clearing Repair
A22: Construction Cost | C22: 11213 | D22: Track Clearing Repair
A23: Construction Cost | C23: 11213 | D23: Track Clearing Repair
D25: Track Clearing Repair Total | G25: =SUBTOTAL(9,G21:G24)
A27: Construction Costs | C27: 11214 | D27: Building Repair (waterproofing)
A28: Construction Costs | C28: 11214 | D28: Building Repair (waterproofing)
A29: Construction Cost | C29: 11214 | D29: Building Repair | G29: 0
D31: Building Repair (waterproofing) Total | G31: =SUBTOTAL(9,G27:G30)
A33: Construction Cost | C33: 11215 | D33: Deferred Maintenance
A34: Construction Cost | C34: 11215 | D34: Deferred Maintenance
A35: Construction Cost | C35: 11215 | D35: Deferred Maintenance
D37: Base Construction Costs Total | G37: =SUBTOTAL(9,G33:G36)
A39: Construction Cost | C39: 11218 | D39: Working Capital
A40: Construction Cost | C40: 11218 | D40: Working Capital
D42: Working Capital Total | G42: =SUBTOTAL(9,G39:G41)
A44: Design and Engineering Consultants | C44: 12115 | D44: A&E
A45: Design and Engineering Consultants | C45: 12115 | D45: A&E
A46: Design and Engineering Consultants | C46: 12115 | D46: A&E | E46: TRC | F46: 50631
A47: Appraisal | C47: 12115 | D47: Appraisal | E47: Colliers International
A48: Appraisal | C48: 12115 | D48: Appraisal | E48: Colliers International
D50: A&E Total | G50: =SUBTOTAL(9,G44:G49)
A52: Design and Engineering Consultants | C52: 12116 | D52: Environmental
A53: Design and Engineering Consultants | C53: 12116 | D53: Environmental
A54: Design and Engineering Consultants | C54: 12116 | D54: Environmental
D56: Environmental Total | G56: =SUBTOTAL(9,G52:G55)
A58: Other Construction Costs | C58: 11230-1 | D58: Other Construction Costs | E58: Agri-Serv Industrial Maintenance | F58: Pay App#1 | G58: 142534.8 | H58: Rec #1
A59: Other Construction Costs | C59: 11230-2 | D59: Other Construction Costs | E59: Stewart Development & Construction, LLC | F59: Pay App#1 | G59: 110286.65 | H59: Rec #1
A60: Other Construction Costs | C60: 11230-7 | D60: Other Construction Costs | E60: Water Asset Holdings | F60: CLR2509 | G60: 5000 | H60: Rec #1
A61: Other Construction Costs | C61: 11230-7 | D61: Other Construction Costs | E61: Double S Industrial Contractors, Inc. | F61: 125-2901-A | G61: 17733 | H61: Rec #1
A62: Other Construction Costs | C62: 11230-7 | D62: Other Construction Costs | E62: Ram Industrial Construction | F62: 17431 | G62: 5000 | H62: Rec #1 | K62: In January GL, Not on Req Report
A63: Other Construction Costs | C63: 11230-7 | D63: Other Construction Costs | E63: Switch Yard Mowing | F63: 10001 | G63: 15660 | H63: Rec #1
A64: Other Construction Costs | C64: 11230-3 | D64: Other Construction Costs | E64: Summit Fire & Security, LLC | F64: Pay App #1 | G64: 129528.9 | H64: Rec #2
A65: Other Construction Costs | C65: 11230-1 | D65: Other Construction Costs | E65: Agri-Serv Industrial Maintenance | F65: Pay App #2 | G65: 302767.57 | H65: Rec #2
A66: Other Construction Costs | C66: 11230-2 | D66: Other Construction Costs | E66: Stewart Development & Construction, LLC | F66: Pay App #2 | G66: 468959.59 | H66: Rec #2
A67: Other Construction Costs | C67: 11230-4 | D67: Other Construction Costs | E67: Strategic Roofing Solutions | F67: Pay App #1 - Roofing | G67: 35997.3 | H67: Rec #2
A68: Other Construction Costs | C68: 11230-5 | D68: Other Construction Costs | E68: Biskamp Electric | F68: Pay App #1 | G68: 168962.15 | H68: Rec #2
A69: Other Construction Costs | C69: 11230-2 | D69: Other Construction Costs | E69: Stewart Development & Construction, LLC | F69: Pay App #3 | G69: 267556.23 | H69: Rec #3
A70: Other Construction Costs | C70: 11230-2 | D70: Other Construction Costs | E70: Stewart Development & Construction, LLC | F70: Pay App #3R | G70: 94089.16 | H70: Rec #3
A71: Other Construction Costs | C71: 11230-4 | D71: Other Construction Costs | E71: Strategic Roofing Solutions | F71: Pay App #2 | G71: 51808.5 | H71: Rec #3
A72: Other Construction Costs | C72: 11230-1 | D72: Other Construction Costs | E72: Agri-Serv Industrial Maintenance | F72: Pay App #3 | G72: 867999.29 | H72: Rec #3
A73: Other Construction Costs | C73: 11230-7 | D73: Other Construction Costs | E73: Bartlett & West | F73: 730105520 | G73: 25750 | H73: Rec #4
A74: Other Construction Costs | C74: 11230-7 | D74: Other Construction Costs | E74: Bartlett & West | F74: 730106293 | G74: 21750 | H74: Rec #4
... A102: Other Construction Costs | C102: 11230-6 | D102: Other Construction Costs | E102: Agri-Serv Industrial Maintenance | F102: Pay App#1b (revised) | G102: -36000 | H102: Rec #8
D104: Expansion Costs (Base Construction Costs) Total | G104: =SUBTOTAL(9,G58:G103)
A106: Design and Engineering Consultants | C106: 11760 | D106: Other Due Diligence
A107: Design and Engineering Consultants | C107: 11760 | D107: Other Due Diligence
A108: Design and Engineering Consultants | C108: 11760 | D108: Other Due Diligence
D110: Other Due Diligence Total | G110: =SUBTOTAL(9,G106:G109)
A112: Financing & Other Costs | C112: 11970 | D112: Other Legal - Legal | E112: Mira Blanton PLLC | F112: 20250109 | G112: 5000 | H112: Rec #1 | K112: In January GL, Not on Req Report
A113: Financing & Other Costs | C113: 11970 | D113: Other Legal - Legal | E113: Jack Holmes | F113: 303 | G113: 2561 | H113: Rec #1 | K113: In April GL, Not on Req Report
A114: Financing & Other Costs | C114: 11970 | D114: Other Legal - Legal | E114: Jack Holmes | F114: 304 | G114: 1928 | H114: Rec #1 | K114: In May GL, Not on Req Report
A115: Financing & Other Costs | C115: 11970 | D115: Other Legal - Legal | E115: Jack Holmes | F115: 308 | G115: 1568 | H115: Rec #1 | K115: In August GL, Not on Req Report
A116: Financing & Other Costs | C116: 11970 | D116: Other Legal - Legal | E116: Patrick M Knapp | F116: 022 | G116: 2379 | H116: Rec #1
A117: Financing & Other Costs | C117: 11970 | D117: Other Legal - Legal | E117: Troutman Pepper Locke | F117: 132053245 | G117: 1207 | H117: Rec #1
A118: Financing & Other Costs | C118: 11970 | D118: Other Legal - Legal | E118: Jack Holmes | F118: 309 | G118: 794 | H118: Rec #4
A119: Financing & Other Costs | C119: 11970 | D119: Other Legal - Legal | E119: Mira Blanton PLLC | F119: 3509 | G119: 5505 | H119: Rec #4
A120: Financing & Other Costs | C120: 11970 | D120: Other Legal - Legal | E120: Mira Blanton PLLC | F120: 3510 | G120: 832.89 | H120: Rec #4
A121: Financing & Other Costs | C121: 11970 | D121: Other Legal - Legal | E121: Mira Blanton PLLC | F121: 3511 | G121: 2381.32 | H121: Rec #4
A122: Financing & Other Costs | C122: 11970 | D122: Other Legal - Legal | E122: Mira Blanton PLLC | F122: 3249 | G122: 1115 | H122: Rec #4
A123: Financing & Other Costs | C123: 11970 | D123: Other Legal - Legal | E123: CLRFI | F123: ADJ JE CLR Fund Loan Closing | G123: 18812.66 | H123: Rec #4
A124: Financing & Other Costs | C124: 11970 | D124: Other Legal - Legal | E124: BoTX | F124: BoTX Loan Closing ADJ JE | G124: 18441.75 | H124: Rec #4
A125: Financing & Other Costs | C125: 11970 | D125: Other Legal - Legal | E125: L.E. Peabody | F125: Feb_2026 | G125: 5560.42 | H125: Rec #7
A126: Financing & Other Costs | C126: 11970 | D126: Other Legal - Legal | E126: L.E. Peabody
D128: Other Legal - Legal Total | G128: =SUBTOTAL(9,G112:G127)
A130: Construction Costs | C130: 12013 | D130: Civil Engineering Plans
A131: Construction Costs | C131: 12013 | D131: Civil Engineering Plans
D133: Civil Engineering Plans Total | G133: =SUBTOTAL(9,G130:G132)
A135: Design and Engineering Consultants | C135: 12115 | D135: A&E | E135: TRC | F135: 48204 | G135: 3836.1 | H135: Rec #1
A136: Appraisal | C136: 12115 | D136: Appraisal | E136: Colliers International | F136: 536237 | G136: 6500 | H136: Rec #1
A137: Appraisal | C137: 12115 | D137: Appraisal | E137: Colliers International | F137: 536249 (Silsbee Portion) | G137: 625 | H137: Rec #1
A138: Design and Engineering Consultants | C138: 12115 | D138: A&E | E138: TRC | F138: 48561 | G138: 4233.98 | H138: Rec #2
A139: Design and Engineering Consultants | C139: 12115 | D139: A&E | E139: Water Asset Holdings | F139: CLR2510 | G139: 5000 | H139: Rec #2
A140: Design and Engineering Consultants | C140: 12115 | D140: A&E | E140: Water Asset Holdings | F140: CLR251003 | G140: 1500 | H140: Rec #2
A141: Design and Engineering Consultants | C141: 12115 | D141: A&E | E141: Water Asset Holdings | F141: CLR2511 | G141: 5000 | H141: Rec #3
A142: Design and Engineering Consultants | C142: 12115 | D142: A&E | E142: TRC | F142: 49013 | G142: 719 | H142: Rec #3
A143: Design and Engineering Consultants | C143: 12115 | D143: A&E | E143: Water Asset Holdings | F143: CLR2512 | G143: 5000 | H143: Rec #4
A144: Design and Engineering Consultants | C144: 12115 | D144: A&E | E144: TRC | F144: 49136 | G144: 19901.12 | H144: Rec #4
A145: Design and Engineering Consultants | C145: 12115 | D145: A&E | E145: Water Asset Holdings | F145: CLR2601 | G145: 5000 | H145: Rec #5
A146: Design and Engineering Consultants | C146: 12115 | D146: A&E | E146: TRC | F146: 49488 | G146: 1816.42 | H146: Rec #5
... A157: Design and Engineering Consultants | C157: 12115 | D157: A&E | E157: TRC | F157: 50631 | G157: 2868.08 | H157: Rec #9
D159: A&E Total | G159: =SUBTOTAL(9,G135:G158)
A161: Professional Services accounting | C161: 12230 | D161: Professional Services - Accounting | E161: CliftonLarsonAllen LLP | F161: L251572229 | G161: 5484.61 | H161: Rec #1
A162: Professional Services accounting | C162: 12230 | D162: Professional Services - Accounting | E162: CliftonLarsonAllen LLP | F162: L251635995 | G162: 8817.86 | H162: Rec #2
A163: Professional Services accounting | C163: 12230 | D163: Professional Services - Accounting | E163: CliftonLarsonAllen LLP | F163: L251712193 | G163: 8014.17 | H163: Rec #3
A164: Professional Services accounting | C164: 12230 | D164: Professional Services - Accounting | E164: CliftonLarsonAllen LLP | F164: L261008873 | G164: 5587 | H164: Rec #4 | J164: - Accrual for December portion of CLA inv
A165: Professional Services accounting | C165: 12230 | D165: Professional Services - Accounting | E165: CliftonLarsonAllen LLP | F165: L261008873 | G165: 8834.97 | H165: Rec #5
A166: Professional Services accounting | C166: 12230 | D166: Professional Services - Accounting | E166: CliftonLarsonAllen LLP | F166: L261093961 | G166: 9216.43 | H166: Rec #6
...

Sheet Dev Fee P1
A2: County Line Rail Silsbee
A3: Development Fee Calculation
A4: 46203
B6: Project costs | C6: Project costs | D6: Project costs
B7: Incurred to date | C7: Incurred - Month of | D7: Incurred
B8: 46203 | C8: =B8 -> 46203 | D8: 46173
A9: Project costs
A10: Hard Costs | B10: ='Budget to Actual P1'!J28 -> 5467355.1 | C10: ='Budget to Actual P1'!I28 -> 182172.28 | D10: =B10-C10 -> 5285182.9
A11: Soft Costs | B11: ='Budget to Actual P1'!J67+'Budget to Actual P1'!J92+'Budget to Actual P1'!J124 -> 1817226.6 | C11: ='Budget to Actual P1'!I67+'Budget to Actual P1'!I92+'Budget to Actual P1'!I124 -> 71320.52 | D11: =B11-C11 -> 1745906.1
D12: =B12-C12 -> 0
A13: Total | B13: =SUM($B$10:$B$12) -> 7284581.7 | C13: =SUM(C10:C12) -> 253492.8 | D13: =SUM($D$10:$D$12) -> 7031088.9
A14: Total per GL
A15: Discrepancy | B15: =B13-B14 -> 7284581.7
A17: Development fees: | B17: Dev fees incurred to date | C17: Current Month Dev Fee | D17: Prior Month Balance
A18: Due to CLR Silsbee Property Owner | B18: =ROUND(B13*0.04,2) -> 291383.27 | C18: =C13*0.04 -> 10139.712 | D18: =ROUND($D$13*0.04,2) -> 281243.56
A19: Total: | B19: =SUM(B18:B18) -> 291383.27 | C19: =C14*0.04 -> 0 | D19: =SUM($D$18:$D$18) -> 281243.56
B25: Total | C25: =C18 -> 10139.712

Sheet Project Costs (Dev)

Sheet OP->

Sheet Budget to Actual (OP)
C2: PROJECT FUNDING REQUISITION
C3: County Line Rail Silsbee LLC
C4: Application Period: 12/31/2025
C5: Requisition Report #17
C7: Operations | D7: Silsbee PO | E7: Previous Contingency | F7: Current Contingency | G7: Silsbee PO | H7: Previous Application | I7: Payment this period | J7: Total Complete & Draw To Date | L7: Balance remaining
B8: GL Coding | C8: Account Name | D8: Approved Budget | E8: Funding & Reallocation | F8: Funding & Reallocation | G8: Current Approved Budget | H8: Inception to 11/30/2025 | I8: 46022 | J8: Incurred to 12/31/2025 | K8: Percent Drawn | L8: As of 12/31/2025
B10: 40120 | C10: In & Out Fees | D10: 303525 | E10: 0 | F10: 0 | G10: =ROUND(D10+E10+F10,2) -> 303525 | H10: =ROUND(SUMIF('Prior Revenue Log (OP)'!B:B,'Budget to Actual (OP)'!C10,'Prior Revenue Log (OP)'!G:G),2) -> 66483 | I10: =ROUND(SUMIF('Current Revenue Log (OP)'!B:B,'Budget to Actual (OP)'!C10,'Current Revenue Log (OP)'!G:G),2) -> 0 | J10: =ROUND(SUM(H10:I10),2) -> 66483 | K10: =IFERROR(J10/G10,0) -> 0.21903632 | L10: =ROUND(+G10-J10,2) -> 237042
B11: 40130 | C11: Storage Fees | D11: 681507.2 | E11: 0 | F11: 0 | G11: =ROUND(D11+E11+F11,2) -> 681507.2 | H11: =ROUND(SUMIF('Prior Revenue Log (OP)'!B:B,'Budget to Actual (OP)'!C11,'Prior Revenue Log (OP)'!G:G),2) -> 588015 | I11: =ROUND(SUMIF('Current Revenue Log (OP)'!B:B,'Budget to Actual (OP)'!C11,'Current Revenue Log (OP)'!G:G),2) -> 0 | J11: =ROUND(SUM(H11:I11),2) -> 588015 | K11: =IFERROR(J11/G11,0) -> 0.86281554 | L11: =ROUND(+G11-J11,2) -> 93492.2
B12: 40140 | C12: Transloading Fees | D12: 0 | E12: 0 | F12: 0 | G12: =ROUND(D12+E12+F12,2) -> 0 | H12: =ROUND(SUMIF('Prior Revenue Log (OP)'!B:B,'Budget to Actual (OP)'!C12,'Prior Revenue Log (OP)'!G:G),2) -> 0 | I12: =ROUND(SUMIF('Current Revenue Log (OP)'!B:B,'Budget to Actual (OP)'!C12,'Current Revenue Log (OP)'!G:G),2) -> 0 | J12: =ROUND(SUM(H12:I12),2) -> 0 | K12: =IFERROR(J12/G12,0) -> 0 | L12: =ROUND(+G12-J12,2) -> 0
B13: 40160 | C13: Intra Plant Switch Fees | D13: 0 | E13: 0 | F13: 0 | G13: =ROUND(D13+E13+F13,2) -> 0 | H13: =ROUND(SUMIF('Prior Revenue Log (OP)'!B:B,'Budget to Actual (OP)'!C13,'Prior Revenue Log (OP)'!G:G),2) -> 0 | I13: =ROUND(SUMIF('Current Revenue Log (OP)'!B:B,'Budget to Actual (OP)'!C13,'Current Revenue Log (OP)'!G:G),2) -> 0 | J13: =ROUND(SUM(H13:I13),2) -> 0 | K13: =IFERROR(J13/G13,0) -> 0 | L13: =ROUND(+G13-J13,2) -> 0
B14: 40400 | C14: Concessions | D14: 0 | E14: 0 | F14: 0 | G14: =ROUND(D14+E14+F14,2) -> 0 | H14: =ROUND(SUMIF('Prior Revenue Log (OP)'!B:B,'Budget to Actual (OP)'!C14,'Prior Revenue Log (OP)'!G:G),2) -> 0 | I14: =ROUND(SUMIF('Current Revenue Log (OP)'!B:B,'Budget to Actual (OP)'!C14,'Current Revenue Log (OP)'!G:G),2) -> 0 | J14: =ROUND(SUM(H14:I14),2) -> 0 | K14: =IFERROR(J14/G14,0) -> 0 | L14: =ROUND(+G14-J14,2) -> 0
B15: 40451 | C15: Bad Debt | D15: 0 | E15: 0 | F15: 0 | G15: =ROUND(D15+E15+F15,2) -> 0 | H15: =ROUND(SUMIF('Prior Revenue Log (OP)'!B:B,'Budget to Actual (OP)'!C15,'Prior Revenue Log (OP)'!G:G),2) -> 0 | I15: =ROUND(SUMIF('Current Revenue Log (OP)'!B:B,'Budget to Actual (OP)'!C15,'Current Revenue Log (OP)'!G:G),2) -> 0 | J15: =ROUND(SUM(H15:I15),2) -> 0 | K15: =IFERROR(J15/G15,0) -> 0 | L15: =ROUND(+G15-J15,2) -> 0
C17: Total Rail Income | D17: =ROUND(SUBTOTAL(9,D10:D16),2) -> 985032.2 | E17: =ROUND(SUBTOTAL(9,E10:E16),2) -> 0 | F17: =ROUND(SUBTOTAL(9,F10:F16),2) -> 0 | G17: =ROUND(SUBTOTAL(9,G10:G16),2) -> 985032.2 | H17: =ROUND(SUBTOTAL(9,H10:H16),2) -> 654498 | I17: =ROUND(SUBTOTAL(9,I10:I16),2) -> 0 | J17: =ROUND(SUBTOTAL(9,J10:J16),2) -> 654498 | K17: =ROUND(SUBTOTAL(9,K10:K16),2) -> 1.08 | L17: =ROUND(SUBTOTAL(9,L10:L16),2) -> 330534.2
B18: 40110 | C18: Short Term Land Leases | D18: 138000 | E18: 0 | F18: 0 | G18: =ROUND(D18+E18+F18,2) -> 138000 | H18: =ROUND(SUMIF('Prior Revenue Log (OP)'!B:B,'Budget to Actual (OP)'!C18,'Prior Revenue Log (OP)'!G:G),2) -> 130360 | I18: =ROUND(SUMIF('Current Revenue Log (OP)'!B:B,'Budget to Actual (OP)'!C18,'Current Revenue Log (OP)'!G:G),2) -> 0 | J18: =ROUND(SUM(H18:I18),2) -> 130360 | K18: =IFERROR(J18/G18,0) -> 0.94463768 | L18: =ROUND(+G18-J18,2) -> 7640
B19: 40140 | C19: Intra-Plant Switch Fees | D19: 0 | E19: 0 | F19: 0 | G19: =ROUND(D19+E19+F19,2) -> 0 | H19: =ROUND(SUMIF('Prior Revenue Log (OP)'!B:B,'Budget to Actual (OP)'!C19,'Prior Revenue Log (OP)'!G:G),2) -> 0 | I19: =ROUND(SUMIF('Current Revenue Log (OP)'!B:B,'Budget to Actual (OP)'!C19,'Current Revenue Log (OP)'!G:G),2) -> 0 | J19: =ROUND(SUM(H19:I19),2) -> 0 | K19: =IFERROR(J19/G19,0) -> 0 | L19: =ROUND(+G19-J19,2) -> 0
B20: 40150 | C20: Warehouse Lease Income | D20: 700000 | E20: 0 | F20: 0 | G20: =ROUND(D20+E20+F20,2) -> 700000 | H20: =ROUND(SUMIF('Prior Revenue Log (OP)'!B:B,'Budget to Actual (OP)'!C20,'Prior Revenue Log (OP)'!G:G),2) -> 200000 | I20: =ROUND(SUMIF('Current Revenue Log (OP)'!B:B,'Budget to Actual (OP)'!C20,'Current Revenue Log (OP)'!G:G),2) -> 0 | J20: =ROUND(SUM(H20:I20),2) -> 200000 | K20: =IFERROR(J20/G20,0) -> 0.28571429 | L20: =ROUND(+G20-J20,2) -> 500000
B21: 40160 | C21: Transloading Fees | D21: 0 | E21: 0 | F21: 0 | G21: =ROUND(D21+E21+F21,2) -> 0 | H21: =ROUND(SUMIF('Prior Revenue Log (OP)'!B:B,'Budget to Actual (OP)'!C21,'Prior Revenue Log (OP)'!G:G),2) -> 0 | I21: =ROUND(SUMIF('Current Revenue Log (OP)'!B:B,'Budget to Actual (OP)'!C21,'Current Revenue Log (OP)'!G:G),2) -> 0 | J21: =ROUND(SUM(H21:I21),2) -> 0 | K21: =IFERROR(J21/G21,0) -> 0 | L21: =ROUND(+G21-J21,2) -> 0
B22: 41114 | C22: Late Fees | D22: 0 | E22: 0 | F22: 0 | G22: =ROUND(D22+E22+F22,2) -> 0 | H22: =ROUND(SUMIF('Prior Revenue Log (OP)'!B:B,'Budget to Actual (OP)'!C22,'Prior Revenue Log (OP)'!G:G),2) -> 0 | I22: =ROUND(SUMIF('Current Revenue Log (OP)'!B:B,'Budget to Actual (OP)'!C22,'Current Revenue Log (OP)'!G:G),2) -> 0 | J22: =ROUND(SUM(H22:I22),2) -> 0 | K22: =IFERROR(J22/G22,0) -> 0 | L22: =ROUND(+G22-J22,2) -> 0
C24: Total Other Income | D24: =ROUND(SUBTOTAL(9,D18:D23),2) -> 838000 | E24: =ROUND(SUBTOTAL(9,E18:E23),2) -> 0 | F24: =ROUND(SUBTOTAL(9,F18:F23),2) -> 0 | G24: =ROUND(SUBTOTAL(9,G18:G23),2) -> 838000 | H24: =ROUND(SUBTOTAL(9,H18:H23),2) -> 330360 | I24: =ROUND(SUBTOTAL(9,I18:I23),2) -> 0 | J24: =ROUND(SUBTOTAL(9,J18:J23),2) -> 330360 | K24: =IFERROR(J24/G24,0) -> 0.39422434 | L24: =ROUND(SUBTOTAL(9,L18:L23),2) -> 507640
C26: Total Income | D26: =ROUND(SUBTOTAL(9,D9:D25),2) -> 1823032.2 | E26: =ROUND(SUBTOTAL(9,E9:E25),2) -> 0 | F26: =ROUND(SUBTOTAL(9,F9:F25),2) -> 0 | G26: =ROUND(SUBTOTAL(9,G9:G25),2) -> 1823032.2 | H26: =ROUND(SUBTOTAL(9,H9:H25),2) -> 984858 | I26: =ROUND(SUBTOTAL(9,I9:I25),2) -> 0 | J26: =ROUND(SUBTOTAL(9,J9:J25),2) -> 984858 | K26: =IFERROR(J26/G26,0) -> 0.54023072 | L26: =ROUND(SUBTOTAL(9,L9:L25),2) -> 838174.2
B27: 63034 | C27: Switchmen Salaries - Reimbursable | D27: 147792.69 | E27: 0 | F27: 0 | G27: =ROUND(D27+E27+F27,2) -> 147792.69 | H27: =ROUND(SUMIF('Prior Invoice Log (OP)'!B:B,'Budget to Actual (OP)'!C27,'Prior Invoice Log (OP)'!H:H),2) -> 163556.67 | I27: =ROUND(SUMIF('Current Invoice Log (OP)'!B:B,C27,'Current Invoice Log (OP)'!H:H),2) -> 11560.34 | J27: =ROUND(SUM(H27:I27),2) -> 175117.01 | K27: =IFERROR(J27/G27,0) -> 1.1848828 | L27: =ROUND(+G27-J27,2) -> -27324.32
B28: 63032 | C28: Switchmen Healthcare – Reimbursable | D28: 0 | E28: 0 | F28: 0 | G28: =ROUND(D28+E28+F28,2) -> 0 | H28: =ROUND(SUMIF('Prior Invoice Log (OP)'!B:B,'Budget to Actual (OP)'!C28,'Prior Invoice Log (OP)'!H:H),2) -> 0 | I28: =ROUND(SUMIF('Current Invoice Log (OP)'!B:B,C28,'Current Invoice Log (OP)'!H:H),2) -> 0 | J28: =ROUND(SUM(H28:I28),2) -> 0 | K28: =IFERROR(J28/G28,0) -> 0 | L28: =ROUND(+G28-J28,2) -> 0
B29: 63033 | C29: Mowing Assistance - Reimbursable | D29: 36000 | E29: 0 | F29: 0 | G29: =ROUND(D29+E29+F29,2) -> 36000 | H29: =ROUND(SUMIF('Prior Invoice Log (OP)'!B:B,'Budget to Actual (OP)'!C29,'Prior Invoice Log (OP)'!H:H),2) -> 17150 | I29: =ROUND(SUMIF('Current Invoice Log (OP)'!B:B,C29,'Current Invoice Log (OP)'!H:H),2) -> 0 | J29: =ROUND(SUM(H29:I29),2) -> 17150 | K29: =IFERROR(J29/G29,0) -> 0.47638889 | L29: =ROUND(+G29-J29,2) -> 18850
B30: 63041 | C30: Onsite Manager | D30: 101165.26 | E30: 0 | F30: 0 | G30: =ROUND(D30+E30+F30,2) -> 101165.26 | H30: =ROUND(SUMIF('Prior Invoice Log (OP)'!B:B,'Budget to Actual (OP)'!C30,'Prior Invoice Log (OP)'!H:H),2) -> 0 | I30: =ROUND(SUMIF('Current Invoice Log (OP)'!B:B,C30,'Current Invoice Log (OP)'!H:H),2) -> 0 | J30: =ROUND(SUM(H30:I30),2) -> 0 | K30: =IFERROR(J30/G30,0) -> 0 | L30: =ROUND(+G30-J30,2) -> 101165.26
B31: 63042 | C31: Overtime | D31: 18000 | E31: 0 | F31: 0 | G31: =ROUND(D31+E31+F31,2) -> 18000 | H31: =ROUND(SUMIF('Prior Invoice Log (OP)'!B:B,'Budget to Actual (OP)'!C31,'Prior Invoice Log (OP)'!H:H),2) -> 0 | I31: =ROUND(SUMIF('Current Invoice Log (OP)'!B:B,C31,'Current Invoice Log (OP)'!H:H),2) -> 0 | J31: =ROUND(SUM(H31:I31),2) -> 0 | K31: =IFERROR(J31/G31,0) -> 0 | L31: =ROUND(+G31-J31,2) -> 18000
B32: 64000 | C32: Security | D32: 80004 | E32: 0 | F32: 0 | G32: =ROUND(D32+E32+F32,2) -> 80004 | H32: =ROUND(SUMIF('Prior Invoice Log (OP)'!B:B,'Budget to Actual (OP)'!C32,'Prior Invoice Log (OP)'!H:H),2) -> 82034.61 | I32: =ROUND(SUMIF('Current Invoice Log (OP)'!B:B,C32,'Current Invoice Log (OP)'!H:H),2) -> 6245.3 | J32: =ROUND(SUM(H32:I32),2) -> 88279.91 | K32: =IFERROR(J32/G32,0) -> 1.1034437 | L32: =ROUND(+G32-J32,2) -> -8275.91
B33: 63028 | C33: Asset Manager - (County Line) | D33: 22500 | E33: 0 | F33: 0 | G33: =ROUND(D33+E33+F33,2) -> 22500 | H33: =ROUND(SUMIF('Prior Invoice Log (OP)'!B:B,'Budget to Actual (OP)'!C33,'Prior Invoice Log (OP)'!H:H),2) -> 13125 | I33: =ROUND(SUMIF('Current Invoice Log (OP)'!B:B,C33,'Current Invoice Log (OP)'!H:H),2) -> 0 | J33: =ROUND(SUM(H33:I33),2) -> 13125 | K33: =IFERROR(J33/G33,0) -> 0.58333333 | L33: =ROUND(+G33-J33,2) -> 9375
B34: 63036 | C34: Accounting (County Line) | D34: 22500 | E34: 0 | F34: 0 | G34: =ROUND(D34+E34+F34,2) -> 22500 | H34: =ROUND(SUMIF('Prior Invoice Log (OP)'!B:B,'Budget to Actual (OP)'!C34,'Prior Invoice Log (OP)'!H:H),2) -> 13125 | I34: =ROUND(SUMIF('Current Invoice Log (OP)'!B:B,C34,'Current Invoice Log (OP)'!H:H),2) -> 0 | J34: =ROUND(SUM(H34:I34),2) -> 13125 | K34: =IFERROR(J34/G34,0) -> 0.58333333 | L34: =ROUND(+G34-J34,2) -> 9375
B35: 63040 | C35: Business Development (County Line) | D35: 60000 | E35: 0 | F35: 0 | G35: =ROUND(D35+E35+F35,2) -> 60000 | H35: =ROUND(SUMIF('Prior Invoice Log (OP)'!B:B,'Budget to Actual (OP)'!C35,'Prior Invoice Log (OP)'!H:H),2) -> 35000 | I35: =ROUND(SUMIF('Current Invoice Log (OP)'!B:B,C35,'Current Invoice Log (OP)'!H:H),2) -> 0 | J35: =ROUND(SUM(H35:I35),2) -> 35000 | K35: =IFERROR(J35/G35,0) -> 0.58333333 | L35: =ROUND(+G35-J35,2) -> 25000
B36: 63041 | C36: Offsite Manager | D36: 0 | E36: 0 | F36: 0 | G36: =ROUND(D36+E36+F36,2) -> 0 | H36: =ROUND(SUMIF('Prior Invoice Log (OP)'!B:B,'Budget to Actual (OP)'!C36,'Prior Invoice Log (OP)'!H:H),2) -> 18592.12 | I36: =ROUND(SUMIF('Current Invoice Log (OP)'!B:B,C36,'Current Invoice Log (OP)'!H:H),2) -> -1603.53 | J36: =ROUND(SUM(H36:I36),2) -> 16988.59 | K36: =IFERROR(J36/G36,0) -> 0 | L36: =ROUND(+G36-J36,2) -> -16988.59
B37: 63042 | C37: Offsite Staff | D37: 0 | E37: 0 | F37: 0 | G37: =ROUND(D37+E37+F37,2) -> 0 | H37: =ROUND(SUMIF('Prior Invoice Log (OP)'!B:B,'Budget to Actual (OP)'!C37,'Prior Invoice Log (OP)'!H:H),2) -> 51130.03 | I37: =ROUND(SUMIF('Current Invoice Log (OP)'!B:B,C37,'Current Invoice Log (OP)'!H:H),2) -> 10116.6 | J37: =ROUND(SUM(H37:I37),2) -> 61246.63 | K37: =IFERROR(J37/G37,0) -> 0 | L37: =ROUND(+G37-J37,2) -> -61246.63 | M37: <-- Non-Budgeted Item
C39: Total Payroll | D39: =ROUND(SUBTOTAL(9,D27:D38),2) -> 487961.95 | E39: =ROUND(SUBTOTAL(9,E27:E38),2) -> 0 | F39: =ROUND(SUBTOTAL(9,F27:F38),2) -> 0 | G39: =ROUND(SUBTOTAL(9,G27:G38),2) -> 487961.95 | H39: =ROUND(SUBTOTAL(9,H27:H38),2) -> 393713.43 | I39: =ROUND(SUBTOTAL(9,I27:I38),2) -> 26318.71 | J39: =ROUND(SUBTOTAL(9,J27:J38),2) -> 420032.14 | K39: =IFERROR(J39/G39,0) -> 0.86078872 | L39: =ROUND(SUBTOTAL(9,L27:L38),2) -> 67929.81
B40: 63025 | C40: Professional Fees | D40: 0 | E40: 0 | F40: 0 | G40: =ROUND(D40+E40+F40,2) -> 0 | H40: =ROUND(SUMIF('Prior Invoice Log (OP)'!B:B,'Budget to Actual (OP)'!C40,'Prior Invoice Log (OP)'!H:H),2) -> 7141.37 | I40: =ROUND(SUMIF('Current Invoice Log (OP)'!B:B,C40,'Current Invoice Log (OP)'!H:H),2) -> 1.25 | J40: =ROUND(SUM(H40:I40),2) -> 7142.62 | K40: =IFERROR(J40/G40,0) -> 0 | L40: =ROUND(+G40-J40,2) -> -7142.62 | M40: <-- Non-Budgeted Item
B41: 63050 | C41: Legal Fees | D41: 18000 | E41: 0 | F41: 0 | G41: =ROUND(D41+E41+F41,2) -> 18000 | H41: =ROUND(SUMIF('Prior Invoice Log (OP)'!B:B,'Budget to Actual (OP)'!C41,'Prior Invoice Log (OP)'!H:H),2) -> 66630.31 | I41: =ROUND(SUMIF('Current Invoice Log (OP)'!B:B,C41,'Current Invoice Log (OP)'!H:H),2) -> 0 | J41: =ROUND(SUM(H41:I41),2) -> 66630.31 | K41: =IFERROR(J41/G41,0) -> 3.7016839 | L41: =ROUND(+G41-J41,2) -> -48630.31
B42: 63100 | C42: Consulting Fees | D42: 10000 | E42: 0 | F42: 0 | G42: =ROUND(D42+E42+F42,2) -> 10000 | H42: =ROUND(SUMIF('Prior Invoice Log (OP)'!B:B,'Budget to Actual (OP)'!C42,'Prior Invoice Log (OP)'!H:H),2) -> 17876.26 | I42: =ROUND(SUMIF('Current Invoice Log (OP)'!B:B,C42,'Current Invoice Log (OP)'!H:H),2) -> 0 | J42: =ROUND(SUM(H42:I42),2) -> 17876.26 | K42: =IFERROR(J42/G42,0) -> 1.787626 | L42: =ROUND(+G42-J42,2) -> -7876.26
B43: 67100 | C43: Dues & Subscriptions | D43: 0 | E43: 0 | F43: 0 | G43: =ROUND(D43+E43+F43,2) -> 0 | H43: =ROUND(SUMIF('Prior Invoice Log (OP)'!B:B,'Budget to Actual (OP)'!C43,'Prior Invoice Log (OP)'!H:H),2) -> 1560 | I43: =ROUND(SUMIF('Current Invoice Log (OP)'!B:B,C43,'Current Invoice Log (OP)'!H:H),2) -> 0 | J43: =ROUND(SUM(H43:I43),2) -> 1560 | K43: =IFERROR(J43/G43,0) -> 0 | L43: =ROUND(+G43-J43,2) -> -1560
B44: 67200 | C44: Office Expense | D44: 12000 | E44: 0 | F44: 0 | G44: =ROUND(D44+E44+F44,2) -> 12000 | H44: =ROUND(SUMIF('Prior Invoice Log (OP)'!B:B,'Budget to Actual (OP)'!C44,'Prior Invoice Log (OP)'!H:H),2) -> 3099.65 | I44: =ROUND(SUMIF('Current Invoice Log (OP)'!B:B,C44,'Current Invoice Log (OP)'!H:H),2) -> 366.67 | J44: =ROUND(SUM(H44:I44),2) -> 3466.32 | K44: =IFERROR(J44/G44,0) -> 0.28886 | L44: =ROUND(+G44-J44,2) -> 8533.68
B45: 67250 | C45: Postage and Delivery | D45: 600 | E45: 0 | F45: 0 | G45: =ROUND(D45+E45+F45,2) -> 600 | H45: =ROUND(SUMIF('Prior Invoice Log (OP)'!B:B,'Budget to Actual (OP)'!C45,'Prior Invoice Log (OP)'!H:H),2) -> 0 | I45: =ROUND(SUMIF('Current Invoice Log (OP)'!B:B,C45,'Current Invoice Log (OP)'!H:H),2) -> 0 | J45: =ROUND(SUM(H45:I45),2) -> 0 | K45: =IFERROR(J45/G45,0) -> 0 | L45: =ROUND(+G45-J45,2) -> 600
B46: 67300 | C46: Telephone & Internet | D46: 1200 | E46: 0 | F46: 0 | G46: =ROUND(D46+E46+F46,2) -> 1200 | H46: =ROUND(SUMIF('Prior Invoice Log (OP)'!B:B,'Budget to Actual (OP)'!C46,'Prior Invoice Log (OP)'!H:H),2) -> 0 | I46: =ROUND(SUMIF('Current Invoice Log (OP)'!B:B,C46,'Current Invoice Log (OP)'!H:H),2) -> 0 | J46: =ROUND(SUM(H46:I46),2) -> 0 | K46: =IFERROR(J46/G46,0) -> 0 | L46: =ROUND(+G46-J46,2) -> 1200
B47: 67400 | C47: Advertising & Marketing | D47: 12000 | E47: 0 | F47: 0 | G47: =ROUND(D47+E47+F47,2) -> 12000 | H47: =ROUND(SUMIF('Prior Invoice Log (OP)'!B:B,'Budget to Actual (OP)'!C47,'Prior Invoice Log (OP)'!H:H),2) -> 0 | I47: =ROUND(SUMIF('Current Invoice Log (OP)'!B:B,C47,'Current Invoice Log (OP)'!H:H),2) -> 0 | J47: =ROUND(SUM(H47:I47),2) -> 0 | K47: =IFERROR(J47/G47,0) -> 0 | L47: =ROUND(+G47-J47,2) -> 12000
B48: 68110 | C48: Bank Fees | D48: 500 | E48: 0 | F48: 0 | G48: =ROUND(D48+E48+F48,2) -> 500 | H48: =ROUND(SUMIF('Prior Invoice Log (OP)'!B:B,'Budget to Actual (OP)'!C48,'Prior Invoice Log (OP)'!H:H),2) -> 910 | I48: =ROUND(SUMIF('Current Invoice Log (OP)'!B:B,C48,'Current Invoice Log (OP)'!H:H),2) -> 0 | J48: =ROUND(SUM(H48:I48),2) -> 910 | K48: =IFERROR(J48/G48,0) -> 1.82 | L48: =ROUND(+G48-J48,2) -> -410
C49: Inventory Management | D49: 0 | E49: 0 | F49: 0 | G49: =ROUND(D49+E49+F49,2) -> 0 | H49: =ROUND(SUMIF('Prior Invoice Log (OP)'!B:B,'Budget to Actual (OP)'!C49,'Prior Invoice Log (OP)'!H:H),2) -> 0 | I49: =ROUND(SUMIF('Current Invoice Log (OP)'!B:B,C49,'Current Invoice Log (OP)'!H:H),2) -> 0 | J49: =ROUND(SUM(H49:I49),2) -> 0 | K49: =IFERROR(J49/G49,0) -> 0 | L49: =ROUND(+G49-J49,2) -> 0
B50: 63000 | C50: Accounting Fees | D50: 65688 | E50: 0 | F50: 0 | G50: =ROUND(D50+E50+F50,2) -> 65688 | H50: =ROUND(SUMIF('Prior Invoice Log (OP)'!B:B,'Budget to Actual (OP)'!C50,'Prior Invoice Log (OP)'!H:H),2) -> 52091.38 | I50: =ROUND(SUMIF('Current Invoice Log (OP)'!B:B,C50,'Current Invoice Log (OP)'!H:H),2) -> 0 | J50: =ROUND(SUM(H50:I50),2) -> 52091.38 | K50: =IFERROR(J50/G50,0) -> 0.79301212 | L50: =ROUND(+G50-J50,2) -> 13596.62
B51: 60210 | C51: Travel | D51: 0 | E51: 0 | F51: 0 | G51: =ROUND(D51+E51+F51,2) -> 0 | H51: =ROUND(SUMIF('Prior Invoice Log (OP)'!B:B,'Budget to Actual (OP)'!C51,'Prior Invoice Log (OP)'!H:H),2) -> 7744.65 | I51: =ROUND(SUMIF('Current Invoice Log (OP)'!B:B,'Budget to Actual (OP)'!C51,'Current Invoice Log (OP)'!H:H),2) -> 217.32 | J51: =ROUND(SUM(H51:I51),2) -> 7961.97 | K51: =IFERROR(J51/G51,0) -> 0 | L51: =ROUND(+G51-J51,2) -> -7961.97 | M51: <-- Non-Budgeted Item
B52: 60500 | C52: Meals | D52: 0 | E52: 0 | F52: 0 | G52: =ROUND(D52+E52+F52,2) -> 0 | H52: =ROUND(SUMIF('Prior Invoice Log (OP)'!B:B,'Budget to Actual (OP)'!C52,'Prior Invoice Log (OP)'!H:H),2) -> 546.54 | I52: =ROUND(SUMIF('Current Invoice Log (OP)'!B:B,'Budget to Actual (OP)'!C52,'Current Invoice Log (OP)'!H:H),2) -> 158.16 | J52: =ROUND(SUM(H52:I52),2) -> 704.7 | K52: =IFERROR(J52/G52,0) -> 0 | L52: =ROUND(+G52-J52,2) -> -704.7 | M52: <-- Non-Budgeted Item
C54: Total Admin | D54: =ROUND(SUBTOTAL(9,D40:D53),2) -> 119988 | E54: =ROUND(SUBTOTAL(9,E40:E53),2) -> 0 | F54: =ROUND(SUBTOTAL(9,F40:F53),2) -> 0 | G54: =ROUND(SUBTOTAL(9,G41:G53),2) -> 119988 | H54: =ROUND(SUBTOTAL(9,H41:H53),2) -> 150458.79 | I54: =ROUND(SUBTOTAL(9,I41:I53),2) -> 742.15 | J54: =ROUND(SUBTOTAL(9,J41:J53),2) -> 151200.94 | K54: =IFERROR(J54/G54,0) -> 1.2601338 | L54: =ROUND(SUBTOTAL(9,L41:L53),2) -> -31212.94
B55: 61051 | C55: Track Repairs | D55: 20000 | E55: 0 | F55: 0 | G55: =ROUND(D55+E55+F55,2) -> 20000 | H55: =ROUND(SUMIF('Prior Invoice Log (OP)'!B:B,'Budget to Actual (OP)'!C55,'Prior Invoice Log (OP)'!H:H),2) -> 1775 | I55: =ROUND(SUMIF('Current Invoice Log (OP)'!B:B,C55,'Current Invoice Log (OP)'!H:H),2) -> 0 | J55: =ROUND(SUM(H55:I55),2) -> 1775 | K55: =IFERROR(J55/G55,0) -> 0.08875 | L55: =ROUND(+G55-J55,2) -> 18225
C56: Switch Repairs | E56: 0 | F56: 0 | G56: =ROUND(D56+E56+F56,2) -> 0 | H56: =ROUND(SUMIF('Prior Invoice Log (OP)'!B:B,'Budget to Actual (OP)'!C56,'Prior Invoice Log (OP)'!H:H),2) -> 0 | I56: =ROUND(SUMIF('Current Invoice Log (OP)'!B:B,C56,'Current Invoice Log (OP)'!H:H),2) -> 0 | J56: =ROUND(SUM(H56:I56),2) -> 0 | K56: =IFERROR(J56/G56,0) -> 0 | L56: =ROUND(+G56-J56,2) -> 0
B57: 61052 | C57: Crossing Repairs | D57: 20004 | E57: 0 | F57: 0 | G57: =ROUND(D57+E57+F57,2) -> 20004 | H57: =ROUND(SUMIF('Prior Invoice Log (OP)'!B:B,'Budget to Actual (OP)'!C57,'Prior Invoice Log (OP)'!H:H),2) -> 9164 | I57: =ROUND(SUMIF('Current Invoice Log (OP)'!B:B,C57,'Current Invoice Log (OP)'!H:H),2) -> 700 | J57: =ROUND(SUM(H57:I57),2) -> 9864 | K57: =IFERROR(J57/G57,0) -> 0.49310138 | L57: =ROUND(+G57-J57,2) -> 10140
B58: 61054 | C58: Locomotive Repair | D58: 18000 | E58: 0 | F58: 0 | G58: =ROUND(D58+E58+F58,2) -> 18000 | H58: =ROUND(SUMIF('Prior Invoice Log (OP)'!B:B,'Budget to Actual (OP)'!C58,'Prior Invoice Log (OP)'!H:H),2) -> 0 | I58: =ROUND(SUMIF('Current Invoice Log (OP)'!B:B,C58,'Current Invoice Log (OP)'!H:H),2) -> 0 | J58: =ROUND(SUM(H58:I58),2) -> 0 | K58: =IFERROR(J58/G58,0) -> 0 | L58: =ROUND(+G58-J58,2) -> 18000
B59: 61056 | C59: Landscape Maintenance | D59: 0 | E59: 0 | F59: 0 | G59: =ROUND(D59+E59+F59,2) -> 0 | H59: =ROUND(SUMIF('Prior Invoice Log (OP)'!B:B,'Budget to Actual (OP)'!C59,'Prior Invoice Log (OP)'!H:H),2) -> 12500 | I59: =ROUND(SUMIF('Current Invoice Log (OP)'!B:B,C59,'Current Invoice Log (OP)'!H:H),2) -> 2500 | J59: =ROUND(SUM(H59:I59),2) -> 15000 | K59: =IFERROR(J59/G59,0) -> 0 | L59: =ROUND(+G59-J59,2) -> -15000 | M59: <-- Non-Budgeted Item
B60: 61050 | C60: Site/Yard Maintenace | D60: 30000 | E60: 0 | F60: 0 | G60: =ROUND(D60+E60+F60,2) -> 30000 | H60: =ROUND(SUMIF('Prior Invoice Log (OP)'!B:B,'Budget to Actual (OP)'!C60,'Prior Invoice Log (OP)'!H:H),2) -> 7444.67 | I60: =ROUND(SUMIF('Current Invoice Log (OP)'!B:B,C60,'Current Invoice Log (OP)'!H:H),2) -> 1061.6 | J60: =ROUND(SUM(H60:I60),2) -> 8506.27 | K60: =IFERROR(J60/G60,0) -> 0.28354233 | L60: =ROUND(+G60-J60,2) -> 21493.73
C61: Road Repairs | D61: 3000 | E61: 0 | F61: 0 | G61: =ROUND(D61+E61+F61,2) -> 3000 | H61: =ROUND(SUMIF('Prior Invoice Log (OP)'!B:B,'Budget to Actual (OP)'!C61,'Prior Invoice Log (OP)'!H:H),2) -> 0 | I61: =ROUND(SUMIF('Current Invoice Log (OP)'!B:B,C61,'Current Invoice Log (OP)'!H:H),2) -> 0 | J61: =ROUND(SUM(H61:I61),2) -> 0 | K61: =IFERROR(J61/G61,0) -> 0 | L61: =ROUND(+G61-J61,2) -> 3000
C62: Vehicle Repairs | D62: 0 | E62: 0 | F62: 0 | G62: =ROUND(D62+E62+F62,2) -> 0 | H62: =ROUND(SUMIF('Prior Invoice Log (OP)'!B:B,'Budget to Actual (OP)'!C62,'Prior Invoice Log (OP)'!H:H),2) -> 0 | I62: =ROUND(SUMIF('Current Invoice Log (OP)'!B:B,C62,'Current Invoice Log (OP)'!H:H),2) -> 0 | J62: =ROUND(SUM(H62:I62),2) -> 0 | K62: =IFERROR(J62/G62,0) -> 0 | L62: =ROUND(+G62-J62,2) -> 0
C63: Other Repairs | D63: 0 | E63: 0 | F63: 0 | G63: =ROUND(D63+E63+F63,2) -> 0 | H63: =ROUND(SUMIF('Prior Invoice Log (OP)'!B:B,'Budget to Actual (OP)'!C63,'Prior Invoice Log (OP)'!H:H),2) -> 0 | I63: =ROUND(SUMIF('Current Invoice Log (OP)'!B:B,C63,'Current Invoice Log (OP)'!H:H),2) -> 0 | J63: =ROUND(SUM(H63:I63),2) -> 0 | K63: =IFERROR(J63/G63,0) -> 0 | L63: =ROUND(+G63-J63,2) -> 0
C65: Total Maintenance | D65: =ROUND(SUBTOTAL(9,D55:D64),2) -> 91004 | E65: =ROUND(SUBTOTAL(9,E55:E64),2) -> 0 | F65: =ROUND(SUBTOTAL(9,F55:F64),2) -> 0 | G65: =ROUND(SUBTOTAL(9,G55:G64),2) -> 91004 | H65: =ROUND(SUBTOTAL(9,H55:H64),2) -> 30883.67 | I65: =ROUND(SUBTOTAL(9,I55:I64),2) -> 4261.6 | J65: =ROUND(SUBTOTAL(9,J55:J64),2) -> 35145.27 | K65: =IFERROR(J65/G65,0) -> 0.38619478 | L65: =ROUND(SUBTOTAL(9,L55:L64),2) -> 55858.73
B66: 61164 | C66: Fuel | D66: 30000 | E66: 0 | F66: 0 | G66: =ROUND(D66+E66+F66,2) -> 30000 | H66: =ROUND(SUMIF('Prior Invoice Log (OP)'!B:B,'Budget to Actual (OP)'!C66,'Prior Invoice Log (OP)'!H:H),2) -> 8554.35 | I66: =ROUND(SUMIF('Current Invoice Log (OP)'!B:B,C66,'Current Invoice Log (OP)'!H:H),2) -> 3969.31 | J66: =ROUND(SUM(H66:I66),2) -> 12523.66 | K66: =IFERROR(J66/G66,0) -> 0.41745533 | L66: =ROUND(+G66-J66,2) -> 17476.34
C67: Locomotive Lease | D67: 0 | E67: 0 | F67: 0 | G67: =ROUND(D67+E67+F67,2) -> 0 | H67: =ROUND(SUMIF('Prior Invoice Log (OP)'!B:B,'Budget to Actual (OP)'!C67,'Prior Invoice Log (OP)'!H:H),2) -> 0 | I67: =ROUND(SUMIF('Current Invoice Log (OP)'!B:B,C67,'Current Invoice Log (OP)'!H:H),2) -> 0 | J67: =ROUND(SUM(H67:I67),2) -> 0 | K67: =IFERROR(J67/G67,0) -> 0 | L67: =ROUND(+G67-J67,2) -> 0
B68: 68105 | C68: Demurrage Charges | D68: 0 | E68: 0 | F68: 0 | G68: =ROUND(D68+E68+F68,2) -> 0 | H68: =ROUND(SUMIF('Prior Invoice Log (OP)'!B:B,'Budget to Actual (OP)'!C68,'Prior Invoice Log (OP)'!H:H),2) -> 0 | I68: =ROUND(SUMIF('Current Invoice Log (OP)'!B:B,C68,'Current Invoice Log (OP)'!H:H),2) -> 0 | J68: =ROUND(SUM(H68:I68),2) -> 0 | K68: =IFERROR(J68/G68,0) -> 0 | L68: =ROUND(+G68-J68,2) -> 0
C69: (Other) | D69: 0 | E69: 0 | G69: =ROUND(D69+E69+F69,2) -> 0 | H69: =ROUND(SUMIF('Prior Invoice Log (OP)'!B:B,'Budget to Actual (OP)'!C69,'Prior Invoice Log (OP)'!H:H),2) -> 0 | I69: =ROUND(SUMIF('Current Invoice Log (OP)'!B:B,C69,'Current Invoice Log (OP)'!H:H),2) -> 0 | J69: =ROUND(SUM(H69:I69),2) -> 0 | K69: =IFERROR(J69/G69,0) -> 0 | L69: =ROUND(+G69-J69,2) -> 0
C71: Total Service/Operating Expenses | D71: =ROUND(SUBTOTAL(9,D66:D70),2) -> 30000 | E71: =ROUND(SUBTOTAL(9,E66:E70),2) -> 0 | F71: =ROUND(SUBTOTAL(9,F66:F70),2) -> 0 | G71: =ROUND(SUBTOTAL(9,G66:G70),2) -> 30000 | H71: =ROUND(SUBTOTAL(9,H66:H70),2) -> 8554.35 | I71: =ROUND(SUBTOTAL(9,I66:I70),2) -> 3969.31 | J71: =ROUND(SUBTOTAL(9,J66:J70),2) -> 12523.66 | K71: =IFERROR(J71/G71,0) -> 0.41745533 | L71: =ROUND(SUBTOTAL(9,L66:L70),2) -> 17476.34
B72: 63026 | C72: Management Fees - Hall Logistics | D72: 123643.22 | E72: 0 | F72: 0 | G72: =ROUND(D72+E72+F72,2) -> 123643.22 | H72: =ROUND(SUMIF('Prior Invoice Log (OP)'!B:B,'Budget to Actual (OP)'!C72,'Prior Invoice Log (OP)'!H:H),2) -> 45640.01 | I72: =ROUND(SUMIF('Current Invoice Log (OP)'!B:B,C72,'Current Invoice Log (OP)'!H:H),2) -> 0 | J72: =ROUND(SUM(H72:I72),2) -> 45640.01 | K72: =IFERROR(J72/G72,0) -> 0.36912667 | L72: =ROUND(+G72-J72,2) -> 78003.21
B73: 63038 | C73: Management Fees - County Line | D73: 0 | E73: 0 | F73: 0 | G73: =ROUND(D73+E73+F73,2) -> 0 | H73: =ROUND(SUMIF('Prior Invoice Log (OP)'!B:B,'Budget to Actual (OP)'!C73,'Prior Invoice Log (OP)'!H:H),2) -> 0 | I73: =ROUND(SUMIF('Current Invoice Log (OP)'!B:B,C73,'Current Invoice Log (OP)'!H:H),2) -> 0 | J73: =ROUND(SUM(H73:I73),2) -> 0 | K73: =IFERROR(J73/G73,0) -> 0 | L73: =ROUND(+G73-J73,2) -> 0
B74: 63027 | C74: AM Fees - Banyan | D74: 150000 | E74: 0 | F74: 0 | G74: =ROUND(D74+E74+F74,2) -> 150000 | H74: =ROUND(SUMIF('Prior Invoice Log (OP)'!B:B,'Budget to Actual (OP)'!C74,'Prior Invoice Log (OP)'!H:H),2) -> 115915.95 | I74: =ROUND(SUMIF('Current Invoice Log (OP)'!B:B,C74,'Current Invoice Log (OP)'!H:H),2) -> 5683.19 | J74: =ROUND(SUM(H74:I74),2) -> 121599.14 | K74: =IFERROR(J74/G74,0) -> 0.81066093 | L74: =ROUND(+G74-J74,2) -> 28400.86
C76: Total AM/Mgmt. Fees | D76: =ROUND(SUBTOTAL(9,D72:D75),2) -> 273643.22 | E76: =ROUND(SUBTOTAL(9,E72:E75),2) -> 0 | F76: =ROUND(SUBTOTAL(9,F72:F75),2) -> 0 | G76: =ROUND(SUBTOTAL(9,G72:G75),2) -> 273643.22 | H76: =ROUND(SUBTOTAL(9,H72:H75),2) -> 161555.96 | I76: =ROUND(SUBTOTAL(9,I72:I75),2) -> 5683.19 | J76: =ROUND(SUBTOTAL(9,J72:J75),2) -> 167239.15 | K76: =IFERROR(J76/G76,0) -> 0.61115766 | L76: =ROUND(SUBTOTAL(9,L72:L75),2) -> 106404.07
C78: Total Variable Expenses | D78: =ROUND(SUBTOTAL(9,D27:D77),2) -> 1002597.2 | E78: =ROUND(SUBTOTAL(9,E27:E77),2) -> 0 | F78: =ROUND(SUBTOTAL(9,F27:F77),2) -> 0 | G78: =ROUND(SUBTOTAL(9,G27:G77),2) -> 1002597.2 | H78: =ROUND(SUBTOTAL(9,H27:H77),2) -> 752307.57 | I78: =ROUND(SUBTOTAL(9,I27:I77),2) -> 40976.21 | J78: =ROUND(SUBTOTAL(9,J27:J77),2) -> 793283.78 | K78: =IFERROR(J78/G78,0) -> 0.79122882 | L78: =ROUND(SUBTOTAL(9,L27:L77),2) -> 209313.39
B79: 68060 | C79: State and Local Taxes | D79: 0 | E79: 0 | F79: 0 | G79: =ROUND(D79+E79+F79,2) -> 0 | H79: =ROUND(SUMIF('Prior Invoice Log (OP)'!B:B,'Budget to Actual (OP)'!C79,'Prior Invoice Log (OP)'!H:H),2) -> 0 | I79: =ROUND(SUMIF('Current Invoice Log (OP)'!B:B,C79,'Current Invoice Log (OP)'!H:H),2) -> 0 | J79: =ROUND(SUM(H79:I79),2) -> 0 | K79: =IFERROR(J79/G79,0) -> 0 | L79: =ROUND(+G79-J79,2) -> 0
B80: 68050 | C80: Property Tax | D80: 115315.76 | E80: 0 | F80: 0 | G80: =ROUND(D80+E80+F80,2) -> 115315.76 | H80: =ROUND(SUMIF('Prior Invoice Log (OP)'!B:B,'Budget to Actual (OP)'!C80,'Prior Invoice Log (OP)'!H:H),2) -> 97743.52 | I80: =ROUND(SUMIF('Current Invoice Log (OP)'!B:B,C80,'Current Invoice Log (OP)'!H:H),2) -> -7962.63 | J80: =ROUND(SUM(H80:I80),2) -> 89780.89 | K80: =IFERROR(J80/G80,0) -> 0.77856565 | L80: =ROUND(+G80-J80,2) -> 25534.87
C81: Builder's Risk Insurance | D81: 0 | E81: 0 | F81: 0 | G81: =ROUND(D81+E81+F81,2) -> 0 | H81: =ROUND(SUMIF('Prior Invoice Log (OP)'!B:B,'Budget to Actual (OP)'!C81,'Prior Invoice Log (OP)'!H:H),2) -> 0 | I81: =ROUND(SUMIF('Current Invoice Log (OP)'!B:B,C81,'Current Invoice Log (OP)'!H:H),2) -> 0 | J81: =ROUND(SUM(H81:I81),2) -> 0 | K81: =IFERROR(J81/G81,0) -> 0 | L81: =ROUND(+G81-J81,2) -> 0
B82: 68055 | C82: Property Insurance | D82: 191276.8 | E82: 0 | F82: 0 | G82: =ROUND(D82+E82+F82,2) -> 191276.8 | H82: =ROUND(SUMIF('Prior Invoice Log (OP)'!B:B,'Budget to Actual (OP)'!C82,'Prior Invoice Log (OP)'!H:H),2) -> 229659.38 | I82: =ROUND(SUMIF('Current Invoice Log (OP)'!B:B,C82,'Current Invoice Log (OP)'!H:H),2) -> 27093.47 | J82: =ROUND(SUM(H82:I82),2) -> 256752.85 | K82: =IFERROR(J82/G82,0) -> 1.3423105 | L82: =ROUND(+G82-J82,2) -> -65476.05
B83: 65000 | C83: Insurance - Liability | D83: 0 | E83: 0 | F83: 0 | G83: =ROUND(D83+E83+F83,2) -> 0 | H83: =ROUND(SUMIF('Prior Invoice Log (OP)'!B:B,'Budget to Actual (OP)'!C83,'Prior Invoice Log (OP)'!H:H),2) -> 0 | I83: =ROUND(SUMIF('Current Invoice Log (OP)'!B:B,C83,'Current Invoice Log (OP)'!H:H),2) -> 0 | J83: =ROUND(SUM(H83:I83),2) -> 0 | K83: =IFERROR(J83/G83,0) -> 0 | L83: =ROUND(+G83-J83,2) -> 0
B84: 61150 | C84: Utilities | D84: 26100 | E84: 0 | F84: 0 | G84: =ROUND(D84+E84+F84,2) -> 26100 | H84: =ROUND(SUMIF('Prior Invoice Log (OP)'!B:B,'Budget to Actual (OP)'!C84,'Prior Invoice Log (OP)'!H:H),2) -> 36198.22 | I84: =ROUND(SUMIF('Current Invoice Log (OP)'!B:B,C84,'Current Invoice Log (OP)'!H:H),2) -> 1184.69 | J84: =ROUND(SUM(H84:I84),2) -> 37382.91 | K84: =IFERROR(J84/G84,0) -> 1.4322954 | L84: =ROUND(+G84-J84,2) -> -11282.91
C86: Total Fixed Expenses | D86: =ROUND(SUBTOTAL(9,D79:D85),2) -> 332692.56 | E86: =ROUND(SUBTOTAL(9,E79:E85),2) -> 0 | F86: =ROUND(SUBTOTAL(9,F79:F85),2) -> 0 | G86: =ROUND(SUBTOTAL(9,G79:G85),2) -> 332692.56 | H86: =ROUND(SUBTOTAL(9,H79:H85),2) -> 363601.12 | I86: =ROUND(SUBTOTAL(9,I79:I85),2) -> 20315.53 | J86: =ROUND(SUBTOTAL(9,J79:J85),2) -> 383916.65 | K86: =IFERROR(J86/G86,0) -> 1.1539682 | L86: =ROUND(SUBTOTAL(9,L79:L85),2) -> -51224.09
C88: Total Expenses | D88: =ROUND(D78+D86,2) -> 1335289.7 | E88: =ROUND(E78+E86,2) -> 0 | F88: =ROUND(F78+F86,2) -> 0 | G88: =ROUND(G78+G86,2) -> 1335289.7 | H88: =ROUND(H78+H86,2) -> 1115908.7 | I88: =ROUND(I78+I86,2) -> 61291.74 | J88: =ROUND(J78+J86,2) -> 1177200.4 | K88: =IFERROR(J88/G88,0) -> 0.88160674 | L88: =ROUND(L78+L86,2) -> 158089.3
C90: Net Operating Income | D90: =ROUND(D26-D88,2) -> 487742.47 | E90: =ROUND(E26-E88,2) -> 0 | F90: =ROUND(F26-F88,2) -> 0 | G90: =ROUND(G26-G88,2) -> 487742.47 | H90: =ROUND(H26-H88,2) -> -131050.69 | I90: =ROUND(I26-I88,2) -> -61291.74 | J90: =ROUND(J26-J88,2) -> -192342.43 | K90: =IFERROR(J90/G90,0) -> -0.39435243 | L90: =ROUND(L26-L88,2) -> 680084.9
C92: Projected Debt Service | D92: 326924.83 | E92: =ROUND(SUBTOTAL(9,E88:E91),2) -> 0 | F92: =ROUND(SUBTOTAL(9,F88:F91),2) -> 0 | G92: =ROUND(D92+E92+F92,2) -> 326924.83 | H92: 0 | I92: 0 | J92: =ROUND(SUBTOTAL(9,J88:J91),2) -> 984858 | K92: =IFERROR(J92/G92,0) -> 3.0124907 | L92: 326924.83
C94: Cash Flow After Debt Service | D94: =ROUND(D90-D92,2) -> 160817.64 | E94: =ROUND(E90-E92,2) -> 0 | F94: =ROUND(F90-F92,2) -> 0 | G94: =ROUND(G90-G92,2) -> 160817.64 | H94: =ROUND(H90-H92,2) -> -131050.69 | I94: =ROUND(I90-I92,2) -> -61291.74 | J94: =ROUND(J90-J92,2) -> -1177200.4 | K94: =ROUND(K90-K92,2) -> -3.41 | L94: =ROUND(L90-L92,2) -> 353160.07
B95: 75000 | C95: Interest Expense | D95: 0 | E95: 0 | F95: 0 | G95: =ROUND(D95+E95+F95,2) -> 0 | H95: =ROUND(SUMIF('Prior Invoice Log (OP)'!B:B,'Budget to Actual (OP)'!C95,'Prior Invoice Log (OP)'!H:H),2) -> 160698.08 | I95: =ROUND(SUMIF('Current Invoice Log (OP)'!B:B,C95,'Current Invoice Log (OP)'!H:H),2) -> 0 | J95: =ROUND(SUM(H95:I95),2) -> 160698.08 | K95: =IFERROR(J95/G95,0) -> 0 | L95: =ROUND(+G95-J95,2) -> -160698.08 | M95: <-- Non-Budgeted Item
B96: 75140 | C96: Legal Expenditures | D96: 43000 | E96: 0 | F96: 0 | G96: =ROUND(D96+E96+F96,2) -> 43000 | H96: =ROUND(SUMIF('Prior Invoice Log (OP)'!B:B,'Budget to Actual (OP)'!C96,'Prior Invoice Log (OP)'!H:H),2) -> 3883.45 | I96: =ROUND(SUMIF('Current Invoice Log (OP)'!B:B,C96,'Current Invoice Log (OP)'!H:H),2) -> 0 | J96: =ROUND(SUM(H96:I96),2) -> 3883.45 | K96: =IFERROR(J96/G96,0) -> 0.090312791 | L96: =ROUND(+G96-J96,2) -> 39116.55
B97: 75110 | C97: Consultant Expenditures | D97: 0 | E97: 0 | F97: 0 | G97: =ROUND(D97+E97+F97,2) -> 0 | H97: =ROUND(SUMIF('Prior Invoice Log (OP)'!B:B,'Budget to Actual (OP)'!C97,'Prior Invoice Log (OP)'!H:H),2) -> 0 | I97: =ROUND(SUMIF('Current Invoice Log (OP)'!B:B,C97,'Current Invoice Log (OP)'!H:H),2) -> 0 | J97: =ROUND(SUM(H97:I97),2) -> 0 | K97: =IFERROR(J97/G97,0) -> 0 | L97: =ROUND(+G97-J97,2) -> 0
B98: 75005 | C98: Unused Fee Expense | D98: 0 | E98: 0 | F98: 0 | G98: =ROUND(D98+E98+F98,2) -> 0 | H98: =ROUND(SUMIF('Prior Invoice Log (OP)'!B:B,'Budget to Actual (OP)'!C98,'Prior Invoice Log (OP)'!H:H),2) -> 3953.57 | I98: =ROUND(SUMIF('Current Invoice Log (OP)'!B:B,C98,'Current Invoice Log (OP)'!H:H),2) -> 3285.89 | J98: =ROUND(SUM(H98:I98),2) -> 7239.46 | K98: =IFERROR(J98/G98,0) -> 0 | L98: =ROUND(+G98-J98,2) -> -7239.46 | M98: <-- Non-Budgeted Item
B99: 75006 | C99: Loan Fee Expense | D99: 0 | E99: 0 | F99: 0 | G99: =ROUND(D99+E99+F99,2) -> 0 | H99: =ROUND(SUMIF('Prior Invoice Log (OP)'!B:B,'Budget to Actual (OP)'!C99,'Prior Invoice Log (OP)'!H:H),2) -> 0 | I99: =ROUND(SUMIF('Current Invoice Log (OP)'!B:B,C99,'Current Invoice Log (OP)'!H:H),2) -> 0 | J99: =ROUND(SUM(H99:I99),2) -> 0 | K99: =IFERROR(J99/G99,0) -> 0 | L99: =ROUND(+G99-J99,2) -> 0 | M99: <-- Non-Budgeted Item
C100: Grant Expenditures | D100: 120000 | E100: 0 | F100: 0 | G100: =ROUND(D100+E100+F100,2) -> 120000 | H100: =ROUND(SUMIF('Prior Invoice Log (OP)'!B:B,'Budget to Actual (OP)'!C100,'Prior Invoice Log (OP)'!H:H),2) -> 0 | I100: =ROUND(SUMIF('Current Invoice Log (OP)'!B:B,C100,'Current Invoice Log (OP)'!H:H),2) -> 0 | J100: =ROUND(SUM(H100:I100),2) -> 0 | K100: =IFERROR(J100/G100,0) -> 0 | L100: =ROUND(+G100-J100,2) -> 120000
C101: Car Reader | D101: 30000 | E101: 0 | F101: 0 | G101: =ROUND(D101+E101+F101,2) -> 30000 | H101: =ROUND(SUMIF('Prior Invoice Log (OP)'!B:B,'Budget to Actual (OP)'!C101,'Prior Invoice Log (OP)'!H:H),2) -> 0 | I101: =ROUND(SUMIF('Current Invoice Log (OP)'!B:B,C101,'Current Invoice Log (OP)'!H:H),2) -> 0 | J101: =ROUND(SUM(H101:I101),2) -> 0 | K101: =IFERROR(J101/G101,0) -> 0 | L101: =ROUND(+G101-J101,2) -> 30000
C102: Tenant Improvements | D102: 200000 | E102: 0 | F102: 0 | G102: =ROUND(D102+E102+F102,2) -> 200000 | H102: =ROUND(SUMIF('Prior Invoice Log (OP)'!B:B,'Budget to Actual (OP)'!C102,'Prior Invoice Log (OP)'!H:H),2) -> 0 | I102: =ROUND(SUMIF('Current Invoice Log (OP)'!B:B,C102,'Current Invoice Log (OP)'!H:H),2) -> 0 | J102: =ROUND(SUM(H102:I102),2) -> 0 | K102: =IFERROR(J102/G102,0) -> 0 | L102: =ROUND(+G102-J102,2) -> 200000
G103: =ROUND(D103+E103+F103,2) -> 0
C104: Total Capital Expenditures | D104: =ROUND(SUBTOTAL(9,D95:D103),2) -> 393000 | E104: =ROUND(SUBTOTAL(9,E95:E103),2) -> 0 | F104: =ROUND(SUBTOTAL(9,F95:F103),2) -> 0 | G104: =ROUND(SUBTOTAL(9,G95:G103),2) -> 393000 | H104: =ROUND(SUBTOTAL(9,H95:H103),2) -> 168535.1 | I104: =ROUND(SUBTOTAL(9,I95:I103),2) -> 3285.89 | J104: =ROUND(SUBTOTAL(9,J95:J103),2) -> 171820.99 | K104: =IFERROR(J104/G104,0) -> 0.43720354 | L104: =ROUND(SUBTOTAL(9,L95:L103),2) -> 221179.01
C105: Lender portion (75%) | I105: =(I88+I104)*0.75 -> 48433.222
C106: Draw Request Total | I106: =ROUND(I105,-4) -> 50000
C107: (Rounded to the nearest 10,000)
G109: Rev: | H109: =ROUND(_xlfn.XLOOKUP("Grand Total",'Prior Revenue Log (OP)'!$D:$D,'Prior Revenue Log (OP)'!$G:$G)-'Budget to Actual (OP)'!H26,2) -> 0 | I109: =ROUND(_xlfn.XLOOKUP("Grand Total",'Current Revenue Log (OP)'!$D:$D,'Current Revenue Log (OP)'!$G:$G)-'Budget to Actual (OP)'!I26,2) -> 0
G110: Expense: | H110: =ROUND(_xlfn.XLOOKUP("Grand Total",'Prior Invoice Log (OP)'!$E:$E,'Prior Invoice Log (OP)'!$H:$H)-'Budget to Actual (OP)'!H88-'Budget to Actual (OP)'!H104,2) -> 0 | I110: =ROUND(_xlfn.XLOOKUP("Grand Total",'Current Invoice Log (OP)'!$E:$E,'Current Invoice Log (OP)'!$H:$H)-'Budget to Actual (OP)'!I88-'Budget to Actual (OP)'!I104,2) -> 0

Sheet Current Revenue Log (OP)
B2: Cost Category | C2: Cost Code # | D2: Cost Code Name | E2: Customer | F2: Invoice # | G2: Amount Paid | H2: Requisition Month | I2: Invoice Date | K2: CURRENT REQ REPORT | L2: DUPLICATE(S)
B4: Short Term Land Leases | C4: 40110 | D4: Land Leases
B5: Short Term Land Leases | C5: 40110 | D5: Land Leases | E5: Utility Lines Construction Services | F5: 1415
D7: Land Leases Total | G7: =SUBTOTAL(9,G4:G6) -> 0
B9: In & Out Fees | C9: 40120 | D9: In & Out Fees
B10: In & Out Fees | C10: 40120 | D10: In & Out Fees
D12: In & Out Fees Total | G12: =SUBTOTAL(9,G9:G11) -> 0
B14: Storage Fees | C14: 40130 | D14: Storage Fees
B15: Storage Fees | C15: 40130 | D15: Storage Fees
D17: Storage Fees Total | G17: =SUBTOTAL(9,G14:G16) -> 0
B19: Trasnloading Fees | C19: 40140 | D19: Transloading | E19: Trecora Resources
D21: Transloading Total | G21: =SUBTOTAL(9,G19:G20) -> 0
B23: Warehouse Lease Income | C23: 40150 | D23: Warehouse Lease | E23: Louisiana-Pacific Corporation
D25: Warehouse Lease Total | G25: =SUBTOTAL(9,G23:G24) -> 0
D27: Grand Total | G27: =SUBTOTAL(9,G4:G26) -> 0

Sheet Prior Revenue Log (OP)
B2: Cost Category | C2: Cost Code # | D2: Cost Code Name | E2: Customer | F2: Invoice # | G2: Amount Paid | H2: Requisition Month | I2: Invoice Date | K2: CURRENT REQ REPORT | L2: DUPLICATE(S)
B4: Short Term Land Leases | C4: 40110 | D4: Land Leases | E4: Silsbee Ford | F4: 1303 | G4: 6500 | H4: 45658 | I4: 45689
B5: Short Term Land Leases | C5: 40110 | D5: Land Leases | E5: Utility Lines Construction Services | F5: 1405 | G5: 4500 | H5: 45658 | I5: 45689
B6: Short Term Land Leases | C6: 40110 | D6: Land Leases | E6: Silsbee Ford | F6: 1404 | G6: 6760 | H6: 45689 | I6: 45720 | M6: GL | N6: GL Term | O6: Invoice Term
B7: Short Term Land Leases | C7: 40110 | D7: Land Leases | E7: Utility Lines Construction Services | F7: 1406 | G7: 4500 | H7: 45689 | I7: 45720 | M7: 40110 | N7: Short Term Land Leases | O7: Rent - Short Term
B8: Short Term Land Leases | C8: 40110 | D8: Land Leases | E8: Silsbee Ford | F8: 1405 | G8: 6760 | H8: 45717 | I8: 45748 | M8: 40120 | N8: In & Out Fees | O8: Inbound/Outbound Fees
B9: Short Term Land Leases | C9: 40110 | D9: Land Leases | E9: Utility Lines Construction Services | F9: 1407 | G9: 4500 | H9: 45717 | I9: 45748 | M9: 40130 | N9: Storage Fees | O9: Warehouse Storage, Base Spots, Overages
B10: Short Term Land Leases | C10: 40110 | D10: Land Leases | E10: Silsbee Ford | F10: 1506 | G10: 6760 | H10: 45748 | I10: 45778 | M10: 40140 | N10: Intra-Plant Switch Fees | O10: Intra-Plant Switch Fees
B11: Short Term Land Leases | C11: 40110 | D11: Land Leases | E11: Utility Lines Construction Services | F11: 1408 | G11: 4500 | H11: 45748 | I11: 45778 | M11: 40150 | N11: Warehouse Lease Income | O11: Rent - Long term - Louisiana-Pacific
B12: Short Term Land Leases | C12: 40110 | D12: Land Leases | E12: Silsbee Ford | F12: 1507 | G12: 6760 | H12: 45802 | I12: 45809 | M12: 40160 | N12: Transloading Fees | O12: Transloading Fees
B13: Short Term Land Leases | C13: 40110 | D13: Land Leases | E13: Utility Lines Construction Services | F13: 1409 | G13: 4500 | H13: 45802 | I13: 45809
B14: Short Term Land Leases | C14: 40110 | D14: Land Leases | E14: Silsbee Ford | F14: 1508 | G14: 6760 | H14: 45833 | I14: 45840
B15: Short Term Land Leases | C15: 40110 | D15: Land Leases | E15: Utility Lines Construction Services | F15: 1411 | G15: 4500 | H15: 45833 | I15: 45840
B16: Short Term Land Leases | C16: 40110 | D16: Land Leases | E16: Silsbee Ford | F16: 1509 | G16: 6760 | H16: 45863 | I16: 45869
B17: Short Term Land Leases | C17: 40110 | D17: Land Leases | E17: Utility Lines Construction Services | F17: 1411 | G17: 4500 | H17: 45863 | I17: 45869
B18: Short Term Land Leases | C18: 40110 | D18: Land Leases | E18: Silsbee Ford | F18: 1510 | G18: 6760 | H18: 45894 | I18: 45900
B19: Short Term Land Leases | C19: 40110 | D19: Land Leases | E19: Utility Lines Construction Services | F19: 1412 | G19: 4500 | H19: 45894 | I19: 45900
B20: Short Term Land Leases | C20: 40110 | D20: Land Leases | E20: Silsbee Ford | F20: 1511 | G20: 6760 | H20: 45901 | I20: 45930
B21: Short Term Land Leases | C21: 40110 | D21: Land Leases | E21: Utility Lines Construction Services | F21: 1413 | G21: 4500 | H21: 45901 | I21: 45930
B22: Short Term Land Leases | C22: 40110 | D22: Land Leases | E22: Silsbee Ford | F22: 1512 | G22: 6760 | H22: 45931 | I22: 45961
B23: Short Term Land Leases | C23: 40110 | D23: Land Leases | E23: Utility Lines Construction Services | F23: 1414 | G23: 4500 | H23: 45931 | I23: 45961
B24: Short Term Land Leases | C24: 40110 | D24: Land Leases | E24: Silsbee Ford | F24: 1513 | G24: 6760 | H24: 45986 | I24: 45991
B25: Short Term Land Leases | C25: 40110 | D25: Land Leases | E25: Utility Lines Construction Services | F25: 1415 | G25: 4500 | H25: 45986 | I25: 45991
B26: Short Term Land Leases | C26: 40110 | D26: Land Leases | E26: Silsbee Ford | F26: 1514 | G26: 6760 | H26: 45992 | I26: 45992
D28: Land Leases Total | G28: =SUBTOTAL(9,G4:G27) -> 130360
B30: In & Out Fees | C30: 40120 | D30: In & Out Fees | E30: Trecora Recources | F30: 1304 | G30: 440 | H30: 45658 | I30: 45699
B31: In & Out Fees | C31: 40120 | D31: In & Out Fees | E31: Valero | F31: 1 | G31: 16425 | H31: 45748 | I31: 45779
B32: In & Out Fees | C32: 40120 | D32: In & Out Fees | E32: Trecora Recources | F32: 8009 | G32: 1265 | H32: 45748 | I32: 45779
B33: In & Out Fees | C33: 40120 | D33: In & Out Fees | E33: Trecora Recources | F33: 8010 | G33: 1760 | H33: 45802 | I33: 45809
B34: In & Out Fees | C34: 40120 | D34: In & Out Fees | E34: Trecora Recources | F34: 8011 | G34: 1155.5 | H34: 45833 | I34: 45840
B35: In & Out Fees | C35: 40120 | D35: In & Out Fees | E35: Valero | F35: 4 | G35: 1125 | H35: 45863 | I35: 45869
B36: In & Out Fees | C36: 40120 | D36: In & Out Fees | E36: Trecora Recources | F36: 8012 | G36: 660 | H36: 45863 | I36: 45869
B37: In & Out Fees | C37: 40120 | D37: In & Out Fees | E37: Valero | F37: 5 | G37: 15187.5 | H37: 45894 | I37: 45900
B38: In & Out Fees | C38: 40120 | D38: In & Out Fees | E38: Trecora Recources | F38: 8013 | G38: 880 | H38: 45894 | I38: 45900
B39: In & Out Fees | C39: 40120 | D39: In & Out Fees | E39: Valero | F39: 6 | G39: 13612.5 | H39: 45901 | I39: 45930
B40: In & Out Fees | C40: 40120 | D40: In & Out Fees | E40: Valero | F40: 8 | G40: 5737.5 | H40: 45986 | I40: 45991
B41: In & Out Fees | C41: 40120 | D41: In & Out Fees | E41: Trecora Resources | F41: 8015 | G41: 275 | H41: 45986 | I41: 45991
B42: In & Out Fees | C42: 40120 | D42: In & Out Fees | E42: Valero | F42: 9 | G42: 6750 | H42: 45992 | I42: 46022
B43: In & Out Fees | C43: 40120 | D43: In & Out Fees | E43: Trecora Resources | F43: 8016 | G43: 1210 | H43: 45992 | I43: 46022
D45: In & Out Fees Total | G45: =SUBTOTAL(9,G30:G44) -> 66483
B47: Storage Fees | C47: 40130 | D47: Storage Fees | E47: USGAI Cement | F47: 1302 | G47: 4459 | H47: 45658 | I47: 45699
B48: Storage Fees | C48: 40130 | D48: Storage Fees | E48: Trecora Resources | F48: 1304 | G48: 16740 | H48: 45658 | I48: 45699
B49: Storage Fees | C49: 40130 | D49: Storage Fees | E49: USGAI Cement | F49: 1402 | G49: 3530 | H49: 45689 | I49: 45720
B50: Storage Fees | C50: 40130 | D50: Storage Fees | E50: Trecora Resources | F50: 1304 | G50: 15120 | H50: 45689 | I50: 45726
B51: Storage Fees | C51: 40130 | D51: Storage Fees | E51: USGAI Cement | F51: 1404 | G51: 3530 | H51: 45717 | I51: 45748
B52: Storage Fees | C52: 40130 | D52: Storage Fees | E52: Trecora Resources | F52: 1406 | G52: 16740 | H52: 45717 | I52: 45748
B53: Storage Fees | C53: 40130 | D53: Storage Fees | E53: Valero | F53: 1 | G53: 36672 | H53: 45748 | I53: 45779
B54: Storage Fees | C54: 40130 | D54: Storage Fees | E54: Trecora Resources | F54: 8009 | G54: 16200 | H54: 45748 | I54: 45779
B55: Storage Fees | C55: 40130 | D55: Storage Fees | E55: USGAI Cement | F55: 1305 | G55: 3530 | H55: 45748 | I55: 45779
B56: Storage Fees | C56: 40130 | D56: Storage Fees | E56: Valero | F56: 2 | G56: 54312 | H56: 45802 | I56: 45809
B57: Storage Fees | C57: 40130 | D57: Storage Fees | E57: Trecora Resources | F57: 8010 | G57: 16200 | H57: 45802 | I57: 45809
B58: Storage Fees | C58: 40130 | D58: Storage Fees | E58: USGAI Cement | F58: 1306 | G58: 3530 | H58: 45802 | I58: 45809
... B63: Storage Fees | C63: 40130 | D63: Storage Fees | E63: Trecora Resources | F63: 8012 | G63: 17298 | H63: 45863 | I63: 45869
B64: Storage Fees | C64: 40130 | D64: Storage Fees | E64: Valero | F64: 5 | G64: 40524 | H64: 45894 | I64: 45900
B65: Storage Fees | C65: 40130 | D65: Storage Fees | E65: Trecora Resources | F65: 8013 | G65: 17298 | H65: 45894 | I65: 45900
B66: Storage Fees | C66: 40130 | D66: Storage Fees | E66: Valero | F66: 6 | G66: 33310 | H66: 45901 | I66: 45930
B67: Storage Fees | C67: 40130 | D67: Storage Fees | E67: Trecora Resources | F67: 8014 | G67: 16200 | H67: 45901 | I67: 45930
B68: Storage Fees | C68: 40130 | D68: Storage Fees | E68: Valero | F68: 7 | G68: 37510 | H68: 45931 | I68: 10/31/205
B69: Storage Fees | C69: 40130 | D69: Storage Fees | E69: Trecora Resources | F69: 8014 | G69: 17298 | H69: 45931 | I69: 10/31/205
B70: Storage Fees | C70: 40130 | D70: Storage Fees | E70: Valero | F70: 8 | G70: 37510 | H70: 45986 | I70: 45991
B71: Storage Fees | C71: 40130 | D71: Storage Fees | E71: Trecora Resources | F71: 8015 | G71: 17298 | H71: 45986 | I71: 45991
B72: Storage Fees | C72: 40130 | D72: Storage Fees | E72: Valero | F72: 9 | G72: 21550 | H72: 45992 | I72: 46022
B73: Storage Fees | C73: 40130 | D73: Storage Fees | E73: Trecora Resources | F73: 8016 | G73: 17298 | H73: 45992 | I73: 46022
D75: Storage Fees Total | G75: =SUBTOTAL(9,G47:G74) -> 588015
B77: Transloading Fees | C77: 40140 | D77: Transloading | I77: 45597
D79: Transloading Total | G79: =SUBTOTAL(9,G77:G78) -> 0
B81: Warehouse Lease Income | C81: 40150 | D81: Warehouse Lease | E81: Louisiana-Pacific Corporation | F81: 1401 | G81: 25000 | H81: 45658 | I81: 45689
B82: Warehouse Lease Income | C82: 40150 | D82: Warehouse Lease | E82: Louisiana-Pacific Corporation | F82: 1501 | G82: 25000 | H82: 45689 | I82: 45717
B83: Warehouse Lease Income | C83: 40150 | D83: Warehouse Lease | E83: Louisiana-Pacific Corporation | F83: 1403 | G83: 25000 | H83: 45717 | I83: 45748
B84: Warehouse Lease Income | C84: 40150 | D84: Warehouse Lease | E84: Louisiana-Pacific Corporation | F84: 1404 | G84: 25000 | H84: 45748 | I84: 45778
B85: Warehouse Lease Income | C85: 40150 | D85: Warehouse Lease | E85: Louisiana-Pacific Corporation | F85: 1405 | G85: 25000 | H85: 45802 | I85: 45809
B86: Warehouse Lease Income | C86: 40150 | D86: Warehouse Lease | E86: Louisiana-Pacific Corporation | F86: 1406 | G86: 25000 | H86: 45833 | I86: 45840
B87: Warehouse Lease Income | C87: 40150 | D87: Warehouse Lease | E87: Louisiana-Pacific Corporation | F87: 1407 | G87: 25000 | H87: 45863 | I87: 45869
B88: Warehouse Lease Income | C88: 40150 | D88: Warehouse Lease | E88: Louisiana-Pacific Corporation | F88: 1408 | G88: 25000 | H88: 45894 | I88: 45900
D90: Warehouse Lease Total | G90: =SUBTOTAL(9,G81:G89) -> 200000
D92: Grand Total | G92: =SUBTOTAL(9,G3:G91) -> 984858

Sheet Current Invoice Log (OP)
B2: Cost Category | C2: Cost Code # | D2: Bank Cost Category | E2: Cost Code Name | F2: Vendor | G2: Bill Number | H2: Amount Paid | I2: Requisition Month | J2: Invoice Date | L2: CURRENT REQ REPORT | M2: DUPLICATE(S)
B4: Travel | C4: 60210 | D4: Travel | E4: Travel | F4: Banyan Residential | G4: Dec_25 UBS CC Reimb. | H4: 217.32 | I4: 46016 | J4: 46022
E6: Travel Total | H6: =SUBTOTAL(9,H4:H5) -> 217.32
B8: Meals | C8: 60500 | D8: Meals | E8: Meals | F8: Banyan Residential | G8: Dec_25 UBS CC Reimb. | H8: 158.16 | I8: 46016 | J8: 46022
E10: Meals Total | H10: =SUBTOTAL(9,H8:H9) -> 158.16
B12: Site/Yard Maintenace | C12: 61050 | D12: Site/Yard Maintenace | E12: Site/Yard Maintenace | F12: Agri-Serv Industrial Maintenance | G12: 788995 | H12: 1061.6 | I12: 46016 | J12: 45993
E14: Site/Yard Maintenace Total | H14: =SUBTOTAL(9,H12:H13) -> 1061.6
B16: Track Repairs | C16: 61051 | D16: Track Repairs | E16: Track Repairs | F16: Mcallen Signal and Boring
E18: Track Repairs Total | H18: =SUBTOTAL(9,H16:H17) -> 0
B20: Crossing Repairs | C20: 61052 | D20: Crossing Repairs | E20: Crossing Repairs | F20: Mcallen Signal and Boring | G20: 12325CLR | H20: 700 | I20: 46016 | J20: 46001
E22: Crossing Repairs Total | H22: =SUBTOTAL(9,H20:H21) -> 700
B24: Landscape Maintenance | C24: 61056 | D24: Landscape Maintenance | E24: Landscape Maintenance | F24: Switch Yard Mowing | G24: 8021 | H24: 2500 | I24: 46016 | J24: 46022
E26: Landscape Maintenance Total | H26: =SUBTOTAL(9,H24:H25) -> 2500
B28: Utilities | C28: 61150 | D28: Utilities | E28: Utilities | F28: Banyan Residential | G28: Dec_25 UBS CC Reimb. | H28: 1184.69 | I28: 46016 | J28: 46022
E30: Utilities Total | H30: =SUBTOTAL(9,H28:H29) -> 1184.69
B32: Fuel | C32: 61164 | D32: Fuel | E32: Fuel | F32: Great Lakes Petroleum | G32: 2698593-IN | H32: 1952.87 | I32: 46016 | J32: 45994
B33: Fuel | C33: 61164 | D33: Fuel | E33: Fuel | F33: Great Lakes Petroleum | G33: 2716338-IN | H33: 2016.44 | I33: 46016 | J33: 46022
E35: Fuel Total | H35: =SUBTOTAL(9,H32:H34) -> 3969.31
B37: Accounting Fees | C37: 63000 | D37: Accounting Fees | E37: Accounting
E39: Accounting Fees Total | H39: =SUBTOTAL(9,H37:H38) -> 0
B41: Professional Fees | C41: 63025 | D41: Professional Fees | E41: Professional Fees | F41: Banyan Residential | G41: Dec_25 UBS CC Reimb. | H41: 1.25 | I41: 46016 | J41: 46022
E43: Professional Fees Total | H43: =SUBTOTAL(9,H41:H42) -> 1.25
B45: Management Fees - Hall Logistics | C45: 63026 | D45: Management Fees - Hall Logistics | E45: Management Fees - Hall Logistics | F45: Hall Rail Logistics
E47: Management Fees - Hall Logistics Total | H47: =SUBTOTAL(9,H45:H46) -> 0
B49: AM Fees - Banyan | C49: 63027 | D49: Management Fees - Banyan Residential | E49: Management Fees - Banyan Residential | F49: Banyan Residential LLC | G49: Dec_25 Management Fee | H49: 5683.19 | I49: 46016 | J49: 46022
E51: Management Fees - Banyan Residential Total | H51: =SUBTOTAL(9,H49:H50) -> 5683.19
B53: Asset Manager - (County Line) | C53: 63028 | D53: Asset Manager - (County Line) | E53: AM Staff Services - Asset Manager | F53: County Line Rail Operations | G53: Aug_25 Asset Manager Fees | I53: 45962 | J53: 45991
E55: AM Staff Services - Asset Manager Total | H55: =SUBTOTAL(9,H53:H54) -> 0
B57: Switchmen Salaries - Reimbursable | C57: 63032 | D57: Switchmen Healthcare – Reimbursable | E57: Switchmen Healthcare – Reimbursable | F57: Hall Rail Logistics
E59: Switchmen Healthcare - Reimbursable Total | H59: =SUBTOTAL(9,H57:H58) -> 0
B61: Mowing Assistance - Reimbursable | C61: 63033 | D61: Mowing Assistance - Reimbursable | E61: Mowing Assistance | F61: Switch Yard Mowing
E63: Mowing Assistance Total | H63: =SUBTOTAL(9,H61:H62) -> 0
B65: Switchmen Salaries - Reimbursable | C65: 63034 | D65: Switchmen Salaries - Reimbursable | E65: Switchmen Salaries - Reimbursable | F65: County Line Rail Operations | G65: 34 | H65: 11560.34 | I65: 46016 | J65: 46022
E67: Switchmen Salaries - Reimbursable Total | H67: =SUBTOTAL(9,H65:H66) -> 11560.34
B69: Offsite Manager | C69: 63041 | D69: Offsite Manager | E69: Management Fees | F69: County Line Rail Operations | G69: 38 | H69: -1603.53 | I69: 46016 | J69: 46022
E71: AM Staff Services - Accounting - Reimbursable Total | H71: =SUBTOTAL(9,H69:H70) -> -1603.53
B73: Offsite Staff | C73: 63042 | D73: Offsite Staff | E73: Offsite Staff | F73: County Line Rail Operations | G73: 34 | H73: 10116.6 | I73: 46016 | J73: 46022
E75: Management Fees Totals | H75: =SUBTOTAL(9,H73:H74) -> 10116.6
B77: Legal Fees | C77: 63050 | D77: Legal Fees | E77: Legal Fees - General | F77: Patrick M Knapp, PC | G77: 026
E79: Legal Fees - General Total | H79: =SUBTOTAL(9,H77:H78) -> 0
B81: Consulting Fees | C81: 63150 | D81: Broker Commission Fee | E81: Broker Commission Fee | F81: M&W Real Estate
E83: Consulting Fee Total | H83: =SUBTOTAL(9,H81:H82) -> 0
B85: Security | C85: 64000 | D85: Security Expense | E85: Security Expense | F85: Tower Security Company | G85: 3030 | H85: 2233.01 | I85: 46016 | J85: 45995
B86: Security | C86: 64000 | D86: Security Expense | E86: Security Expense | F86: Tower Security Company | G86: 3042 | H86: 1337.43 | I86: 46016 | J86: 46002
B87: Security | C87: 64000 | D87: Security Expense | E87: Security Expense | F87: Tower Security Company | G87: 3054 | H87: 1337.43 | I87: 46016 | J87: 46009
B88: Security | C88: 64000 | D88: Security Expense | E88: Security Expense | F88: Tower Security Company | G88: 3066 | H88: 1337.43 | I88: 46016 | J88: 46016
E90: Security Expense Totals | H90: =SUBTOTAL(9,H85:H89) -> 6245.3
B92: Dues & Subscriptions | C92: 67100 | D92: Dues & Subscriptions | E92: Dues & Subscriptions | F92: Banyan Residential
E94: Dues & Subscriptions Total | H94: =SUBTOTAL(9,H92:H93) -> 0
B96: Office Expense | C96: 67200 | D96: Office Expense | E96: Office Expense | F96: Banyan Residential | G96: Dec_25 UBS CC Reimb. | H96: 366.67 | I96: 46016 | J96: 46022
E98: Office Expense Total | H98: =SUBTOTAL(9,H96:H97) -> 366.67
B100: Property Tax | C100: 68050 | D100: Property Tax | E100: Property Tax | F100: DMA, Inc. | G100: Dec_25 Property Tax Accrual | H100: -7962.63 | I100: 46016 | J100: 46022
E102: Property Tax Total | H102: =SUBTOTAL(9,H100:H101) -> -7962.63
B104: Property Insurance | C104: 68055 | D104: Property Insurance | E104: Property Insurance | F104: Pre-paid property insurance | G104: Dec_25 Insurance Accrual | H104: 4917.97 | I104: 46016 | J104: 46022
B105: Property Insurance | C105: 68055 | D105: Property Insurance | E105: Property Insurance | F105: Pre-paid property insurance | G105: Dec_25 Insurance Accrual | H105: 14284.71 | I105: 46016 | J105: 46022
B106: Property Insurance | C106: 68055 | D106: Property Insurance | E106: Property Insurance | F106: Pre-paid property insurance | G106: Dec_25 Insurance Accrual | H106: 7280.46 | I106: 46016 | J106: 46022
B107: Property Insurance | C107: 68055 | D107: Property Insurance | E107: Property Insurance | F107: Pre-paid property insurance | G107: Dec_25 Insurance Accrual | H107: 610.33 | I107: 46016 | J107: 46022
E109: Property Insurance Total | H109: =SUBTOTAL(9,H104:H108) -> 27093.47
B111: Bank Fees | C111: 68110 | D111: Bank Fees | E111: Bank Fees | F111: Veritex Community Bank | G111: Dec_25 Bank Statement
E113: Bank Fees Total | H113: =SUBTOTAL(9,H111:H112) -> 0
B115: Interest Expense | C115: 75000 | D115: Interest Expense | E115: Interest Expense | F115: Sunflower Bank
B116: Interest Expense | C116: 75000 | D116: Interest Expense | E116: Interest Expense | F116: Sunflower Bank
B117: Interest Expense | C117: 75000 | D117: Interest Expense | E117: Interest Expense | F117: Sunflower Bank
E119: Interest Expense Total | H119: =SUBTOTAL(9,H115:H118) -> 0
B121: Unused Fee Expense | C121: 75005 | D121: Unused Fee Expense | E121: Unused Fee Expense | F121: Sunflower Bank | H121: 3285.89 | I121: 46016 | J121: 46022
E123: Unused Fee Expense Total | H123: =SUBTOTAL(9,H121:H122) -> 3285.89
B125: Loan Fee Expense | C125: 75006 | D125: Loan Fee Expense | E125: Loan Fee Expense | F125: Sunflower Bank | G125: CLR Fund Loan Closing
E127: Loan Fee Expense Total | H127: =SUBTOTAL(9,H125:H126) -> 0
B129: Legal Expenditures | C129: 75140 | D129: Legal Expenditures | E129: Condemnation Expense | F129: Cherry Peterson Albert LLC | G129: 134912
E131: Condemnation Expense Total | H131: =SUBTOTAL(9,H129:H130) -> 0
E134: Grand Total | H134: =SUBTOTAL(9,H3:H133) -> 64577.63 | L134: =IF(H134='Budget to Actual (OP)'!I88+'Budget to Actual (OP)'!I104,TRUE,FALSE) -> TRUE

Sheet Prior Invoice Log (OP)
B2: Cost Category | C2: Cost Code # | D2: Bank Cost Category | E2: Cost Code Name | F2: Vendor | G2: Bill Number | H2: Amount Paid | I2: Requisition Month | J2: Invoice Date | L2: CURRENT REQ REPORT | M2: DUPLICATE(S)
B4: Travel | C4: 60210 | D4: Travel | E4: Travel | F4: Banyan Residential | G4: Jan_25 UBS CC Trx | H4: 154.1 | I4: 45682 | J4: 45688
B5: Travel | C5: 60210 | D5: Travel | E5: Travel | F5: Banyan Residential | G5: Dillon Schroeder Mileage (February) | H5: 50.25 | I5: 45689 | J5: 45716
B6: Travel | C6: 60210 | D6: Travel | E6: Travel | F6: Banyan Residential | G6: Feb_25 CC Exp | H6: 50.23 | I6: 45689 | J6: 45716
B7: Travel | C7: 60210 | D7: Travel | E7: Travel | F7: Banyan Residential | G7: Mar_25 CC Reimbursement | H7: 120.97 | I7: 45717 | J7: 45747
B8: Travel | C8: 60210 | D8: Travel | E8: Travel | F8: Dillon Schroeder | G8: Mar_25 Mileage Reimb. | H8: 75 | I8: 45717 | J8: 45747
B9: Travel | C9: 60210 | D9: Travel | E9: Travel | F9: Banyan Residential | G9: Jay Kennedy Mileage (Feb) | H9: 322 | I9: 45748 | J9: 45748
B10: Travel | C10: 60210 | D10: Travel | E10: Travel | F10: Banyan Residential | G10: Jay Kennedy Mileage (Mar) | H10: 161 | I10: 45748 | J10: 45748
B11: Travel | C11: 60210 | D11: Travel | E11: Travel | F11: Banyan Residential | G11: Apr_25 UBS CC Reimbursement | H11: 1048.73 | I11: 45748 | J11: 45770
B12: Travel | C12: 60210 | D12: Travel | E12: Travel | F12: Banyan Residential | G12: Dillon Schroeder Mileage (May) | H12: 154 | I12: 45802 | J12: 45808
B13: Travel | C13: 60210 | D13: Travel | E13: Travel | F13: Banyan Residential | G13: Dillon Schroeder Mileage (June) | H13: 319.2 | I13: 45833 | J13: 45838
B14: Travel | C14: 60210 | D14: Travel | E14: Travel | F14: Banyan Residential | G14: Jay Kennedy Mileage (Juen) | H14: 161 | I14: 45833 | J14: 45838
B15: Travel | C15: 60210 | D15: Travel | E15: Travel | F15: Banyan Residential | G15: June 2025 UBS Credit Card Reimb | H15: 959.28 | I15: 45833 | J15: 45838
... B26: Travel | C26: 60210 | D26: Travel | E26: Travel | F26: Banyan Residential | G26: Dec_25 UBS CC Reimb. | H26: 217.32 | I26: 46016 | J26: 46022
E28: Travel Total | H28: =SUBTOTAL(9,H4:H27) -> 7744.65
B30: Meals | C30: 60500 | D30: Meals | E30: Meals | F30: Banyan Residential | G30: Jul_25 UBS CC Reimb. | H30: 59.22 | I30: 45839 | J30: 45869
B31: Meals | C31: 60500 | D31: Meals | E31: Meals | F31: Banyan Residential | G31: Sep_25 UBS CC | H31: 95.48 | I31: 45925 | J31: 45922
B32: Meals | C32: 60500 | D32: Meals | E32: Meals | F32: Banyan Residential | G32: Oct_25 UBS CC | H32: 62.45 | I32: 45931 | J32: 45961
B33: Meals | C33: 60500 | D33: Meals | E33: Meals | F33: Banyan Residential | G33: Nov_25 UBS CC Reimb. | H33: 171.23 | I33: 45962 | J33: 45991
B34: Meals | C34: 60500 | D34: Meals | E34: Meals | F34: Banyan Residential | G34: Dec_25 UBS CC Reimb. | H34: 158.16 | I34: 46016 | J34: 46022
E36: Meals Total | H36: =SUBTOTAL(9,H30:H35) -> 546.54
B38: Site/Yard Maintenace | C38: 61050 | D38: Site/Yard Maintenace | E38: Site/Yard Maintenace | F38: Biskamp Electric, Inc | G38: 550086-1 | H38: 4239.07 | I38: 45839 | J38: 45849
B39: Site/Yard Maintenace | C39: 61050 | D39: Site/Yard Maintenace | E39: Site/Yard Maintenace | F39: Banyan Residential | G39: Oct_25 UBS CC | H39: 1798 | I39: 45931 | J39: 45961
B40: Site/Yard Maintenace | C40: 61050 | D40: Site/Yard Maintenace | E40: Site/Yard Maintenace | F40: Kauffman Co. | G40: I2510-34 | H40: 346 | I40: 45962 | J40: 45981
B41: Site/Yard Maintenace | C41: 61050 | D41: Site/Yard Maintenace | E41: Site/Yard Maintenace | F41: Agri-Serv Industrial Maintenance | G41: 788995 | H41: 1061.6 | I41: 46016 | J41: 45993
E43: Site/Yard Maintenance Total | H43: =SUBTOTAL(9,H38:H42) -> 7444.67
B45: Track Repairs | C45: 61051 | D45: Track Repairs | E45: Track Repairs | F45: Mcallen Signal and Boring | G45: 11025 | H45: 1775 | I45: 45682 | J45: 45671
E47: Track Repairs Total | H47: =SUBTOTAL(9,H45:H46) -> 1775
B49: Crossing Repairs | C49: 61052 | D49: Crossing Repairs | E49: Crossing Repairs | F49: Mcallen Signal and Boring | G49: 1525CLR | H49: 700 | I49: 45682 | J49: 45670
B50: Crossing Repairs | C50: 61052 | D50: Crossing Repairs | E50: Crossing Repairs | F50: Mcallen Signal and Boring | G50: 12925CLR | H50: 764 | I50: 45689 | J50: 45692
B51: Crossing Repairs | C51: 61052 | D51: Crossing Repairs | E51: Crossing Repairs | F51: Mcallen Signal and Boring | G51: 22825CLR | H51: 700 | I51: 45717 | J51: 45721
B52: Crossing Repairs | C52: 61052 | D52: Crossing Repairs | E52: Crossing Repairs | F52: Mcallen Signal and Boring | G52: 33125CLR | H52: 700 | I52: 45748 | J52: 45756
B53: Crossing Repairs | C53: 61052 | D53: Crossing Repairs | E53: Crossing Repairs | F53: Mcallen Signal and Boring | G53: 42625CLR | H53: 700 | I53: 45802 | J53: 45778
B54: Crossing Repairs | C54: 61052 | D54: Crossing Repairs | E54: Crossing Repairs | F54: Mcallen Signal and Boring | G54: 52225CLR | H54: 700 | I54: 45802 | J54: 45805
B55: Crossing Repairs | C55: 61052 | D55: Crossing Repairs | E55: Crossing Repairs | F55: Mcallen Signal and Boring | G55: 61925CLR | H55: 700 | I55: 45833 | J55: 45833
B56: Crossing Repairs | C56: 61052 | D56: Crossing Repairs | E56: Crossing Repairs | F56: Mcallen Signal and Boring | G56: 71725CLR | H56: 700 | I56: 45839 | J56: 45861
B57: Crossing Repairs | C57: 61052 | D57: Crossing Repairs | E57: Crossing Repairs | F57: Mcallen Signal and Boring | G57: 81425CLR | H57: 700 | I57: 45870 | J57: 45896
B58: Crossing Repairs | C58: 61052 | D58: Crossing Repairs | E58: Crossing Repairs | F58: Mcallen Signal and Boring | G58: 91125CLR | H58: 700 | I58: 45925 | J58: 45916
B59: Crossing Repairs | C59: 61052 | D59: Crossing Repairs | E59: Crossing Repairs | F59: Mcallen Signal and Boring | G59: 101425CLR | H59: 700 | I59: 45931 | J59: 45947
B60: Crossing Repairs | C60: 61052 | D60: Crossing Repairs | E60: Crossing Repairs | F60: Mcallen Signal and Boring | G60: 11425CLR | H60: 700 | I60: 45962 | J60: 45965
B61: Crossing Repairs | C61: 61052 | D61: Crossing Repairs | E61: Crossing Repairs | F61: Mcallen Signal and Boring | G61: 12325CLR | H61: 700 | I61: 46016 | J61: 46001
E63: Crossing Repairs Total | H63: =SUBTOTAL(9,H49:H62) -> 9164
B65: Landscape Maintenance | C65: 61056 | D65: Landscape Maintenance | E65: Landscape Maintenance | F65: Switch Yard Mowing | G65: 8005 | H65: 2500 | I65: 45925 | J65: 45902
B66: Landscape Maintenance | C66: 61056 | D66: Landscape Maintenance | E66: Landscape Maintenance | F66: Switch Yard Mowing | G66: 8009 | H66: 2500 | I66: 45925 | J66: 45930
B67: Landscape Maintenance | C67: 61056 | D67: Landscape Maintenance | E67: Landscape Maintenance | F67: Switch Yard Mowing | G67: 8013 | H67: 2500 | I67: 45931 | J67: 45961
B68: Landscape Maintenance | C68: 61056 | D68: Landscape Maintenance | E68: Landscape Maintenance | F68: Switch Yard Mowing | G68: 8017 | H68: 2500 | I68: 45962 | J68: 45991
B69: Landscape Maintenance | C69: 61056 | D69: Landscape Maintenance | E69: Landscape Maintenance | F69: Switch Yard Mowing | G69: 8021 | H69: 2500 | I69: 46016 | J69: 46022
E71: Landscape Maintenance Total | H71: =SUBTOTAL(9,H65:H70) -> 12500
B73: Utilities | C73: 61150 | D73: Utilities | E73: Utilities | F73: Entergy Services | G73: Jan_25 UBS CC Trx | H73: 113.89 | I73: 45682 | J73: 45688
B74: Utilities | C74: 61150 | D74: Utilities | E74: Utilities | F74: Live Oak Environmental | G74: Jan_25 UBS CC Trx | H74: 120.97 | I74: 45682 | J74: 45688
B75: Utilities | C75: 61150 | D75: Utilities | E75: Utilities | F75: Banyan Residential | G75: Feb_25 CC Exp | H75: 496.99 | I75: 45689 | J75: 45716
B76: Utilities | C76: 61150 | D76: Utilities | E76: Utilities | F76: Banyan Residential | G76: Apr_25 UBS CC Reimbursement | H76: 120.97 | I76: 45748 | J76: 45770
B77: Utilities | C77: 61150 | D77: Utilities | E77: Utilities | F77: Entergy Services, LLC | G77: Apr_2025 Bill Pay | H77: 113.15 | I77: 45748 | J77: 45770
B78: Utilities | C78: 61150 | D78: Utilities | E78: Utilities | F78: Entergy Services, LLC | G78: Apr_2025 Bill Pay | H78: 3451.19 | I78: 45748 | J78: 45771
B79: Utilities | C79: 61150 | D79: Utilities | E79: Utilities | F79: Banyan Residential | G79: May_25 UBS CC Reimbursement | H79: 120.97 | I79: 45802 | J79: 45784
B80: Utilities | C80: 61150 | D80: Utilities | E80: Utilities | F80: Banyan Residential | G80: June_25 UBS CC Reimbursement | H80: 367.1 | I80: 45833 | J80: 45838
B81: Utilities | C81: 61150 | D81: Utilities | E81: Utilities | F81: Entergy Services | G81: June 2025 Bill Pay | H81: 118.6 | I81: 45833 | J81: 45811
B82: Utilities | C82: 61150 | D82: Utilities | E82: Utilities | F82: Entergy Services | G82: July Bill Pay | H82: 238.46 | I82: 45839 | J82: 45848
B83: Utilities | C83: 61150 | D83: Utilities | E83: Utilities | F83: Entergy Services | G83: July Bill Pay | H83: 5516.43 | I83: 45839 | J83: 45848
B84: Utilities | C84: 61150 | D84: Utilities | E84: Utilities | F84: Entergy Services | G84: July Bill Pay | H84: 121.18 | I84: 45839 | J84: 45869
... B100: Utilities | C100: 61150 | D100: Utilities | E100: Utilities | F100: Banyan Residential | G100: Dec_25 UBS CC Reimb. | H100: 1184.69 | I100: 46016 | J100: 46022
E102: Utilities Total | H102: =SUBTOTAL(9,H73:H101) -> 36198.22
B104: Fuel | C104: 61164 | D104: Fuel | E104: Fuel | F104: Great Lakes Petroleum | G104: 2460529-IN | H104: 883.52 | I104: 45682 | J104: 45672
B105: Fuel | C105: 61164 | D105: Fuel | E105: Fuel | F105: Great Lakes Petroleum | G105: 09102025 | H105: 3701.52 | I105: 45925 | J105: 45910
B106: Fuel | C106: 61164 | D106: Fuel | E106: Fuel | F106: Great Lakes Petroleum | G106: 2698593-IN | H106: 1952.87 | I106: 46016 | J106: 45994
B107: Fuel | C107: 61164 | D107: Fuel | E107: Fuel | F107: Great Lakes Petroleum | G107: 2716338-IN | H107: 2016.44 | I107: 46016 | J107: 46022
E109: Fuel Total | H109: =SUBTOTAL(9,H104:H108) -> 8554.35
B111: Accounting Fees | C111: 63000 | D111: Accounting Fees | E111: Accounting | F111: CliftonLarsonAllen LLP | G111: L251010001 | H111: 4709.25 | I111: 45682 | J111: 45667
B112: Accounting Fees | C112: 63000 | D112: Accounting Fees | E112: Accounting | F112: CliftonLarsonAllen LLP | G112: L251077411 | H112: 6914.25 | I112: 45689 | J112: 45708
B113: Accounting Fees | C113: 63000 | D113: Accounting Fees | E113: Accounting | F113: CliftonLarsonAllen LLP | G113: L251127676 | H113: 8121.75 | I113: 45717 | J113: 45747
B114: Accounting Fees | C114: 63000 | D114: Accounting Fees | E114: Accounting | F114: Forvis Mazars | G114: 2427642 | H114: 4068.75 | I114: 45717 | J114: 45747
B115: Accounting Fees | C115: 63000 | D115: Accounting Fees | E115: Accounting | F115: CliftonLarsonAllen LLP | G115: L251199460 | H115: 4498.2 | I115: 45748 | J115: 45758
B116: Accounting Fees | C116: 63000 | D116: Accounting Fees | E116: Accounting | F116: CliftonLarsonAllen LLP | G116: L251128058 | H116: 1192 | I116: 45802 | J116: 45727
B117: Accounting Fees | C117: 63000 | D117: Accounting Fees | E117: Accounting | F117: CliftonLarsonAllen LLP | G117: L251307424 | H117: 8526.75 | I117: 45802 | J117: 45791
B118: Accounting Fees | C118: 63000 | D118: Accounting Fees | E118: Accounting | F118: CliftonLarsonAllen LLP | G118: L251307617 | H118: 149 | I118: 45802 | J118: 45792
B119: Accounting Fees | C119: 63000 | D119: Accounting Fees | E119: Accounting | F119: Forvis Mazars | G119: 2526026 | H119: 4068.75 | I119: 45802 | J119: 45783
B120: Accounting Fees | C120: 63000 | D120: Accounting Fees | E120: Accounting | F120: CliftonLarsonAllen LLP | G120: L251430364 | H120: 4901.25 | I120: 45839 | J120: 45859
B121: Accounting Fees | C121: 63000 | D121: Accounting Fees | E121: Accounting | F121: CliftonLarsonAllen LLP | G121: L251526216 | H121: 4941.43 | I121: 45870 | J121: 45897
E123: Accounting Fees Total | H123: =SUBTOTAL(9,H111:H122) -> 52091.38
B125: Professional Fees | C125: 63025 | D125: Professional Fees | E125: Professional Fees | F125: Banyan Residential | G125: Feb_25 CC Exp | H125: 253.33 | I125: 45689 | J125: 45716
B126: Professional Fees | C126: 63025 | D126: Professional Fees | E126: Professional Fees | F126: Banyan Residential | G126: June_25 UBS CC Reimbursement | H126: 58.69 | I126: 45833 | J126: 45838
B127: Professional Fees | C127: 63025 | D127: Professional Fees | E127: Professional Fees | F127: Banyan Residential | G127: Jul_25 UBS CC Reimb. | H127: 67.77 | I127: 45839 | J127: 45869
B128: Professional Fees | C128: 63025 | D128: Professional Fees | E128: Professional Fees | F128: Banyan Residential | G128: Jul_25 UBS CC Reimb. | H128: 999.99 | I128: 45870 | J128: 45900
B129: Professional Fees | C129: 63025 | D129: Professional Fees | E129: Professional Fees | F129: Banyan Residential | G129: Aug_25 UBS CC (Travel) | H129: 142.22 | I129: 45870 | J129: 45877
B130: Professional Fees | C130: 63025 | D130: Professional Fees | E130: Professional Fees | F130: Banyan Residential | G130: DMA, Inc. | H130: 2500 | I130: 45870 | J130: 45855
B131: Professional Fees | C131: 63025 | D131: Professional Fees | E131: Professional Fees | F131: Banyan Residential | G131: Aug_25 UBS CC 3 | H131: 115 | I131: 45925 | J131: 45901
B132: Professional Fees | C132: 63025 | D132: Professional Fees | E132: Professional Fees | F132: Banyan Residential | G132: Aug_25 UBS CC 3 | H132: 94.79 | I132: 45925 | J132: 45901
B133: Professional Fees | C133: 63025 | D133: Professional Fees | E133: Professional Fees | F133: Banyan Residential | G133: Sep_25 UBS CC | H133: 227.07 | I133: 45925 | J133: 45922
B134: Professional Fees | C134: 63025 | D134: Professional Fees | E134: Professional Fees | F134: CSRS | G134: 55515CLRF (Paid by County Line Rail Fund) | H134: 1960 | I134: 45931 | J134: 45961
B135: Professional Fees | C135: 63025 | D135: Professional Fees | E135: Professional Fees | F135: Hardin County | G135: 2510036 | H135: 425 | I135: 45962 | J135: 45979
B136: Professional Fees | C136: 63025 | D136: Professional Fees | E136: Professional Fees | F136: Banyan Residential | G136: Nov_25 UBS CC Reimb. | H136: 296.26 | I136: 45962 | J136: 45991
B137: Professional Fees | C137: 63025 | D137: Professional Fees | E137: Professional Fees | F137: Banyan Residential | G137: Dec_25 UBS CC Reimb. | H137: 1.25 | I137: 46016 | J137: 46022
E139: Professional Fees Total | H139: =SUBTOTAL(9,H125:H138) -> 7141.37
B141: Management Fees - Hall Logistics | C141: 63026 | D141: Management Fees - Hall Logistics | E141: Management Fees - Hall Logistics | F141: Hall Rail Logistics | G141: 2029 | H141: 2895.77 | I141: 45682 | J141: 45664
B142: Management Fees - Hall Logistics | C142: 63026 | D142: Management Fees - Hall Logistics | E142: Management Fees - Hall Logistics | F142: Hall Rail Logistics | G142: 2031 | H142: 2895.77 | I142: 45689 | J142: 45698
B143: Management Fees - Hall Logistics | C143: 63026 | D143: Management Fees - Hall Logistics | E143: Management Fees - Hall Logistics | F143: Hall Rail Logistics | G143: 2033 | H143: 2943.27 | I143: 45717 | J143: 45747
B144: Management Fees - Hall Logistics | C144: 63026 | D144: Management Fees - Hall Logistics | E144: Management Fees - Hall Logistics | F144: Hall Rail Logistics | G144: 2035 | H144: 3106.5 | I144: 45748 | J144: 45766
B145: Management Fees - Hall Logistics | C145: 63026 | D145: Management Fees - Hall Logistics | E145: Management Fees - Hall Logistics | F145: Hall Rail Logistics | G145: 2037 | H145: 8496.5 | I145: 45802 | J145: 45783
B146: Management Fees - Hall Logistics | C146: 63026 | D146: Management Fees - Hall Logistics | E146: Management Fees - Hall Logistics | F146: Hall Rail Logistics | G146: 2039 | H146: 8667.5 | I146: 45833 | J146: 45813
B147: Management Fees - Hall Logistics | C147: 63026 | D147: Management Fees - Hall Logistics | E147: Management Fees - Hall Logistics | F147: Hall Rail Logistics | G147: 2041 | H147: 8428.2 | I147: 45839 | J147: 45847
...

Sheet Bridge Approvd Budget to Actual
B1: PROJECT FUNDING REQUISITION
B2: Bishop Arts JV, LLC
B3: Application Period: 12/31/21
B4: Requisition: #14
D6: Bishop Arts | E6: Previous Contingency | F6: Current Contingency | G6: Bishop Arts | H6: Previous Application | I6: Payment this period | J6: Total Complete & Draw To Date | L6: Balance remaining
A7: Yardi Code | B7: COA# | C7: Account Name | D7: Approved JV Budget | E7: Funding & Reallocation | F7: Funding & Reallocation | G7: Current Approved Budget | H7: Inception to 11/30/21 | I7: 12/31/21 | J7: Incurred to 12/31/21 | K7: Percent Drawn | L7: As of 12/31/21
A9: 1470005 | B9: 11010 | C9: Land Purchase | D9: 5858494.4 | E9: 0 | F9: 0 | G9: 5858494.4 | H9: 5858494.4 | I9: 0 | J9: 5858494.4 | K9: 1 | L9: 0
A10: 1470900 | B10: 11050 | C10: Other Land Costs | D10: 200754.83 | E10: -49410.84 | F10: 0 | G10: 151343.99 | H10: 151343.99 | I10: 0 | J10: 151343.99 | K10: 1 | L10: 0
C11: Total Land Cost | D11: 6059249.2 | E11: -49410.84 | F11: 0 | G11: 6009838.4 | H11: 6009838.4 | I11: 0 | J11: 6009838.4 | K11: 1 | L11: 0
B12: 11110 | C12: Demolition | D12: 0 | E12: 0 | F12: 0 | G12: 0 | H12: 0 | I12: 0 | J12: 0 | L12: 0
B13: 11120 | C13: Offsite Utilities | D13: 0 | E13: 0 | F13: 0 | G13: 0 | H13: 0 | I13: 0 | J13: 0 | L13: 0
B14: 11130 | C14: Site Work | D14: 0 | E14: 0 | F14: 0 | G14: 0 | H14: 0 | I14: 0 | J14: 0 | L14: 0
A15: 1102605 | B15: 11140 | C15: Utilities Relocation | D15: 150000 | E15: 62251 | F15: 0 | G15: 212251 | H15: 62251.02 | I15: 0 | J15: 62251.02 | K15: 0.29328964 | L15: 149999.98
C16: Total Site Work | D16: 150000 | E16: 62251 | F16: 0 | G16: 212251 | H16: 62251.02 | I16: 0 | J16: 62251.02 | K16: 0.29328964 | L16: 149999.98
A17: 1279100 | B17: 11230 | C17: Other Construction Costs | D17: 400000 | E17: -310000 | F17: 0 | G17: 90000 | H17: 0 | I17: 0 | J17: 0 | K17: 0 | L17: 90000
B18: 11220 | C18: Garage Construction Costs | D18: 0 | E18: 0 | F18: 0 | G18: 0 | H18: 0 | I18: 0 | J18: 0 | K18: #DIV/0! | L18: 0
A19: 1101002 | B19: 11210 | C19: Base Construction Costs | D19: 38698021 | E19: 9300272 | F19: 0 | G19: 47998293 | H19: 0 | I19: 0 | J19: 0 | K19: 0 | L19: 47998293
B20: 11250 | C20: Retail Construction Costs/White Box | D20: 0 | E20: 0 | F20: 0 | G20: 0 | H20: 0 | I20: 0 | J20: 0 | K20: #DIV/0! | L20: 0
B21: 11240 | C21: Inflation | D21: 0 | E21: 0 | F21: 0 | G21: 0 | H21: 0 | I21: 0 | J21: 0 | K21: #DIV/0! | L21: 0
B22: 11310 | C22: Upgrades | D22: 0 | E22: 0 | F22: 0 | G22: 0 | H22: 0 | I22: 0 | J22: 0 | K22: #DIV/0! | L22: 0
B23: 11320 | C23: Landlord Tenant Improvements | D23: 0 | E23: 0 | F23: 0 | G23: 0 | H23: 0 | I23: 0 | J23: 0 | K23: #DIV/0! | L23: 0
B24: 11330 | C24: Commercial Tenant Improvements | D24: 0 | E24: 0 | F24: 0 | G24: 0 | H24: 0 | I24: 0 | J24: 0 | K24: #DIV/0! | L24: 0
B25: 11340 | C25: GMAX Contract Contingency | D25: 0 | E25: 0 | F25: 0 | G25: 0 | H25: 0 | I25: 0 | J25: 0 | K25: #DIV/0! | L25: 0
B26: 11350 | C26: Options and Selections | D26: 0 | E26: 0 | F26: 0 | G26: 0 | H26: 0 | I26: 0 | J26: 0 | K26: #DIV/0! | L26: 0
B27: 11410 | C27: Clubhouse | D27: 0 | E27: 0 | F27: 0 | G27: 0 | H27: 0 | I27: 0 | J27: 0 | K27: #DIV/0! | L27: 0
B28: 11420 | C28: Office | D28: 0 | E28: 0 | F28: 0 | G28: 0 | H28: 0 | I28: 0 | J28: 0 | K28: #DIV/0! | L28: 0
B29: 11430 | C29: Other Structures | D29: 0 | E29: 0 | F29: 0 | G29: 0 | H29: 0 | I29: 0 | J29: 0 | K29: #DIV/0! | L29: 0
B30: 11440 | C30: Other Amenities (Owner Wish List) | D30: 0 | E30: 0 | F30: 0 | G30: 0 | H30: 0 | I30: 0 | J30: 0 | K30: #DIV/0! | L30: 0
B31: 11450 | C31: Amenities | D31: 0 | E31: 0 | F31: 0 | G31: 0 | H31: 0 | I31: 0 | J31: 0 | K31: #DIV/0! | L31: 0
A32: 1279100 | B32: 11610 | C32: Model Furnishings | D32: 40000 | E32: -40000 | F32: 0 | G32: 0 | H32: 0 | I32: 0 | J32: 0 | K32: 0 | L32: 0
A33: 1279100 | B33: 11620 | C33: Common Area Furnishings | D33: 250000 | E33: 661505.77 | F33: 0 | G33: 911505.77 | H33: 0 | I33: 0 | J33: 0 | K33: 0 | L33: 911505.77
B34: 11630 | C34: Audio, Visual, and Security Equipment | D34: 0 | E34: 0 | F34: 0 | G34: 0 | H34: 0 | I34: 0 | J34: 0 | K34: #DIV/0! | L34: 0
B35: 11631 | C35: Televisions and Appliances | D35: 0 | E35: 0 | F35: 0 | G35: 0 | H35: 0 | I35: 0 | J35: 0 | K35: #DIV/0! | L35: 0
A36: 1279100 | B36: 11640 | C36: Fitness and Bicycle Equipment | D36: 105000 | E36: -39000 | F36: 0 | G36: 66000 | H36: 0 | I36: 0 | J36: 0 | K36: 0 | L36: 66000
A37: 1279100 | B37: 11650 | C37: Outdoor Furniture and Equipment | D37: 125000 | E37: -125000 | F37: 0 | G37: 0 | H37: 0 | I37: 0 | J37: 0 | K37: 0 | L37: 0
A38: 1279100 | B38: 11660 | C38: Office Furniture and Equipment | D38: 110000 | E38: -59809 | F38: 0 | G38: 50191 | H38: 0 | I38: 0 | J38: 0 | K38: 0 | L38: 50191
A39: 1279100 | B39: 11670 | C39: Maintenance Equipment | D39: 42500 | E39: -1300 | F39: 0 | G39: 41200 | H39: 0 | I39: 0 | J39: 0 | K39: 0 | L39: 41200
B40: 11680 | C40: Security Equipment | D40: 0 | E40: 0 | F40: 0 | G40: 0 | H40: 0 | I40: 0 | J40: 0 | K40: #DIV/0! | L40: 0
B41: 11690 | C41: Other FF&E | D41: 0 | E41: 0 | F41: 0 | G41: 0 | H41: 0 | I41: 0 | J41: 0 | K41: #DIV/0! | L41: 0
A42: 1144012 | B42: 13010 | C42: Hard Cost Contingency (Excludes Land) | D42: 1914611.1 | E42: 489803.9 | F42: 0 | G42: 2404415 | H42: 0 | I42: 0 | J42: 0 | K42: 0 | L42: 2404415
A43: 1284100 | B43: 13020 | C43: Soft Cost Contingency | D43: 282434.29 | E43: -20494.29 | F43: -13681.74 | G43: 248258.26 | H43: 0 | I43: 0 | J43: 0 | K43: 0 | L43: 248258.26
A44: 1284104 | C44: Working Capital | D44: 0 | E44: 150000 | F44: 0 | G44: 150000 | H44: 150000 | I44: 0 | J44: 150000 | K44: 1 | L44: 0
C45: Construction Costs | D45: 41967566 | E45: 10005978 | F45: -13681.74 | G45: 51959863 | H45: 150000 | I45: 0 | J45: 150000 | K45: 0.0028868436 | L45: 51809863
B46: 11810 | C46: Sanitary Charges | D46: 0 | E46: 0 | F46: 0 | G46: 0 | H46: 0 | I46: 0 | J46: 0 | L46: 0
B47: 11815 | C47: Water Charges | D47: 0 | E47: 0 | F47: 0 | G47: 0 | H47: 0 | I47: 0 | J47: 0 | L47: 0
A48: 1276100 | B48: 11820 | C48: Building Permits | D48: 150000 | E48: 0 | F48: 0 | G48: 150000 | H48: 98975.15 | I48: 17187.22 | J48: 116162.37 | K48: 0.7744158 | L48: 33837.63
A49: #N/A | B49: 11830 | C49: CO Fees | D49: 0 | E49: 0 | F49: 0 | G49: 0 | H49: 0 | I49: 0 | J49: 0 | L49: 0
B50: 11840 | C50: A&E Permit Fees | D50: 0 | E50: 0 | F50: 0 | G50: 0 | H50: 0 | I50: 0 | J50: 0 | L50: 0
B51: 11850 | C51: File & Review Fees | D51: 0 | E51: 0 | F51: 0 | G51: 0 | H51: 0 | I51: 0 | J51: 0 | L51: 0
B52: 11860 | C52: Tax Abatement | D52: 0 | E52: 0 | F52: 0 | G52: 0 | H52: 0 | I52: 0 | J52: 0 | L52: 0
B53: 11870 | C53: Zoning Variances Fees | D53: 0 | E53: 0 | F53: 0 | G53: 0 | H53: 0 | I53: 0 | J53: 0 | L53: 0
B54: 11880 | C54: Impact Fees - General | D54: 0 | E54: 0 | F54: 0 | G54: 0 | H54: 0 | I54: 0 | J54: 0 | L54: 0
B55: 11881 | C55: Impact Fees - Water | D55: 0 | E55: 0 | F55: 0 | G55: 0 | H55: 0 | I55: 0 | J55: 0 | L55: 0
B56: 11882 | C56: Impact Fees - Sewer | D56: 0 | E56: 0 | F56: 0 | G56: 0 | H56: 0 | I56: 0 | J56: 0 | L56: 0
B57: 11883 | C57: Impact Fees - Park | D57: 0 | E57: 0 | F57: 0 | G57: 0 | H57: 0 | I57: 0 | J57: 0 | L57: 0
B58: 11884 | C58: Impact Fees - Road | D58: 0 | E58: 0 | F58: 0 | G58: 0 | H58: 0 | I58: 0 | J58: 0 | L58: 0
B59: 11885 | C59: Impact Fees - School | D59: 0 | E59: 0 | F59: 0 | G59: 0 | H59: 0 | I59: 0 | J59: 0 | L59: 0
B60: 11886 | C60: Impact Fees - Other | D60: 0 | E60: 0 | F60: 0 | G60: 0 | H60: 0 | I60: 0 | J60: 0 | L60: 0
C61: Permits and Fees | D61: 150000 | E61: 0 | F61: 0 | G61: 150000 | H61: 98975.15 | I61: 17187.22 | J61: 116162.37 | K61: 0.7744158 | L61: 33837.63
B62: 11510 | C62: Owner's Representative | D62: 0 | E62: 0 | F62: 0 | G62: 0 | H62: 0 | I62: 0 | J62: 0 | L62: 0
B63: 11511 | C63: Construction Coordinator | D63: 0 | E63: 0 | F63: 0 | G63: 0 | H63: 0 | I63: 0 | J63: 0 | L63: 0
B64: 11512 | C64: Construction Trailer | D64: 0 | E64: 0 | F64: 0 | G64: 0 | H64: 0 | I64: 0 | J64: 0 | L64: 0
B65: 11513 | C65: Construction Manager | D65: 0 | E65: 0 | F65: 0 | G65: 0 | H65: 0 | I65: 0 | J65: 0 | L65: 0
B66: 11514 | C66: Other Salaries | D66: 0 | E66: 0 | F66: 0 | G66: 0 | H66: 0 | I66: 0 | J66: 0 | L66: 0
B67: 11520 | C67: Estimating Expenses | D67: 0 | E67: 0 | F67: 0 | G67: 0 | H67: 0 | I67: 0 | J67: 0 | L67: 0
B68: 11530 | C68: Office Expenses | D68: 0 | E68: 0 | F68: 0 | G68: 0 | H68: 0 | I68: 0 | J68: 0 | L68: 0
B69: 11540 | C69: Travel | D69: 0 | E69: 0 | F69: 0 | G69: 0 | H69: 0 | I69: 0 | J69: 0 | L69: 0
B70: 11505 | C70: Precon Fee | D70: 0 | E70: 0 | F70: 0 | G70: 0 | H70: 0 | I70: 0 | J70: 0 | L70: 0
A71: 1273509 | B71: 11506 | C71: Construction Management | D71: 540000 | E71: 94000 | F71: 0 | G71: 634000 | H71: 126000 | I71: 14000 | J71: 140000 | K71: 0.22082019 | L71: 494000
A72: #N/A | B72: 11710 | C72: Survey | D72: 0 | E72: 0 | F72: 0 | G72: 0 | H72: 0 | I72: 0 | J72: 0 | K72: #DIV/0! | L72: 0
B73: 11711 | C73: Title | D73: 0 | E73: 0 | F73: 0 | G73: 0 | H73: 0 | I73: 0 | J73: 0 | K73: #DIV/0! | L73: 0
B74: 11712 | C74: Geo-technical | D74: 0 | E74: 0 | F74: 0 | G74: 0 | H74: 0 | I74: 0 | J74: 0 | K74: #DIV/0! | L74: 0
B75: 11713 | C75: Environmental | D75: 0 | E75: 0 | F75: 0 | G75: 0 | H75: 0 | I75: 0 | J75: 0 | K75: #DIV/0! | L75: 0
B76: 11720 | C76: Market Study | D76: 0 | E76: 0 | F76: 0 | G76: 0 | H76: 0 | I76: 0 | J76: 0 | K76: #DIV/0! | L76: 0
B77: 11721 | C77: Traffic Study | D77: 0 | E77: 0 | F77: 0 | G77: 0 | H77: 0 | I77: 0 | J77: 0 | K77: #DIV/0! | L77: 0
A78: 1273508 | B78: 11730 | C78: Inspections | D78: 110000 | E78: 0 | F78: 0 | G78: 110000 | H78: 0 | I78: 0 | J78: 0 | K78: 0 | L78: 110000
B79: 11740 | C79: Travel | D79: 0 | E79: 0 | F79: 0 | G79: 0 | H79: 0 | I79: 0 | J79: 0 | K79: #DIV/0! | L79: 0
B80: 11750 | C80: Meals & Entertainment | D80: 0 | E80: 0 | F80: 0 | G80: 0 | H80: 0 | I80: 0 | J80: 0 | K80: #DIV/0! | L80: 0
A81: 1273156 | B81: 11760 | C81: Other Due Diligence | D81: 168137.73 | E81: 126797.27 | F81: 0 | G81: 294935 | H81: 68943.64 | I81: -5084 | J81: 63859.64 | K81: 0.21652106 | L81: 231075.36
A82: #N/A | B82: 11910 | C82: Easement | D82: 0 | E82: 0 | F82: 0 | G82: 0 | H82: 0 | I82: 0 | J82: 0 | K82: #DIV/0! | L82: 0
B83: 11911 | C83: Purchase Agreement | D83: 0 | E83: 0 | F83: 0 | G83: 0 | H83: 0 | I83: 0 | J83: 0 | K83: #DIV/0! | L83: 0
B84: 11912 | C84: Zoning & Appro. | D84: 0 | E84: 0 | F84: 0 | G84: 0 | H84: 0 | I84: 0 | J84: 0 | K84: #DIV/0! | L84: 0
B85: 11913 | C85: Applications & Permits | D85: 0 | E85: 0 | F85: 0 | G85: 0 | H85: 0 | I85: 0 | J85: 0 | K85: #DIV/0! | L85: 0
B86: 11914 | C86: Corporate Set Up | D86: 0 | E86: 0 | F86: 0 | G86: 0 | H86: 0 | I86: 0 | J86: 0 | K86: #DIV/0! | L86: 0
B87: 11915 | C87: Litigation | D87: 0 | E87: 0 | F87: 0 | G87: 0 | H87: 0 | I87: 0 | J87: 0 | K87: #DIV/0! | L87: 0
B88: 11920 | C88: Professional Services | D88: 0 | E88: 0 | F88: 0 | G88: 0 | H88: 0 | I88: 0 | J88: 0 | K88: #DIV/0! | L88: 0
B89: 11930 | C89: HPR Documents | D89: 0 | E89: 0 | F89: 0 | G89: 0 | H89: 0 | I89: 0 | J89: 0 | K89: #DIV/0! | L89: 0
B90: 11940 | C90: Tenant Leasing | D90: 0 | E90: 0 | F90: 0 | G90: 0 | H90: 0 | I90: 0 | J90: 0 | K90: #DIV/0! | L90: 0
B91: 11945 | C91: Public Financing | D91: 0 | E91: 0 | F91: 0 | G91: 0 | H91: 0 | I91: 0 | J91: 0 | K91: #DIV/0! | L91: 0
B92: 11946 | C92: TIF Financing-City | D92: 0 | E92: 0 | F92: 0 | G92: 0 | H92: 0 | I92: 0 | J92: 0 | K92: #DIV/0! | L92: 0
B93: 11947 | C93: TIF Financing-Owner | D93: 0 | E93: 0 | F93: 0 | G93: 0 | H93: 0 | I93: 0 | J93: 0 | K93: #DIV/0! | L93: 0
B94: 11950 | C94: Debt Financing | D94: 0 | E94: 0 | F94: 0 | G94: 0 | H94: 0 | I94: 0 | J94: 0 | K94: #DIV/0! | L94: 0
... B99: 11960 | C99: Sales & Marketing | D99: 0 | E99: 0 | F99: 0 | G99: 0 | H99: 0 | I99: 0 | J99: 0 | K99: #DIV/0! | L99: 0
A100: 1280100 | B100: 11970 | C100: Other Legal | D100: 150000 | E100: 115000 | F100: 4999 | G100: 269999 | H100: 109277.13 | I100: 123102.34 | J100: 232379.47 | K100: 0.86066789 | L100: 37619.53
A101: #N/A | B101: 12010 | C101: Construction Coordination | D101: 0 | E101: 0 | F101: 0 | G101: 0 | H101: 0 | I101: 0 | J101: 0 | K101: #DIV/0! | L101: 0
B102: 12011 | C102: Platting | D102: 0 | E102: 0 | F102: 0 | G102: 0 | H102: 0 | I102: 0 | J102: 0 | K102: #DIV/0! | L102: 0
B103: 12012 | C103: Conceptual Planning | D103: 0 | E103: 0 | F103: 0 | G103: 0 | H103: 0 | I103: 0 | J103: 0 | K103: #DIV/0! | L103: 0
A104: 1272200 | B104: 12013 | C104: Civil Engineering Plans | D104: 287506.73 | E104: 174746.27 | F104: 13681.74 | G104: 475934.74 | H104: 461588.86 | I104: 14345.88 | J104: 475934.74 | K104: 1 | L104: 0
A105: #N/A | B105: 12014 | C105: Condominium Docs | D105: 0 | E105: 0 | F105: 0 | G105: 0 | H105: 0 | I105: 0 | J105: 0 | K105: #DIV/0! | L105: 0
B106: 12015 | C106: Feasibility/Testing | D106: 0 | E106: 0 | F106: 0 | G106: 0 | H106: 0 | I106: 0 | J106: 0 | K106: #DIV/0! | L106: 0
...

Sheet Budget to Actual (2)
A1: PROJECT FUNDING REQUISITION
A2: ='Budget to Actual P1'!#REF! -> #REF!
A3: ='Budget to Actual P1'!B4 -> 46203
A4: ='Budget to Actual P1'!A5 -> 0
C6: Bishop Arts | D6: Previous Contingency | E6: Current Contingency | F6: Bishop Arts | G6: Previous Application | H6: Payment this period | I6: Total Complete & Draw To Date | K6: Balance remaining
A7: COA# | B7: Account Name | C7: Approved JVA Budget | D7: Funding & Reallocation | E7: Funding & Reallocation | F7: Current Approved Budget | G7: Inception to 6/30/2022 | H7: 7/31/2022 | I7: Incurred to 7/31/2022 | J7: Percent Drawn | K7: As of 7/31/2022
A9: 11010 | B9: Land Purchase | C9: 5858494.4 | D9: 0 | E9: 0 | F9: 5858494.4 | G9: 5858494.4 | H9: 0 | I9: 5858494.4 | J9: 1 | K9: 0
A10: 11050 | B10: Other Land Costs | C10: 200754.83 | D10: -49410.84 | E10: 0 | F10: 151343.99 | G10: 151343.99 | H10: 0 | I10: 151343.99 | J10: 1 | K10: 0
B11: Total Land Cost | C11: 6059249.2 | D11: -49410.84 | E11: 0 | F11: 6009838.4 | G11: 6009838.4 | H11: 0 | I11: 6009838.4 | J11: 1 | K11: 0
A12: 11110 | B12: Demolition | C12: 0 | D12: 0 | E12: 0 | F12: 0 | G12: 0 | H12: 0 | I12: 0 | K12: 0
A13: 11120 | B13: Offsite Utilities | C13: 0 | D13: 0 | E13: 0 | F13: 0 | G13: 0 | H13: 0 | I13: 0 | K13: 0
A14: 11130 | B14: Site Work | C14: 0 | D14: 0 | E14: 0 | F14: 0 | G14: 0 | H14: 0 | I14: 0 | K14: 0
A15: 11140 | B15: Utilities Relocation | C15: 150000 | D15: 62251 | E15: 0 | F15: 212251 | G15: 62251.02 | H15: 0 | I15: 62251.02 | J15: 0.29328964 | K15: 149999.98
B16: Total Site Work | C16: 150000 | D16: 62251 | E16: 0 | F16: 212251 | G16: 62251.02 | H16: 0 | I16: 62251.02 | J16: 0.29328964 | K16: 149999.98
A17: 11230 | B17: Other Construction Costs | C17: 400000 | D17: -310000 | E17: 0 | F17: 90000 | G17: 0 | H17: 0 | I17: 0 | J17: 0 | K17: 90000
A18: 11220 | B18: Garage Construction Costs | C18: 0 | D18: 0 | E18: 0 | F18: 0 | G18: 0 | H18: 0 | I18: 0 | J18: #DIV/0! | K18: 0
A19: 11210 | B19: Base Construction Costs | C19: 38698021 | D19: 9454867.4 | E19: 0 | F19: 48152888 | G19: 6814171.3 | H19: 505411.87 | I19: 7319583.1 | J19: 0.15200715 | K19: 40833305
A20: 11250 | B20: Retail Construction Costs/White Box | C20: 0 | D20: 0 | E20: 0 | F20: 0 | G20: 0 | H20: 0 | I20: 0 | J20: #DIV/0! | K20: 0
A21: 11240 | B21: Inflation | C21: 0 | D21: 0 | E21: 0 | F21: 0 | G21: 0 | H21: 0 | I21: 0 | J21: #DIV/0! | K21: 0
A22: 11310 | B22: Upgrades | C22: 0 | D22: 0 | E22: 0 | F22: 0 | G22: 0 | H22: 0 | I22: 0 | J22: #DIV/0! | K22: 0
A23: 11320 | B23: Landlord Tenant Improvements | C23: 0 | D23: 0 | E23: 0 | F23: 0 | G23: 0 | H23: 0 | I23: 0 | J23: #DIV/0! | K23: 0
A24: 11330 | B24: Commercial Tenant Improvements | C24: 0 | D24: 0 | E24: 0 | F24: 0 | G24: 0 | H24: 0 | I24: 0 | J24: #DIV/0! | K24: 0
A25: 11340 | B25: GMAX Contract Contingency | C25: 0 | D25: 0 | E25: 0 | F25: 0 | G25: 0 | H25: 0 | I25: 0 | J25: #DIV/0! | K25: 0
A26: 11350 | B26: Options and Selections | C26: 0 | D26: 0 | E26: 0 | F26: 0 | G26: 0 | H26: 0 | I26: 0 | J26: #DIV/0! | K26: 0
A27: 11410 | B27: Clubhouse | C27: 0 | D27: 0 | E27: 0 | F27: 0 | G27: 0 | H27: 0 | I27: 0 | J27: #DIV/0! | K27: 0
A28: 11420 | B28: Office | C28: 0 | D28: 0 | E28: 0 | F28: 0 | G28: 0 | H28: 0 | I28: 0 | J28: #DIV/0! | K28: 0
A29: 11430 | B29: Other Structures | C29: 0 | D29: 0 | E29: 0 | F29: 0 | G29: 0 | H29: 0 | I29: 0 | J29: #DIV/0! | K29: 0
A30: 11440 | B30: Other Amenities (Owner Wish List) | C30: 0 | D30: 0 | E30: 0 | F30: 0 | G30: 0 | H30: 0 | I30: 0 | J30: #DIV/0! | K30: 0
A31: 11450 | B31: Amenities | C31: 0 | D31: 0 | E31: 0 | F31: 0 | G31: 0 | H31: 0 | I31: 0 | J31: #DIV/0! | K31: 0
A32: 11610 | B32: Model Furnishings | C32: 40000 | D32: -40000 | E32: 0 | F32: 0 | G32: 0 | H32: 0 | I32: 0 | J32: 0 | K32: 0
A33: 11620 | B33: Common Area Furnishings | C33: 250000 | D33: 661505.77 | E33: 0 | F33: 911505.77 | G33: 0 | H33: 0 | I33: 0 | J33: 0 | K33: 911505.77
A34: 11630 | B34: Audio, Visual, and Security Equipment | C34: 0 | D34: 0 | E34: 0 | F34: 0 | G34: 0 | H34: 0 | I34: 0 | J34: #DIV/0! | K34: 0
A35: 11631 | B35: Televisions and Appliances | C35: 0 | D35: 0 | E35: 0 | F35: 0 | G35: 0 | H35: 0 | I35: 0 | J35: #DIV/0! | K35: 0
A36: 11640 | B36: Fitness and Bicycle Equipment | C36: 105000 | D36: -39000 | E36: 0 | F36: 66000 | G36: 32330.93 | H36: 0 | I36: 32330.93 | J36: 0.48986258 | K36: 33669.07
A37: 11650 | B37: Outdoor Furniture and Equipment | C37: 125000 | D37: -125000 | E37: 0 | F37: 0 | G37: 0 | H37: 0 | I37: 0 | J37: 0 | K37: 0
A38: 11660 | B38: Office Furniture and Equipment | C38: 110000 | D38: -59809 | E38: 0 | F38: 50191 | G38: 0 | H38: 0 | I38: 0 | J38: 0 | K38: 50191
A39: 11670 | B39: Maintenance Equipment | C39: 42500 | D39: -1300 | E39: 0 | F39: 41200 | G39: 0 | H39: 0 | I39: 0 | J39: 0 | K39: 41200
A40: 11680 | B40: Security Equipment | C40: 0 | D40: 0 | E40: 0 | F40: 0 | G40: 0 | H40: 0 | I40: 0 | J40: #DIV/0! | K40: 0
A41: 11690 | B41: Other FF&E | C41: 0 | D41: 0 | E41: 0 | F41: 0 | G41: 0 | H41: 0 | I41: 0 | J41: #DIV/0! | K41: 0
A42: 13010 | B42: Hard Cost Contingency (Excludes Land) | C42: 1914611.1 | D42: 335208.48 | E42: 0 | F42: 2249819.6 | G42: 0 | H42: 0 | I42: 0 | J42: 0 | K42: 2249819.6
A43: 13020 | B43: Soft Cost Contingency | C43: 282434.29 | D43: -121013.02 | E43: -2438.18 | F43: 158983.09 | G43: 0 | H43: 0 | I43: 0 | J43: 0 | K43: 158983.09
B44: Working Capital | C44: 0 | D44: 150000 | E44: 0 | F44: 150000 | G44: 150000 | H44: 0 | I44: 150000 | J44: 1 | K44: 0
B45: Construction Costs | C45: 41967566 | D45: 9905459.6 | E45: -2438.18 | F45: 51870588 | G45: 6996502.2 | H45: 505411.87 | I45: 7501914.1 | J45: 0.14462751 | K45: 44368674
A46: 11810 | B46: Sanitary Charges | C46: 0 | D46: 0 | E46: 0 | F46: 0 | G46: 0 | H46: 0 | I46: 0 | K46: 0
A47: 11815 | B47: Water Charges | C47: 0 | D47: 0 | E47: 0 | F47: 0 | G47: 0 | H47: 0 | I47: 0 | K47: 0
A48: 11820 | B48: Building Permits | C48: 150000 | D48: 0 | E48: 0 | F48: 150000 | G48: 134442.37 | H48: 0 | I48: 134442.37 | J48: 0.89628247 | K48: 15557.63
A49: 11830 | B49: CO Fees | C49: 0 | D49: 0 | E49: 0 | F49: 0 | G49: 0 | H49: 0 | I49: 0 | K49: 0
A50: 11840 | B50: A&E Permit Fees | C50: 0 | D50: 0 | E50: 0 | F50: 0 | G50: 0 | H50: 0 | I50: 0 | K50: 0
A51: 11850 | B51: File & Review Fees | C51: 0 | D51: 0 | E51: 0 | F51: 0 | G51: 0 | H51: 0 | I51: 0 | K51: 0
A52: 11860 | B52: Tax Abatement | C52: 0 | D52: 0 | E52: 0 | F52: 0 | G52: 0 | H52: 0 | I52: 0 | K52: 0
A53: 11870 | B53: Zoning Variances Fees | C53: 0 | D53: 0 | E53: 0 | F53: 0 | G53: 0 | H53: 0 | I53: 0 | K53: 0
A54: 11880 | B54: Impact Fees - General | C54: 0 | D54: 0 | E54: 0 | F54: 0 | G54: 0 | H54: 0 | I54: 0 | K54: 0
A55: 11881 | B55: Impact Fees - Water | C55: 0 | D55: 0 | E55: 0 | F55: 0 | G55: 0 | H55: 0 | I55: 0 | K55: 0
A56: 11882 | B56: Impact Fees - Sewer | C56: 0 | D56: 0 | E56: 0 | F56: 0 | G56: 0 | H56: 0 | I56: 0 | K56: 0
A57: 11883 | B57: Impact Fees - Park | C57: 0 | D57: 0 | E57: 0 | F57: 0 | G57: 0 | H57: 0 | I57: 0 | K57: 0
A58: 11884 | B58: Impact Fees - Road | C58: 0 | D58: 0 | E58: 0 | F58: 0 | G58: 0 | H58: 0 | I58: 0 | K58: 0
A59: 11885 | B59: Impact Fees - School | C59: 0 | D59: 0 | E59: 0 | F59: 0 | G59: 0 | H59: 0 | I59: 0 | K59: 0
A60: 11886 | B60: Impact Fees - Other | C60: 0 | D60: 0 | E60: 0 | F60: 0 | G60: 0 | H60: 0 | I60: 0 | K60: 0
B61: Permits and Fees | C61: 150000 | D61: 0 | E61: 0 | F61: 150000 | G61: 134442.37 | H61: 0 | I61: 134442.37 | J61: 0.89628247 | K61: 15557.63
A62: 11510 | B62: Owner's Representative | C62: 0 | D62: 0 | E62: 0 | F62: 0 | G62: 0 | H62: 0 | I62: 0 | K62: 0
A63: 11511 | B63: Construction Coordinator | C63: 0 | D63: 0 | E63: 0 | F63: 0 | G63: 0 | H63: 0 | I63: 0 | K63: 0
A64: 11512 | B64: Construction Trailer | C64: 0 | D64: 0 | E64: 0 | F64: 0 | G64: 0 | H64: 0 | I64: 0 | K64: 0
A65: 11513 | B65: Construction Manager | C65: 0 | D65: 0 | E65: 0 | F65: 0 | G65: 0 | H65: 0 | I65: 0 | K65: 0
A66: 11514 | B66: Other Salaries | C66: 0 | D66: 0 | E66: 0 | F66: 0 | G66: 0 | H66: 0 | I66: 0 | K66: 0
A67: 11520 | B67: Estimating Expenses | C67: 0 | D67: 0 | E67: 0 | F67: 0 | G67: 0 | H67: 0 | I67: 0 | K67: 0
A68: 11530 | B68: Office Expenses | C68: 0 | D68: 0 | E68: 0 | F68: 0 | G68: 0 | H68: 0 | I68: 0 | K68: 0
A69: 11540 | B69: Travel | C69: 0 | D69: 0 | E69: 0 | F69: 0 | G69: 0 | H69: 0 | I69: 0 | K69: 0
A70: 11505 | B70: Precon Fee | C70: 0 | D70: 0 | E70: 0 | F70: 0 | G70: 0 | H70: 0 | I70: 0 | K70: 0
A71: 11506 | B71: Construction Management | C71: 540000 | D71: 94000 | E71: 0 | F71: 634000 | G71: 260000 | H71: 20000 | I71: 280000 | J71: 0.44164038 | K71: 354000
A72: 11710 | B72: Survey | C72: 0 | D72: 0 | E72: 0 | F72: 0 | G72: 0 | H72: 0 | I72: 0 | J72: #DIV/0! | K72: 0
A73: 11711 | B73: Title | C73: 0 | D73: 0 | E73: 0 | F73: 0 | G73: 0 | H73: 0 | I73: 0 | J73: #DIV/0! | K73: 0
A74: 11712 | B74: Geo-technical | C74: 0 | D74: 0 | E74: 0 | F74: 0 | G74: 0 | H74: 0 | I74: 0 | J74: #DIV/0! | K74: 0
A75: 11713 | B75: Environmental | C75: 0 | D75: 0 | E75: 0 | F75: 0 | G75: 0 | H75: 0 | I75: 0 | J75: #DIV/0! | K75: 0
A76: 11720 | B76: Market Study | C76: 0 | D76: 0 | E76: 0 | F76: 0 | G76: 0 | H76: 0 | I76: 0 | J76: #DIV/0! | K76: 0
A77: 11721 | B77: Traffic Study | C77: 0 | D77: 0 | E77: 0 | F77: 0 | G77: 0 | H77: 0 | I77: 0 | J77: #DIV/0! | K77: 0
A78: 11730 | B78: Inspections | C78: 110000 | D78: 0 | E78: 0 | F78: 110000 | G78: 29050 | H78: 0 | I78: 29050 | J78: 0.26409091 | K78: 80950
A79: 11740 | B79: Travel | C79: 0 | D79: 0 | E79: 0 | F79: 0 | G79: 0 | H79: 0 | I79: 0 | J79: #DIV/0! | K79: 0
A80: 11750 | B80: Meals & Entertainment | C80: 0 | D80: 0 | E80: 0 | F80: 0 | G80: 0 | H80: 0 | I80: 0 | J80: #DIV/0! | K80: 0
A81: 11760 | B81: Other Due Diligence | C81: 168137.73 | D81: 126797.27 | E81: 0 | F81: 294935 | G81: 117436.63 | H81: 4620.63 | I81: 122057.26 | J81: 0.41384461 | K81: 172877.74
A82: 11910 | B82: Easement | C82: 0 | D82: 0 | E82: 0 | F82: 0 | G82: 0 | H82: 0 | I82: 0 | J82: #DIV/0! | K82: 0
A83: 11911 | B83: Purchase Agreement | C83: 0 | D83: 0 | E83: 0 | F83: 0 | G83: 0 | H83: 0 | I83: 0 | J83: #DIV/0! | K83: 0
A84: 11912 | B84: Zoning & Appro. | C84: 0 | D84: 0 | E84: 0 | F84: 0 | G84: 0 | H84: 0 | I84: 0 | J84: #DIV/0! | K84: 0
A85: 11913 | B85: Applications & Permits | C85: 0 | D85: 0 | E85: 0 | F85: 0 | G85: 0 | H85: 0 | I85: 0 | J85: #DIV/0! | K85: 0
A86: 11914 | B86: Corporate Set Up | C86: 0 | D86: 0 | E86: 0 | F86: 0 | G86: 0 | H86: 0 | I86: 0 | J86: #DIV/0! | K86: 0
A87: 11915 | B87: Litigation | C87: 0 | D87: 0 | E87: 0 | F87: 0 | G87: 0 | H87: 0 | I87: 0 | J87: #DIV/0! | K87: 0
A88: 11920 | B88: Professional Services | C88: 0 | D88: 0 | E88: 0 | F88: 0 | G88: 0 | H88: 0 | I88: 0 | J88: #DIV/0! | K88: 0
A89: 11930 | B89: HPR Documents | C89: 0 | D89: 0 | E89: 0 | F89: 0 | G89: 0 | H89: 0 | I89: 0 | J89: #DIV/0! | K89: 0
A90: 11940 | B90: Tenant Leasing | C90: 0 | D90: 0 | E90: 0 | F90: 0 | G90: 0 | H90: 0 | I90: 0 | J90: #DIV/0! | K90: 0
A91: 11945 | B91: Public Financing | C91: 0 | D91: 0 | E91: 0 | F91: 0 | G91: 0 | H91: 0 | I91: 0 | J91: #DIV/0! | K91: 0
A92: 11946 | B92: TIF Financing-City | C92: 0 | D92: 0 | E92: 0 | F92: 0 | G92: 0 | H92: 0 | I92: 0 | J92: #DIV/0! | K92: 0
A93: 11947 | B93: TIF Financing-Owner | C93: 0 | D93: 0 | E93: 0 | F93: 0 | G93: 0 | H93: 0 | I93: 0 | J93: #DIV/0! | K93: 0
... A99: 11960 | B99: Sales & Marketing | C99: 0 | D99: 0 | E99: 0 | F99: 0 | G99: 0 | H99: 0 | I99: 0 | J99: #DIV/0! | K99: 0
A100: 11970 | B100: Other Legal | C100: 150000 | D100: 119999 | E100: 0 | F100: 269999 | G100: 245310.03 | H100: 3463.5 | I100: 248773.53 | J100: 0.92138686 | K100: 21225.47
A101: 12010 | B101: Construction Coordination | C101: 0 | D101: 0 | E101: 0 | F101: 0 | G101: 0 | H101: 0 | I101: 0 | J101: #DIV/0! | K101: 0
A102: 12011 | B102: Platting | C102: 0 | D102: 0 | E102: 0 | F102: 0 | G102: 0 | H102: 0 | I102: 0 | J102: #DIV/0! | K102: 0
A103: 12012 | B103: Conceptual Planning | C103: 0 | D103: 0 | E103: 0 | F103: 0 | G103: 0 | H103: 0 | I103: 0 | J103: #DIV/0! | K103: 0
A104: 12013 | B104: Civil Engineering Plans | C104: 287506.73 | D104: 257537.76 | E104: 2438.18 | F104: 547482.67 | G104: 545044.49 | H104: 2438.18 | I104: 547482.67 | J104: 1 | K104: 0
A105: 12014 | B105: Condominium Docs | C105: 0 | D105: 0 | E105: 0 | F105: 0 | G105: 0 | H105: 0 | I105: 0 | J105: #DIV/0! | K105: 0
A106: 12015 | B106: Feasibility/Testing | C106: 0 | D106: 0 | E106: 0 | F106: 0 | G106: 0 | H106: 0 | I106: 0 | J106: #DIV/0! | K106: 0
A107: 12018 | B107: Landscape Plan | C107: 0 | D107: 0 | E107: 0 | F107: 0 | G107: 0 | H107: 0 | I107: 0 | J107: #DIV/0! | K107: 0
...
